Workbook

Sheet Cover
B2: ASSESSMENT OF DRILLING AND GROUND SUPPORT
B3: CONSUMABLE COSTS FOR UNDERGROUND DEVELOPMENT
B4: Navachab Gold Mine Project, Byrnecut. May to August 2026.
B6: STUDY DETAILS
B7: Researcher | C7: Irene Zinyetu Kavhura, student number 221315594
B8: Programme | C8: BSc Honours in Mining Engineering, University of Namibia
B9: Department | C9: Civil and Mining Engineering
B10: Supervisor | C10: Mr. Nekwaya Tuyeni Kelao
B11: Development contractor | C11: Byrnecut
B12: Analysis period | C12: May, June, July and August 2026
B13: Currency | C13: United States dollars, converted at the rate on the Inputs sheet
B15: WHERE EACH OBJECTIVE IS ANSWERED
B16: Objective | C16: Sheet | E16: Status
B17: Objective 1: drilling consumable unit cost per metre | C17: Unit_Cost section 2, C_Face_Drilling | E17: Complete. Reported per metre advanced and per drilled metre.
B18: Objective 2: ground support unit cost per metre, and the main cost drivers | C18: Unit_Cost section 1, Pareto | E18: Complete.
B19: Objective 3: development productivity baseline | C19: Advance section 2, DRM | E19: Complete. Metres per month and per heading, and drilled metres per advance metre.
B20: Objective 4: advance rate against total unit cost | C20: Unit_Cost sections 3 to 5 | E20: Complete. Equation 4 separates the consumption effect from the advance effect.
B21: Analysis by heading and by portal | C21: Portal_Analysis | E21: Complete. All four months, with reconciliation checks.
B22: Design compliance and over consumption | C22: Plan_vs_Actual | E22: Complete for bolts, split sets and mesh against the GSS standards.
B24: CONTENTS
B25: Equations | C25: Every equation used, with its symbols defined
B26: Inputs | C26: Unit costs, exchange rate, design standards, portal split bases
B27: Advance | C27: Survey advance as recorded, and monthly totals
B28: Consumption_PL | C28: Stock counts as recorded, with consumption derived
B29: A_Scaling | C29: Scaling consumables
B30: B_Ground_Support | C30: Bolts, bearing plates and mesh
B31: C_Face_Drilling | C31: Shanks, bits, rods, couplings, centralisers, dollies
B32: D_Cable_Bolting | C32: Cable bolts and hardware
B33: DRM | C33: Drilled metres, and bit life for the 43 mm and 48 mm bits
B34: Plan_vs_Actual | C34: Design quantity against actual, by ground class
B35: Unit_Cost | C35: Equations 1 to 4, and why the unit cost moved
B36: Portal_Analysis | C36: Heading and portal results, with reconciliation checks
... B44: How_to_Read | C44: Symbols, formats and the numbered notes
B46: READING THE WORKBOOK
B47: Blue figures | C47: Entered from a source document
B48: Green figures | C48: Drawn from another sheet
B49: Black figures | C49: Calculated
B50: x | C50: No unit price exists in the source data. Never treated as zero.
B51: - | C51: Cost already carried by another line
B52: ( ) | C52: A negative figure, in the accounting convention
B53: Shaded cells | C53: Awaiting data, listed on the Anomalies sheet

Sheet Dashboard
B2: DASHBOARD
B3: Whole underground mine, May to August 2026.
B6: 1 HEADLINE
B7: Measure | C7: Unit | E7: May | F7: June | G7: July | H7: August | J7: Period
B8: Development advance | C8: m | E8: =Advance!E53 -> 270.436 | F8: =Advance!F53 -> 316.617 | G8: =Advance!G53 -> 397.798 | H8: =Advance!H53 -> 390.967 | J8: =Advance!H53 -> 390.967
B9: Ground support consumable cost | C9: US$ | E9: =Unit_Cost!E13 -> 377506.07 | F9: =Unit_Cost!F13 -> 298939.35 | G9: =Unit_Cost!G13 -> 385623.4 | H9: =Unit_Cost!H13 -> 327302.19 | J9: =Unit_Cost!H13 -> 327302.19
B10: Drilling consumable cost | C10: US$ | E10: =Unit_Cost!E24 -> 175938.32 | F10: =Unit_Cost!F24 -> 164342.43 | G10: =Unit_Cost!G24 -> 350729.41 | H10: =Unit_Cost!H24 -> 294906.06 | J10: =Unit_Cost!H24 -> 294906.06
B11: Total consumable cost | C11: US$ | E11: =Unit_Cost!E13+Unit_Cost!E24 -> 553444.39 | F11: =Unit_Cost!F13+Unit_Cost!F24 -> 463281.78 | G11: =Unit_Cost!G13+Unit_Cost!G24 -> 736352.81 | H11: =Unit_Cost!H13+Unit_Cost!H24 -> 622208.25 | J11: =Unit_Cost!H13+Unit_Cost!H24 -> 622208.25
B12: Total drilled metres | C12: drilled m | E12: =DRM!E26 -> 29381.1 | F12: =DRM!F26 -> 33867 | G12: =DRM!G26 -> 49347.6 | H12: =DRM!H26 -> 42289.6 | J12: =DRM!H26 -> 42289.6
B13: Consumable cost per metre advanced | C13: US$/m | E13: =IF(E8=0,0,E11/E8) -> 2046.4893 | F13: =IF(F8=0,0,F11/F8) -> 1463.2246 | G13: =IF(G8=0,0,G11/G8) -> 1851.0722 | H13: =IF(H8=0,0,H11/H8) -> 1591.4598 | J13: =IF(J8=0,0,J11/J8) -> 1591.4598
B14: Consumable cost per drilled metre | C14: US$/drilled m | E14: =IF(E12=0,0,E11/E12) -> 18.836748 | F14: =IF(F12=0,0,F11/F12) -> 13.679445 | G14: =IF(G12=0,0,G11/G12) -> 14.921755 | H14: =IF(H12=0,0,H11/H12) -> 14.713032 | J14: =IF(J12=0,0,J11/J12) -> 14.713032
B15: Drilled metres per metre advanced | C15: ratio | E15: =IF(E8=0,0,E12/E8) -> 108.64345 | F15: =IF(F8=0,0,F12/F8) -> 106.9652 | G15: =IF(G8=0,0,G12/G8) -> 124.05191 | H15: =IF(H8=0,0,H12/H8) -> 108.16667 | J15: =IF(J8=0,0,J12/J8) -> 108.16667
B17: 2 PORTAL AND GROUND CLASS
B18: Portal | C18: Ground | E18: Metres, period | F18: Share of metres | J18: Ground support cost per metre
B19: Northern Portal | C19: All fair to poor, GSS_02 and GSS_03 | E19: =Portal_Analysis!E41 -> 756.39 | F19: =IF(Portal_Analysis!G41=0,0,E19/Portal_Analysis!G41) -> 0.54977475 | J19: =Portal_Analysis!E53 -> 1036.7869
B20: Southern Portal | C20: All good, GSS_01 | E20: =Portal_Analysis!F41 -> 619.428 | F20: =IF(Portal_Analysis!G41=0,0,E20/Portal_Analysis!G41) -> 0.45022525 | J20: =Portal_Analysis!F53 -> 976.95906
B22: Portal and ground class coincide exactly in this data, so the two cannot be separated statistically.
B24: 3 WHERE THE MONEY IS
B25: Consumable | E25: Period cost | F25: Share | G25: Cumulative
B26: =Pareto!B7 -> 1. MD bolt 2.4 m galvanised | E26: =Pareto!E7 -> 904575.32 | F26: =Pareto!H7 -> 0.38082776 | G26: =Pareto!I7 -> 0.38082776
B27: =Pareto!B8 -> 2. Shank T45 RD520/525 D45 L525 | E27: =Pareto!E8 -> 473326.75 | F27: =Pareto!H8 -> 0.19927137 | G27: =Pareto!I8 -> 0.58009913
B28: =Pareto!B9 -> 3. Mesh 2.40 x 4.50 m galvanised | E28: =Pareto!E9 -> 353779.93 | F28: =Pareto!H9 -> 0.14894196 | G28: =Pareto!I9 -> 0.72904109
B29: =Pareto!B10 -> 4. Bit adaptor T45F / T38M | E29: =Pareto!E10 -> 227125.95 | F29: =Pareto!H10 -> 0.095620415 | G29: =Pareto!I10 -> 0.8246615
B30: =Pareto!B11 -> 5. Coupling sleeve T45 / T38 | E30: =Pareto!E11 -> 100124.44 | F30: =Pareto!H11 -> 0.042152561 | G30: =Pareto!I11 -> 0.86681407
B33: 4 DATA COMPLETENESS
B34: Measure | E34: Value | I34: Meaning
B35: Consumption captured by the issue registers | E35: =Consumption_Compare!J176 -> 0 | L35: The registers record about half of what the stock counts measure
B36: Drilling items consumed but unpriced | E36: =COUNTIF(C_Face_Drilling!$E$7:$E$60,"x") -> 0 | L36: Each one shows x rather than zero
B37: Material bought but not recorded as installed | E37: =IF(Triangulation!$E$40=0,0,1-Triangulation!$F$40/Triangulation!$E$40) -> 0.37845136 | L37: Stock count against LiveMine installation record

Sheet Equations
B2: EQUATIONS USED IN THIS MODEL
B3: Every calculated figure in the workbook comes from one of the equations below.
B6: Equation 1 Drilling consumable unit cost
B7: UC drill = ( C bits + C rods + C shanks + C couplings + C centralisers ) ÷ m
B8: UC drill | C8: Drilling consumable unit cost, US$ per metre
B9: C bits, C rods, C shanks, C couplings, C centralisers | C9: Total cost of drill steel consumed in the period, US$. Consumption quantity from the stock reconciliation multiplied by the supplier unit price.
B10: m | C10: Total metres advanced in the same period, from the survey end of month report
B11: Calculated on | C11: Unit_Cost, and the item detail on C_Face_Drilling
B13: Equation 2 Ground support consumable unit cost
B14: UC support = ( C bolts + C mesh + C plates + C resin + C cable ) ÷ m
B15: UC support | C15: Ground support consumable unit cost, US$ per metre
B16: C bolts, C mesh, C plates, C resin, C cable | C16: Total cost of ground support consumed in the period, US$. Bearing plates are quoted inside the bolt price and are not costed separately.
B17: m | C17: Total metres advanced in the same period. Every development metre in this data receives support.
B18: Calculated on | C18: Unit_Cost, and the item detail on B_Ground_Support and D_Cable_Bolting
B20: Equation 3 Total development unit cost
B21: UC total = UC drill + UC support
B22: UC total | C22: Total consumable unit cost, US$ per metre
B23: UC drill, UC support | C23: Consumable unit costs from Equations 1 and 2, US$ per metre
B24: Scope | C24: Consumables only. Labour and equipment operating costs are outside the scope of this study and are not included in any figure in this workbook.
B25: Calculated on | C25: Unit_Cost
B27: Equation 4 Change in unit cost between two periods
B28: U1 − U0 = ( C1 − C0 ) ÷ A0 + C1 × ( 1/A1 − 1/A0 )
B29: U0, U1 | C29: Consumable unit cost in the earlier and later period, US$ per metre
B30: C0, C1 | C30: Total consumable cost in the earlier and later period, US$
B31: A0, A1 | C31: Metres advanced in the earlier and later period
B32: first term | C32: Consumption effect: the cost of using more or less material, holding advance constant
B33: second term | C33: Advance effect: the effect of spreading the same spend over a different number of metres
B34: Calculated on | C34: Unit_Cost, section 4
B36: Equation 5 Pareto contribution
B37: P i = C i ÷ Σ C i × 100 Cum i = Σ ( C 1 … C i ) ÷ Σ C i × 100
B38: P i | C38: Percentage contribution of consumable i to total consumable cost
B39: C i | C39: Total cost of consumable i in the period, with items ranked highest to lowest
B40: Cum i | C40: Cumulative percentage down the ranked list
B41: Calculated on | C41: Pareto
B43: Equation 6 Currency conversion
B44: Cost in US$ = Cost in N$ ÷ R
B45: R | C45: Exchange rate, Namibia dollars per United States dollar
B46: Cost in N$ | C46: Supplier unit cost as stated in the mine price list
B47: Cost in US$ | C47: The reporting currency of this workbook. Drilling prices are already quoted in United States dollars and are not converted.
B48: Calculated on | C48: Inputs, and every cost sheet
B50: In any cost cell, x means that no unit price for that item exists in the source data. It is never treated as zero.

Sheet Inputs
B2: INPUTS AND ASSUMPTIONS
B3: Unit costs, exchange rate, design standards and drilling geometry used throughout the workbook.
B4: Blue figures are taken directly from a source document. Shaded cells are awaiting data; each one is listed on the Data_Quality sheet.
B6: 1 EXCHANGE RATE
B7: Item | C7: Description | D7: Unit | E7: Value
B8: R | C8: Namibia dollars per United States dollar | D8: N$ / USD | E8: 16.16
B10: 2 CONSUMABLE UNIT COSTS
B11: Item code | C11: Description | D11: Unit | E11: Unit cost (USD) | F11: Unit cost (US$)
B12: FB39090GWA | C12: Friction bolt 39 x 900 galvanised | D12: each | E12: 7.3844946 | F12: =E12*Inputs!$E$8 -> 119.33343
B13: FB47090GWA | C13: Friction bolt 47 x 900 galvanised | D13: each | E13: 12.897225 | F13: =E13*Inputs!$E$8 -> 208.41916
B14: FB47-2400G | C14: Friction bolt 47 x 2400 galvanised | D14: each | E14: 15.931125 | F14: =E14*Inputs!$E$8 -> 257.44698
B15: BMG2024S | C15: MD bolt 2.4 m galvanised | D15: each | E15: 65.878328 | F15: =E15*Inputs!$E$8 -> 1064.5938
B16: CBD1B065DC05WA | C16: Cable bolt twin strand bulbed 15.2 mm | D16: each | E16: 68.071961 | F16: =E16*Inputs!$E$8 -> 1100.0429
B17: MESH2.4X4.5 | C17: Mesh 2.40 x 4.50 m galvanised | D17: sheet | E17: =E20*E21 -> 82.485411 | F17: =E17*Inputs!$E$8 -> 1332.9642
B19: 3 CONVERSION FACTORS
B20: Mesh sheet area | C20: One sheet measures 2.40 m by 4.50 m | D20: m2 | E20: 10.8
B21: Mesh rate | C21: Galvanised mesh, price per square metre | D21: USD / m2 | E21: 7.637538
B23: 4 PORTAL SPLIT OF GROUND SUPPORT COST
B24: Month | C24: Northern Portal | D24: Southern Portal | F24: Basis
B25: May 2026 | C25: 0.39673913 | D25: =1-C25 -> 0.60326087 | F25: LiveMine installed quantities, measured by heading
B26: June 2026 | C26: 0.60118078 | D26: =1-C26 -> 0.39881922 | F26: LiveMine installed quantities, measured by heading
B27: July 2026 | C27: 0.66189193 | D27: =1-C27 -> 0.33810807 | F27: LiveMine installed quantities, measured by heading
B28: August 2026 | C28: 0.60948622 | D28: =1-C28 -> 0.39051378 | F28: Metres advanced. No LiveMine inventory extract was supplied for this month
B30: See Notes sheet, note 1.
B32: 5 PORTAL SPLIT OF DRILLING CONSUMABLE COST
B33: Month | C33: Northern Portal | D33: Southern Portal | F33: Basis
B34: May 2026 | C34: 0.40359578 | D34: =1-C34 -> 0.59640422 | F34: Drilled metres, 8,398 north and 12,410 south
B35: June 2026 | C35: 0.56313131 | D35: =1-C35 -> 0.43686869 | F35: Drilled metres, 12,466 north and 9,671 south
B36: July 2026 | C36: 0.64772425 | D36: =1-C36 -> 0.35227575 | F36: Drilled metres, 20,928 north and 11,382 south
B37: August 2026 | C37: 0.64296728 | D37: =1-C37 -> 0.35703272 | F37: Drilled metres, 16,138 north and 8,961 south
B39: See Notes sheet, note 2.
B41: 6 DRILLING CONSUMABLE UNIT COSTS
B42: Item code | C42: Description | D42: Unit | E42: Unit cost (US$)
B43: 7304-7669-01 | C43: Shank T38 RD520/525 D45 L525 | D43: each | E43: 308.1
B44: 7305-7669-01 | C44: Shank T45 RD520/525 D45 L525 | D44: each | E44: 5568.55
B45: 7335-4401 | C45: Bit adaptor T45F / T38M | D45: each | E45: 4453.45
B46: 7314-6261 | C46: Coupling sleeve T45 / T38 | D46: each | E46: 1925.47
B47: 7314-3652 | C47: Coupling sleeve T38 / T38 | D47: each | E47: 69.96
B48: 7580-5243A-S70 | C48: A340 43 mm button bit | D48: each | E48: 66.52
B49: 7580-5345A-R48 | C49: A340 45 mm button bit | D49: each | E49: 78.93
B50: 7580-5148A-S81 | C50: A340 48 mm TC button bit | D50: each | E50: 108.19
B51: 7580-4651A-S70 | C51: A340 51 mm retrac bit | D51: each | E51: 94.13
B52: 7580-5602P-S70 | C52: Reaming bit A340 102 mm | D52: each | E52: 343.33
B53: 7514-1664-S70 | C53: T38 64 mm button bit | D53: each | E53: 136.44
B54: 7580-6045-F49 | C54: Speedy bit A340 45 mm XT49 | D54: each | E54: 79.73
... B68: 7979-2626 | C68: T38 dolly 39 mm | D68: each | E68: 96.3
B71: 6 GROUND SUPPORT DESIGN STANDARD, MINIMUM QUANTITY PER CUT
B72: Standard | C72: Ground condition | D72: MD bolt 2.4 m x 47 mm | E72: Split set 2.4 m x 47 mm | F72: Stubby split set 0.9 m x 39 mm | G72: Mesh sheet 4.5 x 2.4 m | I72: Source
B73: GSS_01 | C73: Good ground, Q >= 10 | D73: 33 | E73: 0 | F73: 11 | G73: 6 | I73: GSS01 drawing, minimum quantity per cut
B74: GSS_02 | C74: Fair to poor ground, 10 > Q >= 4 | D74: 15 | E74: 18 | F74: 11 | G74: 6 | I74: GSS02 drawing, minimum quantity per cut
B75: GSS_03 | C75: Poor ground, Q < 4 | D75: 15 | E75: 18 | F75: 11 | G75: 6 | I75: GSS02 standard applied
B77: 7 DRILLING GEOMETRY, USED TO CALCULATE DRILLED METRES
B78: Symbol | C78: Description | D78: Unit | E78: Value
B79: Cut length | C79: Metres advanced per blast round | D79: m | E79: 4
B80: Holes per face | C80: Face holes drilled divided by rounds, from LiveMine | D80: holes | E80: 65.4
B81: Hole length | C81: Drilled length of each face hole, from LiveMine | D81: m | E81: 4.3
B82: Bolt hole, MD bolt | C82: Drilled length per MD bolt hole | D82: m | E82: 2.4
B83: Bolt hole, split set 2.4m | C83: Drilled length per 2.4 m split set hole | D83: m | E83: 2.4
B84: Bolt hole, split set 0.9m | C84: Drilled length per 0.9 m split set hole | D84: m | E84: 0.9
B85: Bolt hole, cable bolt | C85: Drilled length per cable bolt hole | D85: m | E85: 6.5

Sheet Advance
B2: SURVEY DEVELOPMENT ADVANCE
B3: Source: Byrnecut Development Payment end of month reports, EOM Advance column, signed by the Byrnecut surveyor.
B4: Ore and waste rows of one heading are consolidated. North Shoot Decline and NS_1040_ACC_N are one location.
B6: 1 ADVANCE AS RECORDED BY SURVEY
B7: Month | C7: Survey period | D7: Heading as recorded | E7: Location used in this model | F7: Portal | G7: Material | H7: GS type | I7: Profile (m2) | J7: Advance (m)
B8: May 2026 | C8: 1 to 31 May 2026 | D8: SOUTH DECLINE | E8: South Decline | F8: Southern Portal | G8: Waste | H8: GSS_01 | I8: 31.12 | J8: 75.154
B9: May 2026 | C9: 1 to 31 May 2026 | D9: NORTH DECLINE | E9: North Decline | F9: Northern Portal | G9: Waste | H9: GSS_02 | I9: 31.12 | J9: 55.882
B10: May 2026 | C10: 1 to 31 May 2026 | D10: MS_1040_ACC_waste | E10: N_1040_ACCESS (NS 1040 access) | F10: Northern Portal | G10: Waste | H10: GSS_02 | I10: 31.12 | J10: 6
B11: May 2026 | C11: 1 to 31 May 2026 | D11: MS900_ACC_E | E11: MS900_ACC_E | F11: Southern Portal | G11: Waste | H11: GSS_01 | I11: 31.12 | J11: 17.508
B12: May 2026 | C12: 1 to 31 May 2026 | D12: MS_1040_ACC_waste | E12: N_1040_ACCESS (NS 1040 access) | F12: Northern Portal | G12: Waste | H12: GSS_01 | I12: 31.12 | J12: 4.278
B13: May 2026 | C13: 1 to 31 May 2026 | D13: MS900_DDR_N_waste | E13: MS900_DDR_N | F13: Southern Portal | G13: Waste | H13: GSS_01 | I13: 31.12 | J13: 22.683
B14: May 2026 | C14: 1 to 31 May 2026 | D14: MS900_DDR_N_waste1 | E14: MS900_DDR_N | F14: Southern Portal | G14: Waste | H14: GSS_01 | I14: 24.519 | J14: 16.102
B15: May 2026 | C15: 1 to 31 May 2026 | D15: S890_SP_W | E15: S890_SP_W | F15: Southern Portal | G15: Waste | H15: GSS_01 | I15: 31.12 | J15: 24.029
B16: May 2026 | C16: 1 to 31 May 2026 | D16: S900_SMP W | E16: S900_SMP_W | F16: Southern Portal | G16: Waste | H16: GSS_01 | I16: 24.519 | J16: 5
B17: May 2026 | C17: 1 to 31 May 2026 | D17: MS_1040_ACC_OD | E17: N_1040_ACCESS (NS 1040 access) | F17: Northern Portal | G17: ORE | H17: GSS_02 | I17: 31.12 | J17: 16.9
B18: May 2026 | C18: 1 to 31 May 2026 | D18: MS900_DDR_N_OD | E18: MS900_DDR_N | F18: Southern Portal | G18: ORE | H18: GSS_01 | I18: 24.519 | J18: 26.9
B19: June 2026 | C19: 29 May to 28 June 2026 | D19: SOUTH DECLINE | E19: South Decline | F19: Southern Portal | G19: Waste | H19: GSS_01 | I19: 31.12 | J19: 70.356
... B48: August 2026 | C48: 29 July to 28 August 2026 | D48: NS_1020_RAD_N | E48: NS_1020_RAD_N | F48: Northern Portal | G48: Waste | H48: GSS_02 | I48: 29.81 | J48: 32.709
B50: 2 MONTHLY TOTALS, WHOLE UNDERGROUND MINE
B51: Measure | C51: Unit | E51: May 2026 | F51: June 2026 | G51: July 2026 | H51: August 2026 | I51: Period total | K51: Mean per month
B52: Days in period | C52: days | E52: 31 | F52: 31 | G52: 30 | H52: 31
B53: Total advance | C53: m | E53: =SUMIFS($J$8:$J$48,$B$8:$B$48,"May 2026") -> 270.436 | F53: =SUMIFS($J$8:$J$48,$B$8:$B$48,"June 2026") -> 316.617 | G53: =SUMIFS($J$8:$J$48,$B$8:$B$48,"July 2026") -> 397.798 | H53: =SUMIFS($J$8:$J$48,$B$8:$B$48,"August 2026") -> 390.967 | I53: =SUM(E53:H53) -> 1375.818 | K53: =AVERAGE(E53:H53) -> 343.9545
B54: Advance rate | C54: m / day | E54: =IF(E52=0,0,E53/E52) -> 8.7237419 | F54: =IF(F52=0,0,F53/F52) -> 10.213452 | G54: =IF(G52=0,0,G53/G52) -> 13.259933 | H54: =IF(H52=0,0,H53/H52) -> 12.611839 | K54: =AVERAGE(E54:H54) -> 11.202241
B55: Advance rate | C55: m / shift | E55: y | F55: y | G55: y | H55: y
B57: See Notes sheet, note 3.

Sheet Consumption_PL
B2: STOCK RECONCILIATION, MEASURED CONSUMPTION
B3: Source: EOM PL Count Sheets for May and June 2026 and the End July EOM Stocktake Sheet.
B4: Consumption = Opening count + Quantity received − Closing count. This measures material actually used, not material signed out of store.
F6: May 2026 | J6: June 2026 | N6: July 2026 | R6: August 2026
B7: Item code | C7: Description | D7: Unit | F7: Opening (units) | G7: Received (units) | H7: Closing (units) | I7: Consumption (units) | J7: Opening (units) | K7: Received (units) | L7: Closing (units) | M7: Consumption (units) | N7: Opening (units) | O7: Received (units) | P7: Closing (units) | Q7: Consumption (units)
B8: 7324-8043-20 | C8: Drifter rod T38 H35 A340 L=430, scaling rod | D8: each | F8: 75 | G8: 0 | H8: 68 | I8: =F8+G8-H8 -> 7 | J8: 68 | L8: 67 | M8: =J8+K8-L8 -> 1 | N8: 67 | O8: 5 | P8: 71 | Q8: =N8+O8-P8 -> 1 | R8: 71 | T8: 72 | U8: =R8+S8-T8 -> -1
B9: 7580-5243A-S70 | C9: A340 43 mm button bit | D9: each | F9: 85 | G9: 50 | H9: 20 | I9: =F9+G9-H9 -> 115 | J9: 20 | L9: 20 | M9: =J9+K9-L9 -> 0 | N9: 20 | O9: 40 | P9: 50 | Q9: =N9+O9-P9 -> 10 | R9: 50 | T9: 50 | U9: =R9+S9-T9 -> 0
B10: 7580-5345A-R48 | C10: A340 45 mm button bit | D10: each | F10: 330 | G10: 0 | H10: 258 | I10: =F10+G10-H10 -> 72 | J10: 258 | L10: 258 | M10: =J10+K10-L10 -> 0 | N10: 258 | P10: 248 | Q10: =N10+O10-P10 -> 10 | R10: 248 | T10: 223 | U10: =R10+S10-T10 -> 25
B11: 7304-7669-01 | C11: Shank T38 RD520/525 D45 L525 | D11: each | F11: 26 | G11: 0 | H11: 25 | I11: =F11+G11-H11 -> 1 | J11: 25 | L11: 20 | M11: =J11+K11-L11 -> 5 | N11: 20 | O11: 45 | P11: 20 | Q11: =N11+O11-P11 -> 45 | R11: 20 | T11: 19 | U11: =R11+S11-T11 -> 1
B12: FB39090GWA | C12: Friction bolt 39 x 900 galvanised | D12: each | F12: 3483 | G12: 0 | H12: 3300 | I12: =F12+G12-H12 -> 183 | J12: 3300 | L12: 3123 | M12: =J12+K12-L12 -> 177 | N12: 3123 | P12: 3380 | Q12: =N12+O12-P12 -> -257 | R12: 3380 | T12: 3300 | U12: =R12+S12-T12 -> 80
B13: FB47090GWA | C13: Friction bolt 47 x 900 galvanised | D13: each | F13: 3750 | G13: 0 | H13: 3450 | I13: =F13+G13-H13 -> 300 | J13: 3450 | L13: 2921 | M13: =J13+K13-L13 -> 529 | N13: 2921 | P13: 2520 | Q13: =N13+O13-P13 -> 401 | R13: 2520 | T13: 2200 | U13: =R13+S13-T13 -> 320
B14: FB47-2400G | C14: Friction bolt 47 x 2400 galvanised | D14: each | F14: 888 | G14: 0 | H14: 145 | I14: =F14+G14-H14 -> 743 | J14: 145 | K14: 4800 | L14: 3996 | M14: =J14+K14-L14 -> 949 | N14: 3996 | O14: 4800 | P14: 6637 | Q14: =N14+O14-P14 -> 2159 | R14: 6486 | T14: 4200 | U14: =R14+S14-T14 -> 2286
B15: BMG2024S | C15: MD bolt 2.4 m galvanised | D15: each | F15: 11095 | G15: 0 | H15: 8520 | I15: =F15+G15-H15 -> 2575 | J15: 8520 | K15: 10080 | L15: 14926 | M15: =J15+K15-L15 -> 3674 | N15: 14926 | P15: 10763 | Q15: =N15+O15-P15 -> 4163 | R15: 10279 | T15: 6960 | U15: =R15+S15-T15 -> 3319
B16: D1515441GWA | C16: Plate dome 150 x 150 x 4, 41H galvanised | D16: each | F16: 3560 | G16: 0 | H16: 3560 | I16: =F16+G16-H16 -> 0 | J16: 3560 | L16: 3545 | M16: =J16+K16-L16 -> 15 | N16: 3545 | P16: 3545 | Q16: =N16+O16-P16 -> 0 | R16: 3545 | T16: 3336 | U16: =R16+S16-T16 -> 209
B17: CBP328154-47G | C17: D/Fly plate 300 x 280 galvanised | D17: each | F17: 4078 | G17: 0 | H17: 3438 | I17: =F17+G17-H17 -> 640 | J17: 3356 | K17: 4800 | L17: 7102 | M17: =J17+K17-L17 -> 1054 | N17: 7102 | O17: 4800 | P17: 9300 | Q17: =N17+O17-P17 -> 2602 | R17: 9200 | T17: 5970 | U17: =R17+S17-T17 -> 3230
B18: BPG3002806 | C18: Combi plate 300 x 280 x 6 mm galvanised | D18: each | F18: 10560 | G18: 0 | H18: 7820 | I18: =F18+G18-H18 -> 2740 | J18: 7820 | K18: 10080 | L18: 15170 | M18: =J18+K18-L18 -> 2730 | N18: 15170 | P18: 10680 | Q18: =N18+O18-P18 -> 4490 | R18: 10638 | T18: 6240 | U18: =R18+S18-T18 -> 4398
B19: MESH2.4X4.5 | C19: Mesh 2.40 x 4.50 m galvanised | D19: sheet | F19: 2256 | G19: 3675 | H19: 3640 | I19: =F19+G19-H19 -> 2291 | J19: 3640 | L19: 3232 | M19: =J19+K19-L19 -> 408 | N19: 3232 | P19: 2411 | Q19: =N19+O19-P19 -> 821 | R19: 2411 | T19: 1642 | U19: =R19+S19-T19 -> 769
B20: 7305-7669-01 | C20: Shank T45 RD520/525 D45 L525 | D20: each | F20: 15 | G20: 50 | H20: 57 | I20: =F20+G20-H20 -> 8 | J20: 57 | K20: 60 | L20: 98 | M20: =J20+K20-L20 -> 19 | N20: 98 | O20: 45 | P20: 109 | Q20: =N20+O20-P20 -> 34 | R20: 109 | T20: 85 | U20: =R20+S20-T20 -> 24
B21: 7335-4401 | C21: Bit adaptor T45F / T38M | D21: each | F21: 39 | G21: 30 | H21: 54 | I21: =F21+G21-H21 -> 15 | J21: 54 | L21: 50 | M21: =J21+K21-L21 -> 4 | N21: 50 | P21: 34 | Q21: =N21+O21-P21 -> 16 | R21: 34 | T21: 18 | U21: =R21+S21-T21 -> 16
B22: 7314-6261 | C22: Coupling sleeve T45 / T38 | D22: each | F22: 13 | G22: 0 | H22: 2 | I22: =F22+G22-H22 -> 11 | J22: 2 | K22: 60 | L22: 55 | M22: =J22+K22-L22 -> 7 | N22: 55 | O22: 45 | P22: 86 | Q22: =N22+O22-P22 -> 14 | R22: 86 | T22: 66 | U22: =R22+S22-T22 -> 20
B23: 7314-3652 | C23: Coupling sleeve T38 / T38 | D23: each | F23: 55 | G23: 0 | H23: 50 | I23: =F23+G23-H23 -> 5 | J23: 50 | L23: 49 | M23: =J23+K23-L23 -> 1 | N23: 49 | P23: 46 | Q23: =N23+O23-P23 -> 3 | R23: 46 | T23: 46 | U23: =R23+S23-T23 -> 0
B24: 7580-5148A-S81 | C24: A340 48 mm TC button bit | D24: each | F24: 0 | G24: 0 | H24: 0 | I24: =F24+G24-H24 -> 0 | J24: 0 | L24: 0 | M24: =J24+K24-L24 -> 0 | N24: 0 | O24: 70 | P24: 70 | Q24: =N24+O24-P24 -> 0 | R24: 70 | T24: 35 | U24: =R24+S24-T24 -> 35
B25: 7580-4651A-S70 | C25: A340 51 mm retrac bit | D25: each | F25: 30 | G25: 0 | H25: 20 | I25: =F25+G25-H25 -> 10 | J25: 20 | L25: 5 | M25: =J25+K25-L25 -> 15 | N25: 5 | O25: 20 | P25: 15 | Q25: =N25+O25-P25 -> 10 | R25: 15 | T25: 0 | U25: =R25+S25-T25 -> 15
B26: 7580-5602P-S70 | C26: Reaming bit A340 102 mm | D26: each | F26: 38 | G26: 0 | H26: 24 | I26: =F26+G26-H26 -> 14 | J26: 24 | L26: 22 | M26: =J26+K26-L26 -> 2 | N26: 22 | O26: 15 | P26: 23 | Q26: =N26+O26-P26 -> 14 | R26: 23 | T26: 11 | U26: =R26+S26-T26 -> 12
B27: 7514-1664-S70 | C27: T38 64 mm button bit | D27: each | F27: 3 | G27: 40 | H27: 21 | I27: =F27+G27-H27 -> 22 | J27: 21 | L27: 1 | M27: =J27+K27-L27 -> 20 | N27: 1 | O27: 20 | P27: 20 | Q27: =N27+O27-P27 -> 1 | R27: 20 | T27: 8 | U27: =R27+S27-T27 -> 12
B28: 7580-6045-F49 | C28: Speedy bit A340 45 mm XT49 | D28: each | F28: 70 | G28: 100 | H28: 108 | I28: =F28+G28-H28 -> 62 | J28: 108 | L28: 66 | M28: =J28+K28-L28 -> 42 | N28: 66 | O28: 70 | P28: 116 | Q28: =N28+O28-P28 -> 20 | R28: 116 | T28: 46 | U28: =R28+S28-T28 -> 70
B29: 7324-8037-20 | C29: Drifter rod T38 H35 A340 L=370, drilling steel | D29: each | F29: 27 | G29: 0 | H29: 26 | I29: =F29+G29-H29 -> 1 | J29: 26 | L29: 26 | M29: =J29+K29-L29 -> 0 | N29: 26 | P29: 19 | Q29: =N29+O29-P29 -> 7 | R29: 19 | T29: 0 | U29: =R29+S29-T29 -> 19
B30: 7324-7949-20 | C30: Drifter rod T38 R39 A340 L=491, speed rod | D30: each | F30: 202 | G30: 0 | H30: 187 | I30: =F30+G30-H30 -> 15 | J30: 187 | L30: 169 | M30: =J30+K30-L30 -> 18 | N30: 169 | O30: 35 | P30: 188 | Q30: =N30+O30-P30 -> 16 | R30: 187 | T30: 163 | U30: =R30+S30-T30 -> 24
B31: 7324-4731-85 | C31: MF rod T38 R39 L=3050 mm | D31: each | F31: 59 | G31: 0 | H31: 57 | I31: =F31+G31-H31 -> 2 | J31: 57 | L31: 56 | M31: =J31+K31-L31 -> 1 | N31: 56 | P31: 53 | Q31: =N31+O31-P31 -> 3 | R31: 53 | T31: 49 | U31: =R31+S31-T31 -> 4
B32: 7324-4331C-30 | C32: T38 extension round rod L=3050 mm | D32: each | F32: 36 | G32: 0 | H32: 21 | I32: =F32+G32-H32 -> 15 | J32: 21 | L32: 9 | M32: =J32+K32-L32 -> 12 | N32: 9 | P32: 9 | Q32: =N32+O32-P32 -> 0 | R32: 9 | T32: 5 | U32: =R32+S32-T32 -> 4
B33: 7324-4309C-30 | C33: Extension rod T38 R39 L=915 mm | D33: each | F33: 7 | G33: 0 | H33: 7 | I33: =F33+G33-H33 -> 0 | J33: 7 | L33: 3 | M33: =J33+K33-L33 -> 4 | N33: 3 | O33: 5 | P33: 7 | Q33: =N33+O33-P33 -> 1 | R33: 7 | T33: 6 | U33: =R33+S33-T33 -> 1
B34: 7324-4709C-20 | C34: MF rod T38 R39 L=915 mm | D34: each | F34: 6 | G34: 0 | H34: 6 | I34: =F34+G34-H34 -> 0 | J34: 6 | L34: 5 | M34: =J34+K34-L34 -> 1 | N34: 5 | O34: 5 | P34: 9 | Q34: =N34+O34-P34 -> 1 | R34: 9 | T34: 8 | U34: =R34+S34-T34 -> 1
B35: M2000354 | C35: Bolting centraliser dia 70 mm front | D35: each | G35: 0 | H35: 48 | I35: =F35+G35-H35 -> -48 | J35: 48 | L35: 39 | M35: =J35+K35-L35 -> 9 | N35: 39 | O35: 60 | P35: 87 | Q35: =N35+O35-P35 -> 12 | R35: 87 | T35: 83 | U35: =R35+S35-T35 -> 4
B36: M2000353 | C36: Bolting centraliser dia 70 mm back | D36: each | F36: 26 | G36: 0 | H36: 60 | I36: =F36+G36-H36 -> -34 | J36: 60 | L36: 60 | M36: =J36+K36-L36 -> 0 | N36: 60 | O36: 60 | P36: 118 | Q36: =N36+O36-P36 -> 2 | R36: 118 | T36: 117 | U36: =R36+S36-T36 -> 1
B37: M33191232 | C37: Boring centraliser dia 48 mm | D37: each | G37: 0 | H37: 48 | I37: =F37+G37-H37 -> -48 | J37: 48 | L37: 48 | M37: =J37+K37-L37 -> 0 | N37: 48 | O37: 50 | P37: 94 | Q37: =N37+O37-P37 -> 4 | R37: 94 | T37: 92 | U37: =R37+S37-T37 -> 2
B38: 33191231 | C38: Boring centraliser dia 41 mm | D38: each | I38: =F38+G38-H38 -> 0 | M38: =J38+K38-L38 -> 0 | N38: 87 | P38: 78 | Q38: =N38+O38-P38 -> 9 | R38: 78 | T38: 77 | U38: =R38+S38-T38 -> 1
B39: 33191232 | C39: Boring centraliser dia 48 mm | D39: each | I39: =F39+G39-H39 -> 0 | M39: =J39+K39-L39 -> 0 | N39: 85 | P39: 83 | Q39: =N39+O39-P39 -> 2 | R39: 83 | T39: 82 | U39: =R39+S39-T39 -> 1
B40: 33191234 | C40: Bolting centraliser dia 66 mm guide | D40: each | I40: =F40+G40-H40 -> 0 | M40: =J40+K40-L40 -> 0 | N40: 163 | P40: 161 | Q40: =N40+O40-P40 -> 2 | R40: 161 | T40: 161 | U40: =R40+S40-T40 -> 0
B41: 7979-2630 | C41: T38 dolly 47 mm | D41: each | F41: 46 | G41: 0 | H41: 46 | I41: =F41+G41-H41 -> 0 | J41: 46 | L41: 43 | M41: =J41+K41-L41 -> 3 | N41: 43 | O41: 5 | P41: 47 | Q41: =N41+O41-P41 -> 1 | R41: 47 | T41: 43 | U41: =R41+S41-T41 -> 4
B42: 7979-2626 | C42: T38 dolly 39 mm | D42: each | F42: 7 | G42: 0 | H42: 7 | I42: =F42+G42-H42 -> 0 | J42: 7 | L42: 7 | M42: =J42+K42-L42 -> 0 | N42: 7 | O42: 5 | P42: 7 | Q42: =N42+O42-P42 -> 5 | R42: 7 | T42: 7 | U42: =R42+S42-T42 -> 0
B43: CBD1B065DC05WA | C43: Cable bolt twin strand bulbed 15.2 mm | D43: each | F43: 1777 | G43: 0 | H43: 1750 | I43: =F43+G43-H43 -> 27 | J43: 1750 | L43: 1750 | M43: =J43+K43-L43 -> 0 | N43: 1750 | P43: 1690 | Q43: =N43+O43-P43 -> 60 | R43: 1690 | T43: 1630 | U43: =R43+S43-T43 -> 60
B44: BLW15003RWA | C44: Barrel and 3 piece wedge anchor | D44: each | F44: 1850 | G44: 0 | H44: 1847 | I44: =F44+G44-H44 -> 3 | J44: 1847 | K44: 400 | L44: 1841 | M44: =J44+K44-L44 -> 406 | N44: 1841 | P44: 1841 | Q44: =N44+O44-P44 -> 0 | R44: 1841 | T44: 1700 | U44: =R44+S44-T44 -> 141
B45: FCB20203H222WA | C45: Plate flat 200 x 200 x 12 mm | D45: each | F45: 2490 | G45: 0 | H45: 2184 | I45: =F45+G45-H45 -> 306 | J45: 2184 | K45: 600 | L45: 2690 | M45: =J45+K45-L45 -> 94 | N45: 2690 | P45: 2664 | Q45: =N45+O45-P45 -> 26 | R45: 2664 | T45: 2507 | U45: =R45+S45-T45 -> 157
B47: See Notes sheet, note 4.

Sheet Consumption_Issues
B2: CONSUMPTION FROM THE STOCK USAGE ISSUE REGISTERS
B3: Source: Stock Usage Sheets, May to August 2026. Sum of the Qty issued column by item and month.
B4: This measures material signed out of store and recorded on a transaction. It is the second, independent measure of consumption.
B6: Item code | C6: Description | D6: Unit | F6: May (units) | G6: June (units) | H6: July (units) | I6: August (units) | J6: Total (units) | L6: Note
B7: 7324-8043-20 | C7: Drifter rod T38 H35 A340 L=430, scaling rod | D7: each | F7: 0 | G7: 2 | H7: 0 | I7: =SUM(F7:H7) -> 2
B8: 7580-5243A-S70 | C8: A340 43 mm button bit | D8: each | F8: 110 | G8: 0 | H8: 10 | I8: =SUM(F8:H8) -> 120
B9: 7580-5345A-R48 | C9: A340 45 mm button bit | D9: each | F9: 62 | G9: 0 | H9: 10 | I9: =SUM(F9:H9) -> 72
B10: 7304-7669-01 | C10: Shank T38 RD520/525 D45 L525 | D10: each | F10: 1 | G10: 7 | H10: 2 | I10: =SUM(F10:H10) -> 10
B11: FB39090GWA | C11: Friction bolt 39 x 900 galvanised | D11: each | F11: 0 | G11: 0 | H11: 150 | I11: =SUM(F11:H11) -> 150
B12: FB47090GWA | C12: Friction bolt 47 x 900 galvanised | D12: each | F12: 26 | G12: 150 | H12: 270 | I12: =SUM(F12:H12) -> 446
B13: FB47-2400G | C13: Friction bolt 47 x 2400 galvanised | D13: each | F13: 156 | G13: 1350 | H13: 728 | I13: =SUM(F13:H13) -> 2234
B14: BMG2024S | C14: MD bolt 2.4 m galvanised | D14: each | F14: 1852 | G14: 885 | H14: 1602 | I14: =SUM(F14:H14) -> 4339
B15: D1515441GWA | C15: Plate dome 150 x 150 x 4, 41H galvanised | D15: each | F15: 0 | G15: 0 | H15: 0 | I15: =SUM(F15:H15) -> 0 | K15: No issue transaction recorded for this item
B16: CBP328154-47G | C16: D/Fly plate 300 x 280 galvanised | D16: each | F16: 20 | G16: 0 | H16: 780 | I16: =SUM(F16:H16) -> 800
B17: BPG3002806 | C17: Combi plate 300 x 280 x 6 mm galvanised | D17: each | F17: 3496 | G17: 2245 | H17: 1733 | I17: =SUM(F17:H17) -> 7474
B18: MESH2.4X4.5 | C18: Mesh 2.40 x 4.50 m galvanised | D18: sheet | F18: 200 | G18: 230 | H18: 369 | I18: =SUM(F18:H18) -> 799
B19: 7305-7669-01 | C19: Shank T45 RD520/525 D45 L525 | D19: each | F19: 6 | G19: 23 | H19: 32 | I19: =SUM(F19:H19) -> 61
B20: 7335-4401 | C20: Bit adaptor T45F / T38M | D20: each | F20: 12 | G20: 4 | H20: 10 | I20: =SUM(F20:H20) -> 26
B21: 7314-6261 | C21: Coupling sleeve T45 / T38 | D21: each | F21: 10 | G21: 7 | H21: 14 | I21: =SUM(F21:H21) -> 31
B22: 7314-3652 | C22: Coupling sleeve T38 / T38 | D22: each | F22: 5 | G22: 1 | H22: 3 | I22: =SUM(F22:H22) -> 9
B23: 7580-5148A-S81 | C23: A340 48 mm TC button bit | D23: each | F23: 0 | G23: 0 | H23: 10 | I23: =SUM(F23:H23) -> 10
B24: 7580-4651A-S70 | C24: A340 51 mm retrac bit | D24: each | F24: 8 | G24: 15 | H24: 10 | I24: =SUM(F24:H24) -> 33
B25: 7580-5602P-S70 | C25: Reaming bit A340 102 mm | D25: each | F25: 12 | G25: 0 | H25: 14 | I25: =SUM(F25:H25) -> 26
B26: 7514-1664-S70 | C26: T38 64 mm button bit | D26: each | F26: 27 | G26: 20 | H26: 3 | I26: =SUM(F26:H26) -> 50
B27: 7580-6045-F49 | C27: Speedy bit A340 45 mm XT49 | D27: each | F27: 60 | G27: 26 | H27: 30 | I27: =SUM(F27:H27) -> 116
... B35: M2000353 | C35: Bolting centraliser dia 70 mm back | D35: each | F35: 0 | G35: 0 | H35: 2 | I35: =SUM(F35:H35) -> 2
B36: M33191232 | C36: Boring centraliser dia 48 mm | D36: each | F36: 0 | G36: 0 | H36: 0 | I36: =SUM(F36:H36) -> 0 | K36: No issue transaction recorded for this item
B37: 33191231 | C37: Boring centraliser dia 41 mm | D37: each | F37: 4 | G37: 3 | H37: 5 | I37: =SUM(F37:H37) -> 12
B38: 33191232 | C38: Boring centraliser dia 48 mm | D38: each | F38: 0 | G38: 5 | H38: 6 | I38: =SUM(F38:H38) -> 11
B39: 33191234 | C39: Bolting centraliser dia 66 mm guide | D39: each | F39: 0 | G39: 2 | H39: 2 | I39: =SUM(F39:H39) -> 4
B40: 7979-2630 | C40: T38 dolly 47 mm | D40: each | F40: 0 | G40: 1 | H40: 2 | I40: =SUM(F40:H40) -> 3
B41: 7979-2626 | C41: T38 dolly 39 mm | D41: each | F41: 0 | G41: 2 | H41: 0 | I41: =SUM(F41:H41) -> 2
B42: CBD1B065DC05WA | C42: Cable bolt twin strand bulbed 15.2 mm | D42: each | F42: 0 | G42: 51 | H42: 18 | I42: =SUM(F42:H42) -> 69
B43: BLW15003RWA | C43: Barrel and 3 piece wedge anchor | D43: each | F43: 50 | G43: 0 | H43: 50 | I43: =SUM(F43:H43) -> 100
B44: FCB20203H222WA | C44: Plate flat 200 x 200 x 12 mm | D44: each | F44: 0 | G44: 0 | H44: 38 | I44: =SUM(F44:H44) -> 38
C45: Total, all items | F45: =SUM(F7:F44) -> 6124 | G45: =SUM(G7:G44) -> 5062 | H45: =SUM(H7:H44) -> 5916 | I45: =SUM(I7:I44) -> 17102 | J45: =SUM(J7:J44) -> 0
B47: See Notes sheet, note 5.

Sheet Consumption_Compare
B2: COMPARISON OF THE TWO CONSUMPTION MEASURES
B3: Stock count consumption against issue register consumption, by item and month.
B4: The stock count is the costing basis. The issue register is the corroborating measure. Neither has been adjusted to match the other.
B6: MAY 2026
B7: Item code | C7: Description | D7: Unit | F7: Stock count (units) | G7: Issue register (units) | H7: Gap (units) | K7: Register capture | M7: Flag
B8: 7324-8043-20 | C8: Drifter rod T38 H35 A340 L=430, scaling rod | D8: each | F8: =Consumption_PL!I8 -> 7 | G8: =Consumption_Issues!F7 -> 0 | H8: =G8-F8 -> -7 | K8: =IF(F8<=0,"n/a",G8/F8) -> 0 | L8: =IF(F8<=0,"",IF(OR(J8<0.5,J8>1.5),"Check","")) -> Check
B9: 7580-5243A-S70 | C9: A340 43 mm button bit | D9: each | F9: =Consumption_PL!I9 -> 115 | G9: =Consumption_Issues!F8 -> 110 | H9: =G9-F9 -> -5 | K9: =IF(F9<=0,"n/a",G9/F9) -> 0.95652174 | L9: =IF(F9<=0,"",IF(OR(J9<0.5,J9>1.5),"Check","")) -> Check
B10: 7580-5345A-R48 | C10: A340 45 mm button bit | D10: each | F10: =Consumption_PL!I10 -> 72 | G10: =Consumption_Issues!F9 -> 62 | H10: =G10-F10 -> -10 | K10: =IF(F10<=0,"n/a",G10/F10) -> 0.86111111 | L10: =IF(F10<=0,"",IF(OR(J10<0.5,J10>1.5),"Check","")) -> Check
B11: 7304-7669-01 | C11: Shank T38 RD520/525 D45 L525 | D11: each | F11: =Consumption_PL!I11 -> 1 | G11: =Consumption_Issues!F10 -> 1 | H11: =G11-F11 -> 0 | K11: =IF(F11<=0,"n/a",G11/F11) -> 1 | L11: =IF(F11<=0,"",IF(OR(J11<0.5,J11>1.5),"Check","")) -> Check
B12: FB39090GWA | C12: Friction bolt 39 x 900 galvanised | D12: each | F12: =Consumption_PL!I12 -> 183 | G12: =Consumption_Issues!F11 -> 0 | H12: =G12-F12 -> -183 | K12: =IF(F12<=0,"n/a",G12/F12) -> 0 | L12: =IF(F12<=0,"",IF(OR(J12<0.5,J12>1.5),"Check","")) -> Check
B13: FB47090GWA | C13: Friction bolt 47 x 900 galvanised | D13: each | F13: =Consumption_PL!I13 -> 300 | G13: =Consumption_Issues!F12 -> 26 | H13: =G13-F13 -> -274 | K13: =IF(F13<=0,"n/a",G13/F13) -> 0.086666667 | L13: =IF(F13<=0,"",IF(OR(J13<0.5,J13>1.5),"Check","")) -> Check
B14: FB47-2400G | C14: Friction bolt 47 x 2400 galvanised | D14: each | F14: =Consumption_PL!I14 -> 743 | G14: =Consumption_Issues!F13 -> 156 | H14: =G14-F14 -> -587 | K14: =IF(F14<=0,"n/a",G14/F14) -> 0.20995962 | L14: =IF(F14<=0,"",IF(OR(J14<0.5,J14>1.5),"Check","")) -> Check
B15: BMG2024S | C15: MD bolt 2.4 m galvanised | D15: each | F15: =Consumption_PL!I15 -> 2575 | G15: =Consumption_Issues!F14 -> 1852 | H15: =G15-F15 -> -723 | K15: =IF(F15<=0,"n/a",G15/F15) -> 0.7192233 | L15: =IF(F15<=0,"",IF(OR(J15<0.5,J15>1.5),"Check","")) -> Check
B16: D1515441GWA | C16: Plate dome 150 x 150 x 4, 41H galvanised | D16: each | F16: =Consumption_PL!I16 -> 0 | G16: =Consumption_Issues!F15 -> 0 | H16: =G16-F16 -> 0 | K16: =IF(F16<=0,"n/a",G16/F16) -> n/a | L16: =IF(F16<=0,"",IF(OR(J16<0.5,J16>1.5),"Check",""))
B17: CBP328154-47G | C17: D/Fly plate 300 x 280 galvanised | D17: each | F17: =Consumption_PL!I17 -> 640 | G17: =Consumption_Issues!F16 -> 20 | H17: =G17-F17 -> -620 | K17: =IF(F17<=0,"n/a",G17/F17) -> 0.03125 | L17: =IF(F17<=0,"",IF(OR(J17<0.5,J17>1.5),"Check","")) -> Check
B18: BPG3002806 | C18: Combi plate 300 x 280 x 6 mm galvanised | D18: each | F18: =Consumption_PL!I18 -> 2740 | G18: =Consumption_Issues!F17 -> 3496 | H18: =G18-F18 -> 756 | K18: =IF(F18<=0,"n/a",G18/F18) -> 1.2759124 | L18: =IF(F18<=0,"",IF(OR(J18<0.5,J18>1.5),"Check","")) -> Check
B19: MESH2.4X4.5 | C19: Mesh 2.40 x 4.50 m galvanised | D19: sheet | F19: =Consumption_PL!I19 -> 2291 | G19: =Consumption_Issues!F18 -> 200 | H19: =G19-F19 -> -2091 | K19: =IF(F19<=0,"n/a",G19/F19) -> 0.087298123 | L19: =IF(F19<=0,"",IF(OR(J19<0.5,J19>1.5),"Check","")) -> Check
... B45: FCB20203H222WA | C45: Plate flat 200 x 200 x 12 mm | D45: each | F45: =Consumption_PL!I45 -> 306 | G45: =Consumption_Issues!F44 -> 0 | H45: =G45-F45 -> -306 | K45: =IF(F45<=0,"n/a",G45/F45) -> 0 | L45: =IF(F45<=0,"",IF(OR(J45<0.5,J45>1.5),"Check","")) -> Check
C46: May 2026 total | F46: =SUM(F8:F45) -> 10053 | G46: =SUM(G8:G45) -> 6124 | H46: =SUM(H8:H45) -> -3929 | K46: =IF(F46<=0,"n/a",G46/F46) -> 0.60917139
B48: JUNE 2026
B49: Item code | C49: Description | D49: Unit | F49: Stock count (units) | G49: Issue register (units) | H49: Gap (units) | K49: Register capture | M49: Flag
B50: 7324-8043-20 | C50: Drifter rod T38 H35 A340 L=430, scaling rod | D50: each | F50: =Consumption_PL!M8 -> 1 | G50: =Consumption_Issues!G7 -> 2 | H50: =G50-F50 -> 1 | K50: =IF(F50<=0,"n/a",G50/F50) -> 2 | L50: =IF(F50<=0,"",IF(OR(J50<0.5,J50>1.5),"Check","")) -> Check
B51: 7580-5243A-S70 | C51: A340 43 mm button bit | D51: each | F51: =Consumption_PL!M9 -> 0 | G51: =Consumption_Issues!G8 -> 0 | H51: =G51-F51 -> 0 | K51: =IF(F51<=0,"n/a",G51/F51) -> n/a | L51: =IF(F51<=0,"",IF(OR(J51<0.5,J51>1.5),"Check",""))
B52: 7580-5345A-R48 | C52: A340 45 mm button bit | D52: each | F52: =Consumption_PL!M10 -> 0 | G52: =Consumption_Issues!G9 -> 0 | H52: =G52-F52 -> 0 | K52: =IF(F52<=0,"n/a",G52/F52) -> n/a | L52: =IF(F52<=0,"",IF(OR(J52<0.5,J52>1.5),"Check",""))
B53: 7304-7669-01 | C53: Shank T38 RD520/525 D45 L525 | D53: each | F53: =Consumption_PL!M11 -> 5 | G53: =Consumption_Issues!G10 -> 7 | H53: =G53-F53 -> 2 | K53: =IF(F53<=0,"n/a",G53/F53) -> 1.4 | L53: =IF(F53<=0,"",IF(OR(J53<0.5,J53>1.5),"Check","")) -> Check
B54: FB39090GWA | C54: Friction bolt 39 x 900 galvanised | D54: each | F54: =Consumption_PL!M12 -> 177 | G54: =Consumption_Issues!G11 -> 0 | H54: =G54-F54 -> -177 | K54: =IF(F54<=0,"n/a",G54/F54) -> 0 | L54: =IF(F54<=0,"",IF(OR(J54<0.5,J54>1.5),"Check","")) -> Check
B55: FB47090GWA | C55: Friction bolt 47 x 900 galvanised | D55: each | F55: =Consumption_PL!M13 -> 529 | G55: =Consumption_Issues!G12 -> 150 | H55: =G55-F55 -> -379 | K55: =IF(F55<=0,"n/a",G55/F55) -> 0.28355388 | L55: =IF(F55<=0,"",IF(OR(J55<0.5,J55>1.5),"Check","")) -> Check
B56: FB47-2400G | C56: Friction bolt 47 x 2400 galvanised | D56: each | F56: =Consumption_PL!M14 -> 949 | G56: =Consumption_Issues!G13 -> 1350 | H56: =G56-F56 -> 401 | K56: =IF(F56<=0,"n/a",G56/F56) -> 1.4225501 | L56: =IF(F56<=0,"",IF(OR(J56<0.5,J56>1.5),"Check","")) -> Check
B57: BMG2024S | C57: MD bolt 2.4 m galvanised | D57: each | F57: =Consumption_PL!M15 -> 3674 | G57: =Consumption_Issues!G14 -> 885 | H57: =G57-F57 -> -2789 | K57: =IF(F57<=0,"n/a",G57/F57) -> 0.24088187 | L57: =IF(F57<=0,"",IF(OR(J57<0.5,J57>1.5),"Check","")) -> Check
B58: D1515441GWA | C58: Plate dome 150 x 150 x 4, 41H galvanised | D58: each | F58: =Consumption_PL!M16 -> 15 | G58: =Consumption_Issues!G15 -> 0 | H58: =G58-F58 -> -15 | K58: =IF(F58<=0,"n/a",G58/F58) -> 0 | L58: =IF(F58<=0,"",IF(OR(J58<0.5,J58>1.5),"Check","")) -> Check
B59: CBP328154-47G | C59: D/Fly plate 300 x 280 galvanised | D59: each | F59: =Consumption_PL!M17 -> 1054 | G59: =Consumption_Issues!G16 -> 0 | H59: =G59-F59 -> -1054 | K59: =IF(F59<=0,"n/a",G59/F59) -> 0 | L59: =IF(F59<=0,"",IF(OR(J59<0.5,J59>1.5),"Check","")) -> Check
B60: BPG3002806 | C60: Combi plate 300 x 280 x 6 mm galvanised | D60: each | F60: =Consumption_PL!M18 -> 2730 | G60: =Consumption_Issues!G17 -> 2245 | H60: =G60-F60 -> -485 | K60: =IF(F60<=0,"n/a",G60/F60) -> 0.82234432 | L60: =IF(F60<=0,"",IF(OR(J60<0.5,J60>1.5),"Check","")) -> Check
B61: MESH2.4X4.5 | C61: Mesh 2.40 x 4.50 m galvanised | D61: sheet | F61: =Consumption_PL!M19 -> 408 | G61: =Consumption_Issues!G18 -> 230 | H61: =G61-F61 -> -178 | K61: =IF(F61<=0,"n/a",G61/F61) -> 0.56372549 | L61: =IF(F61<=0,"",IF(OR(J61<0.5,J61>1.5),"Check","")) -> Check
... B87: FCB20203H222WA | C87: Plate flat 200 x 200 x 12 mm | D87: each | F87: =Consumption_PL!M45 -> 94 | G87: =Consumption_Issues!G44 -> 0 | H87: =G87-F87 -> -94 | K87: =IF(F87<=0,"n/a",G87/F87) -> 0 | L87: =IF(F87<=0,"",IF(OR(J87<0.5,J87>1.5),"Check","")) -> Check
C88: June 2026 total | F88: =SUM(F50:F87) -> 10200 | G88: =SUM(G50:G87) -> 5062 | H88: =SUM(H50:H87) -> -5138 | K88: =IF(F88<=0,"n/a",G88/F88) -> 0.49627451
B90: JULY 2026
B91: Item code | C91: Description | D91: Unit | F91: Stock count (units) | G91: Issue register (units) | H91: Gap (units) | K91: Register capture | M91: Flag
B92: 7324-8043-20 | C92: Drifter rod T38 H35 A340 L=430, scaling rod | D92: each | F92: =Consumption_PL!Q8 -> 1 | G92: =Consumption_Issues!H7 -> 0 | H92: =G92-F92 -> -1 | K92: =IF(F92<=0,"n/a",G92/F92) -> 0 | L92: =IF(F92<=0,"",IF(OR(J92<0.5,J92>1.5),"Check","")) -> Check
B93: 7580-5243A-S70 | C93: A340 43 mm button bit | D93: each | F93: =Consumption_PL!Q9 -> 10 | G93: =Consumption_Issues!H8 -> 10 | H93: =G93-F93 -> 0 | K93: =IF(F93<=0,"n/a",G93/F93) -> 1 | L93: =IF(F93<=0,"",IF(OR(J93<0.5,J93>1.5),"Check","")) -> Check
B94: 7580-5345A-R48 | C94: A340 45 mm button bit | D94: each | F94: =Consumption_PL!Q10 -> 10 | G94: =Consumption_Issues!H9 -> 10 | H94: =G94-F94 -> 0 | K94: =IF(F94<=0,"n/a",G94/F94) -> 1 | L94: =IF(F94<=0,"",IF(OR(J94<0.5,J94>1.5),"Check","")) -> Check
B95: 7304-7669-01 | C95: Shank T38 RD520/525 D45 L525 | D95: each | F95: =Consumption_PL!Q11 -> 45 | G95: =Consumption_Issues!H10 -> 2 | H95: =G95-F95 -> -43 | K95: =IF(F95<=0,"n/a",G95/F95) -> 0.044444444 | L95: =IF(F95<=0,"",IF(OR(J95<0.5,J95>1.5),"Check","")) -> Check
B96: FB39090GWA | C96: Friction bolt 39 x 900 galvanised | D96: each | F96: =Consumption_PL!Q12 -> -257 | G96: =Consumption_Issues!H11 -> 150 | H96: =G96-F96 -> 407 | K96: =IF(F96<=0,"n/a",G96/F96) -> n/a | L96: =IF(F96<=0,"",IF(OR(J96<0.5,J96>1.5),"Check",""))
B97: FB47090GWA | C97: Friction bolt 47 x 900 galvanised | D97: each | F97: =Consumption_PL!Q13 -> 401 | G97: =Consumption_Issues!H12 -> 270 | H97: =G97-F97 -> -131 | K97: =IF(F97<=0,"n/a",G97/F97) -> 0.67331671 | L97: =IF(F97<=0,"",IF(OR(J97<0.5,J97>1.5),"Check","")) -> Check
B98: FB47-2400G | C98: Friction bolt 47 x 2400 galvanised | D98: each | F98: =Consumption_PL!Q14 -> 2159 | G98: =Consumption_Issues!H13 -> 728 | H98: =G98-F98 -> -1431 | K98: =IF(F98<=0,"n/a",G98/F98) -> 0.33719314 | L98: =IF(F98<=0,"",IF(OR(J98<0.5,J98>1.5),"Check","")) -> Check
B99: BMG2024S | C99: MD bolt 2.4 m galvanised | D99: each | F99: =Consumption_PL!Q15 -> 4163 | G99: =Consumption_Issues!H14 -> 1602 | H99: =G99-F99 -> -2561 | K99: =IF(F99<=0,"n/a",G99/F99) -> 0.38481864 | L99: =IF(F99<=0,"",IF(OR(J99<0.5,J99>1.5),"Check","")) -> Check
B100: D1515441GWA | C100: Plate dome 150 x 150 x 4, 41H galvanised | D100: each | F100: =Consumption_PL!Q16 -> 0 | G100: =Consumption_Issues!H15 -> 0 | H100: =G100-F100 -> 0 | K100: =IF(F100<=0,"n/a",G100/F100) -> n/a | L100: =IF(F100<=0,"",IF(OR(J100<0.5,J100>1.5),"Check",""))
B101: CBP328154-47G | C101: D/Fly plate 300 x 280 galvanised | D101: each | F101: =Consumption_PL!Q17 -> 2602 | G101: =Consumption_Issues!H16 -> 780 | H101: =G101-F101 -> -1822 | K101: =IF(F101<=0,"n/a",G101/F101) -> 0.29976941 | L101: =IF(F101<=0,"",IF(OR(J101<0.5,J101>1.5),"Check","")) -> Check
B102: BPG3002806 | C102: Combi plate 300 x 280 x 6 mm galvanised | D102: each | F102: =Consumption_PL!Q18 -> 4490 | G102: =Consumption_Issues!H17 -> 1733 | H102: =G102-F102 -> -2757 | K102: =IF(F102<=0,"n/a",G102/F102) -> 0.38596882 | L102: =IF(F102<=0,"",IF(OR(J102<0.5,J102>1.5),"Check","")) -> Check
B103: MESH2.4X4.5 | C103: Mesh 2.40 x 4.50 m galvanised | D103: sheet | F103: =Consumption_PL!Q19 -> 821 | G103: =Consumption_Issues!H18 -> 369 | H103: =G103-F103 -> -452 | K103: =IF(F103<=0,"n/a",G103/F103) -> 0.44945189 | L103: =IF(F103<=0,"",IF(OR(J103<0.5,J103>1.5),"Check","")) -> Check
... B129: FCB20203H222WA | C129: Plate flat 200 x 200 x 12 mm | D129: each | F129: =Consumption_PL!Q45 -> 26 | G129: =Consumption_Issues!H44 -> 38 | H129: =G129-F129 -> 12 | K129: =IF(F129<=0,"n/a",G129/F129) -> 1.4615385 | L129: =IF(F129<=0,"",IF(OR(J129<0.5,J129>1.5),"Check","")) -> Check
C130: July 2026 total | F130: =SUM(F92:F129) -> 14708 | G130: =SUM(G92:G129) -> 5916 | H130: =SUM(H92:H129) -> -8792 | K130: =IF(F130<=0,"n/a",G130/F130) -> 0.40223008
B132: AUGUST 2026
B133: Item code | C133: Description | D133: Unit | F133: Stock count (units) | G133: Issue register (units) | H133: Gap (units) | K133: Register capture | M133: Flag
B134: 7324-8043-20 | C134: Drifter rod T38 H35 A340 L=430, scaling rod | D134: each | F134: =Consumption_PL!U8 -> -1 | G134: =Consumption_Issues!I7 -> 2 | H134: =G134-F134 -> 3 | K134: =IF(F134<=0,"n/a",G134/F134) -> n/a | L134: =IF(F134<=0,"",IF(OR(J134<0.5,J134>1.5),"Check",""))
B135: 7580-5243A-S70 | C135: A340 43 mm button bit | D135: each | F135: =Consumption_PL!U9 -> 0 | G135: =Consumption_Issues!I8 -> 120 | H135: =G135-F135 -> 120 | K135: =IF(F135<=0,"n/a",G135/F135) -> n/a | L135: =IF(F135<=0,"",IF(OR(J135<0.5,J135>1.5),"Check",""))
B136: 7580-5345A-R48 | C136: A340 45 mm button bit | D136: each | F136: =Consumption_PL!U10 -> 25 | G136: =Consumption_Issues!I9 -> 72 | H136: =G136-F136 -> 47 | K136: =IF(F136<=0,"n/a",G136/F136) -> 2.88 | L136: =IF(F136<=0,"",IF(OR(J136<0.5,J136>1.5),"Check","")) -> Check
B137: 7304-7669-01 | C137: Shank T38 RD520/525 D45 L525 | D137: each | F137: =Consumption_PL!U11 -> 1 | G137: =Consumption_Issues!I10 -> 10 | H137: =G137-F137 -> 9 | K137: =IF(F137<=0,"n/a",G137/F137) -> 10 | L137: =IF(F137<=0,"",IF(OR(J137<0.5,J137>1.5),"Check","")) -> Check
B138: FB39090GWA | C138: Friction bolt 39 x 900 galvanised | D138: each | F138: =Consumption_PL!U12 -> 80 | G138: =Consumption_Issues!I11 -> 150 | H138: =G138-F138 -> 70 | K138: =IF(F138<=0,"n/a",G138/F138) -> 1.875 | L138: =IF(F138<=0,"",IF(OR(J138<0.5,J138>1.5),"Check","")) -> Check
B139: FB47090GWA | C139: Friction bolt 47 x 900 galvanised | D139: each | F139: =Consumption_PL!U13 -> 320 | G139: =Consumption_Issues!I12 -> 446 | H139: =G139-F139 -> 126 | K139: =IF(F139<=0,"n/a",G139/F139) -> 1.39375 | L139: =IF(F139<=0,"",IF(OR(J139<0.5,J139>1.5),"Check","")) -> Check
B140: FB47-2400G | C140: Friction bolt 47 x 2400 galvanised | D140: each | F140: =Consumption_PL!U14 -> 2286 | G140: =Consumption_Issues!I13 -> 2234 | H140: =G140-F140 -> -52 | K140: =IF(F140<=0,"n/a",G140/F140) -> 0.97725284 | L140: =IF(F140<=0,"",IF(OR(J140<0.5,J140>1.5),"Check","")) -> Check
B141: BMG2024S | C141: MD bolt 2.4 m galvanised | D141: each | F141: =Consumption_PL!U15 -> 3319 | G141: =Consumption_Issues!I14 -> 4339 | H141: =G141-F141 -> 1020 | K141: =IF(F141<=0,"n/a",G141/F141) -> 1.3073215 | L141: =IF(F141<=0,"",IF(OR(J141<0.5,J141>1.5),"Check","")) -> Check
B142: D1515441GWA | C142: Plate dome 150 x 150 x 4, 41H galvanised | D142: each | F142: =Consumption_PL!U16 -> 209 | G142: =Consumption_Issues!I15 -> 0 | H142: =G142-F142 -> -209 | K142: =IF(F142<=0,"n/a",G142/F142) -> 0 | L142: =IF(F142<=0,"",IF(OR(J142<0.5,J142>1.5),"Check","")) -> Check
B143: CBP328154-47G | C143: D/Fly plate 300 x 280 galvanised | D143: each | F143: =Consumption_PL!U17 -> 3230 | G143: =Consumption_Issues!I16 -> 800 | H143: =G143-F143 -> -2430 | K143: =IF(F143<=0,"n/a",G143/F143) -> 0.24767802 | L143: =IF(F143<=0,"",IF(OR(J143<0.5,J143>1.5),"Check","")) -> Check
B144: BPG3002806 | C144: Combi plate 300 x 280 x 6 mm galvanised | D144: each | F144: =Consumption_PL!U18 -> 4398 | G144: =Consumption_Issues!I17 -> 7474 | H144: =G144-F144 -> 3076 | K144: =IF(F144<=0,"n/a",G144/F144) -> 1.6994088 | L144: =IF(F144<=0,"",IF(OR(J144<0.5,J144>1.5),"Check","")) -> Check
B145: MESH2.4X4.5 | C145: Mesh 2.40 x 4.50 m galvanised | D145: sheet | F145: =Consumption_PL!U19 -> 769 | G145: =Consumption_Issues!I18 -> 799 | H145: =G145-F145 -> 30 | K145: =IF(F145<=0,"n/a",G145/F145) -> 1.0390117 | L145: =IF(F145<=0,"",IF(OR(J145<0.5,J145>1.5),"Check","")) -> Check
... B171: FCB20203H222WA | C171: Plate flat 200 x 200 x 12 mm | D171: each | F171: =Consumption_PL!U45 -> 157 | G171: =Consumption_Issues!I44 -> 38 | H171: =G171-F171 -> -119 | K171: =IF(F171<=0,"n/a",G171/F171) -> 0.24203822 | L171: =IF(F171<=0,"",IF(OR(J171<0.5,J171>1.5),"Check","")) -> Check
C172: August 2026 total | F172: =SUM(F134:F171) -> 15264 | G172: =SUM(G134:G171) -> 17102 | H172: =SUM(H134:H171) -> 1838 | K172: =IF(F172<=0,"n/a",G172/F172) -> 1.120414
B174: OVERALL
B175: Measure | F175: Stock count (units) | G175: Issue register (units) | H175: Gap (units) | K175: Register capture
B176: All items, period total | F176: =F46+F88+F130 -> 34961 | G176: =G46+G88+G130 -> 17102 | H176: =H46+H88+H130 -> -17859 | K176: =IF(F176<=0,"n/a",G176/F176) -> 0.48917365
B178: See Notes sheet, note 6.
B180: See Notes sheet, note 7.

Sheet A_Scaling
B2: SHEET A SCALING
B3: Scaling and sounding of the face and walls before development drilling.
B4: Quantities are measured consumption. Cost = quantity x unit cost. All costs in United States dollars.
B6: Item code | C6: Description | D6: Unit | E6: Unit cost (US$) | G6: May (units) | H6: June (units) | I6: July (units) | J6: August (units) | K6: Total (units) | M6: Units per metre | N6: Total cost (US$), period | O6: Cost per metre (US$/m), period
B7: Drilling consumables
B8: 7324-8043-20 | C8: Drifter rod T38 H35 A340 L=430, scaling rod | D8: each | E8: x | G8: =MAX(0,Consumption_PL!I8) -> 7 | H8: =MAX(0,Consumption_PL!M8) -> 1 | I8: =MAX(0,Consumption_PL!Q8) -> 1 | J8: =MAX(0,Consumption_PL!U8) -> 0 | K8: =SUM(G8:J8) -> 9 | M8: =IF(Advance!$I$53=0,0,K8/Advance!$I$53) -> 0.0065415629 | N8: =IF(NOT(ISNUMBER($E8)),$E8,K8*$E8) -> x | O8: =IF(NOT(ISNUMBER($E8)),$E8,N8/Advance!$I$53) -> x
B9: 7580-5243A-S70 | C9: A340 43 mm button bit | D9: each | E9: - | G9: =MAX(0,Consumption_PL!I9) -> 115 | H9: =MAX(0,Consumption_PL!M9) -> 0 | I9: =MAX(0,Consumption_PL!Q9) -> 10 | J9: =MAX(0,Consumption_PL!U9) -> 0 | K9: =SUM(G9:J9) -> 125 | M9: =IF(Advance!$I$53=0,0,K9/Advance!$I$53) -> 0.09085504 | N9: =IF(NOT(ISNUMBER($E9)),$E9,K9*$E9) -> - | O9: =IF(NOT(ISNUMBER($E9)),$E9,N9/Advance!$I$53) -> -
B10: 7580-5345A-R48 | C10: A340 45 mm button bit | D10: each | E10: - | G10: =MAX(0,Consumption_PL!I10) -> 72 | H10: =MAX(0,Consumption_PL!M10) -> 0 | I10: =MAX(0,Consumption_PL!Q10) -> 10 | J10: =MAX(0,Consumption_PL!U10) -> 25 | K10: =SUM(G10:J10) -> 107 | M10: =IF(Advance!$I$53=0,0,K10/Advance!$I$53) -> 0.077771915 | N10: =IF(NOT(ISNUMBER($E10)),$E10,K10*$E10) -> - | O10: =IF(NOT(ISNUMBER($E10)),$E10,N10/Advance!$I$53) -> -
B11: 7304-7669-01 | C11: Shank T38 RD520/525 D45 L525 | D11: each | E11: - | G11: =MAX(0,Consumption_PL!I11) -> 1 | H11: =MAX(0,Consumption_PL!M11) -> 5 | I11: =MAX(0,Consumption_PL!Q11) -> 45 | J11: =MAX(0,Consumption_PL!U11) -> 1 | K11: =SUM(G11:J11) -> 52 | M11: =IF(Advance!$I$53=0,0,K11/Advance!$I$53) -> 0.037795697 | N11: =IF(NOT(ISNUMBER($E11)),$E11,K11*$E11) -> - | O11: =IF(NOT(ISNUMBER($E11)),$E11,N11/Advance!$I$53) -> -
C12: Drilling consumables, subtotal | K12: =SUM(K8:K11) -> 293 | M12: =SUM(M8:M11) -> 0.21296421 | N12: =IF(COUNT(N8:N11)=0,"x",SUM(N8:N11)) -> x | O12: =IF(COUNT(O8:O11)=0,"x",SUM(O8:O11)) -> x
C14: SHEET TOTAL | N14: =IF(COUNT(N12)=0,"x",SUM(N12)) -> x | O14: =IF(COUNT(O12)=0,"x",SUM(O12)) -> x
C16: Key
C17: x | D17: No unit price in the source data.
C18: - | D18: Same item as the face drill uses. Counted once, on sheet C.

Sheet B_Ground_Support
B2: SHEET B GROUND SUPPORT, BOLTING AND MESHING
B3: Installation of primary ground support: bolts, bearing plates and mesh.
B4: Quantities are measured consumption. Cost = quantity x unit cost. All costs in United States dollars.
B6: Item code | C6: Description | D6: Unit | E6: Unit cost (US$) | G6: May (units) | H6: June (units) | I6: July (units) | J6: August (units) | K6: Total (units) | M6: Units per metre | N6: Total cost (US$), period | O6: Cost per metre (US$/m), period
B7: Bolts
B8: FB39090GWA | C8: Friction bolt 39 x 900 galvanised | D8: each | E8: =Inputs!$E$12 -> 7.3844946 | G8: =MAX(0,Consumption_PL!I12) -> 183 | H8: =MAX(0,Consumption_PL!M12) -> 177 | I8: =MAX(0,Consumption_PL!Q12) -> 0 | J8: =MAX(0,Consumption_PL!U12) -> 80 | K8: =SUM(G8:J8) -> 440 | M8: =IF(Advance!$I$53=0,0,K8/Advance!$I$53) -> 0.31980974 | N8: =IF(NOT(ISNUMBER($E8)),$E8,K8*$E8) -> 3249.1776 | O8: =IF(NOT(ISNUMBER($E8)),$E8,N8/Advance!$I$53) -> 2.3616333
B9: FB47090GWA | C9: Friction bolt 47 x 900 galvanised | D9: each | E9: =Inputs!$E$13 -> 12.897225 | G9: =MAX(0,Consumption_PL!I13) -> 300 | H9: =MAX(0,Consumption_PL!M13) -> 529 | I9: =MAX(0,Consumption_PL!Q13) -> 401 | J9: =MAX(0,Consumption_PL!U13) -> 320 | K9: =SUM(G9:J9) -> 1550 | M9: =IF(Advance!$I$53=0,0,K9/Advance!$I$53) -> 1.1266025 | N9: =IF(NOT(ISNUMBER($E9)),$E9,K9*$E9) -> 19990.699 | O9: =IF(NOT(ISNUMBER($E9)),$E9,N9/Advance!$I$53) -> 14.530046
B10: FB47-2400G | C10: Friction bolt 47 x 2400 galvanised | D10: each | E10: =Inputs!$E$14 -> 15.931125 | G10: =MAX(0,Consumption_PL!I14) -> 743 | H10: =MAX(0,Consumption_PL!M14) -> 949 | I10: =MAX(0,Consumption_PL!Q14) -> 2159 | J10: =MAX(0,Consumption_PL!U14) -> 2286 | K10: =SUM(G10:J10) -> 6137 | M10: =IF(Advance!$I$53=0,0,K10/Advance!$I$53) -> 4.4606191 | N10: =IF(NOT(ISNUMBER($E10)),$E10,K10*$E10) -> 97769.314 | O10: =IF(NOT(ISNUMBER($E10)),$E10,N10/Advance!$I$53) -> 71.06268
B11: BMG2024S | C11: MD bolt 2.4 m galvanised | D11: each | E11: =Inputs!$E$15 -> 65.878328 | G11: =MAX(0,Consumption_PL!I15) -> 2575 | H11: =MAX(0,Consumption_PL!M15) -> 3674 | I11: =MAX(0,Consumption_PL!Q15) -> 4163 | J11: =MAX(0,Consumption_PL!U15) -> 3319 | K11: =SUM(G11:J11) -> 13731 | M11: =IF(Advance!$I$53=0,0,K11/Advance!$I$53) -> 9.9802445 | N11: =IF(NOT(ISNUMBER($E11)),$E11,K11*$E11) -> 904575.32 | O11: =IF(NOT(ISNUMBER($E11)),$E11,N11/Advance!$I$53) -> 657.48182
C12: Bolts, subtotal | K12: =SUM(K8:K11) -> 21858 | M12: =SUM(M8:M11) -> 15.887276 | N12: =IF(COUNT(N8:N11)=0,"x",SUM(N8:N11)) -> 1025584.5 | O12: =IF(COUNT(O8:O11)=0,"x",SUM(O8:O11)) -> 745.43617
B14: Bearing plates
B15: D1515441GWA | C15: Plate dome 150 x 150 x 4, 41H galvanised | D15: each | E15: - | G15: =MAX(0,Consumption_PL!I16) -> 0 | H15: =MAX(0,Consumption_PL!M16) -> 15 | I15: =MAX(0,Consumption_PL!Q16) -> 0 | J15: =MAX(0,Consumption_PL!U16) -> 209 | K15: =SUM(G15:J15) -> 224 | M15: =IF(Advance!$I$53=0,0,K15/Advance!$I$53) -> 0.16281223 | N15: =IF(NOT(ISNUMBER($E15)),$E15,K15*$E15) -> - | O15: =IF(NOT(ISNUMBER($E15)),$E15,N15/Advance!$I$53) -> -
B16: CBP328154-47G | C16: D/Fly plate 300 x 280 galvanised | D16: each | E16: - | G16: =MAX(0,Consumption_PL!I17) -> 640 | H16: =MAX(0,Consumption_PL!M17) -> 1054 | I16: =MAX(0,Consumption_PL!Q17) -> 2602 | J16: =MAX(0,Consumption_PL!U17) -> 3230 | K16: =SUM(G16:J16) -> 7526 | M16: =IF(Advance!$I$53=0,0,K16/Advance!$I$53) -> 5.4702003 | N16: =IF(NOT(ISNUMBER($E16)),$E16,K16*$E16) -> - | O16: =IF(NOT(ISNUMBER($E16)),$E16,N16/Advance!$I$53) -> -
B17: BPG3002806 | C17: Combi plate 300 x 280 x 6 mm galvanised | D17: each | E17: - | G17: =MAX(0,Consumption_PL!I18) -> 2740 | H17: =MAX(0,Consumption_PL!M18) -> 2730 | I17: =MAX(0,Consumption_PL!Q18) -> 4490 | J17: =MAX(0,Consumption_PL!U18) -> 4398 | K17: =SUM(G17:J17) -> 14358 | M17: =IF(Advance!$I$53=0,0,K17/Advance!$I$53) -> 10.435973 | N17: =IF(NOT(ISNUMBER($E17)),$E17,K17*$E17) -> - | O17: =IF(NOT(ISNUMBER($E17)),$E17,N17/Advance!$I$53) -> -
C18: Bearing plates, subtotal | K18: =SUM(K15:K17) -> 22108 | M18: =SUM(M15:M17) -> 16.068986 | N18: =IF(COUNT(N15:N17)=0,"x",SUM(N15:N17)) -> x | O18: =IF(COUNT(O15:O17)=0,"x",SUM(O15:O17)) -> x
B20: Mesh
B21: MESH2.4X4.5 | C21: Mesh 2.40 x 4.50 m galvanised | D21: sheet | E21: =Inputs!$E$17 -> 82.485411 | G21: =MAX(0,Consumption_PL!I19) -> 2291 | H21: =MAX(0,Consumption_PL!M19) -> 408 | I21: =MAX(0,Consumption_PL!Q19) -> 821 | J21: =MAX(0,Consumption_PL!U19) -> 769 | K21: =SUM(G21:J21) -> 4289 | M21: =IF(Advance!$I$53=0,0,K21/Advance!$I$53) -> 3.1174181 | N21: =IF(NOT(ISNUMBER($E21)),$E21,K21*$E21) -> 353779.93 | O21: =IF(NOT(ISNUMBER($E21)),$E21,N21/Advance!$I$53) -> 257.14152
C22: Mesh, subtotal | K22: =SUM(K21:K21) -> 4289 | M22: =SUM(M21:M21) -> 3.1174181 | N22: =IF(COUNT(N21:N21)=0,"x",SUM(N21:N21)) -> 353779.93 | O22: =IF(COUNT(O21:O21)=0,"x",SUM(O21:O21)) -> 257.14152
C24: SHEET TOTAL | N24: =IF(COUNT(N12,N18,N22)=0,"x",SUM(N12,N18,N22)) -> 1379364.4 | O24: =IF(COUNT(O12,O18,O22)=0,"x",SUM(O12,O18,O22)) -> 1002.5777
C26: Key
C27: - | D27: Plate cost is inside the bolt price, quoted Bolt and Plate.

Sheet C_Face_Drilling
B2: SHEET C DEVELOPMENT DRILLING, FACE DRILL
B3: Face drilling for blast rounds. This sheet carries all shared drill steel.
B4: Quantities are measured consumption. Cost = quantity x unit cost. All costs in United States dollars.
B6: Item code | C6: Description | D6: Unit | E6: Unit cost (US$) | G6: May (units) | H6: June (units) | I6: July (units) | J6: August (units) | K6: Total (units) | M6: Units per metre | N6: Total cost (US$), period | O6: Cost per metre (US$/m), period
B7: Shanks
B8: 7304-7669-01 | C8: Shank T38 RD520/525 D45 L525 | D8: each | E8: =Inputs!$E$43 -> 308.1 | G8: =MAX(0,Consumption_PL!I11) -> 1 | H8: =MAX(0,Consumption_PL!M11) -> 5 | I8: =MAX(0,Consumption_PL!Q11) -> 45 | J8: =MAX(0,Consumption_PL!U11) -> 1 | K8: =SUM(G8:J8) -> 52 | M8: =IF(Advance!$I$53=0,0,K8/Advance!$I$53) -> 0.037795697 | N8: =IF(NOT(ISNUMBER($E8)),$E8,K8*$E8) -> 16021.2 | O8: =IF(NOT(ISNUMBER($E8)),$E8,N8/Advance!$I$53) -> 11.644854
B9: 7305-7669-01 | C9: Shank T45 RD520/525 D45 L525 | D9: each | E9: =Inputs!$E$44 -> 5568.55 | G9: =MAX(0,Consumption_PL!I20) -> 8 | H9: =MAX(0,Consumption_PL!M20) -> 19 | I9: =MAX(0,Consumption_PL!Q20) -> 34 | J9: =MAX(0,Consumption_PL!U20) -> 24 | K9: =SUM(G9:J9) -> 85 | M9: =IF(Advance!$I$53=0,0,K9/Advance!$I$53) -> 0.061781427 | N9: =IF(NOT(ISNUMBER($E9)),$E9,K9*$E9) -> 473326.75 | O9: =IF(NOT(ISNUMBER($E9)),$E9,N9/Advance!$I$53) -> 344.03297
C10: Shanks, subtotal | K10: =SUM(K8:K9) -> 137 | M10: =SUM(M8:M9) -> 0.099577124 | N10: =IF(COUNT(N8:N9)=0,"x",SUM(N8:N9)) -> 489347.95 | O10: =IF(COUNT(O8:O9)=0,"x",SUM(O8:O9)) -> 355.67782
B12: Couplings and adaptors
B13: 7335-4401 | C13: Bit adaptor T45F / T38M | D13: each | E13: =Inputs!$E$45 -> 4453.45 | G13: =MAX(0,Consumption_PL!I21) -> 15 | H13: =MAX(0,Consumption_PL!M21) -> 4 | I13: =MAX(0,Consumption_PL!Q21) -> 16 | J13: =MAX(0,Consumption_PL!U21) -> 16 | K13: =SUM(G13:J13) -> 51 | M13: =IF(Advance!$I$53=0,0,K13/Advance!$I$53) -> 0.037068856 | N13: =IF(NOT(ISNUMBER($E13)),$E13,K13*$E13) -> 227125.95 | O13: =IF(NOT(ISNUMBER($E13)),$E13,N13/Advance!$I$53) -> 165.0843
B14: 7314-6261 | C14: Coupling sleeve T45 / T38 | D14: each | E14: =Inputs!$E$46 -> 1925.47 | G14: =MAX(0,Consumption_PL!I22) -> 11 | H14: =MAX(0,Consumption_PL!M22) -> 7 | I14: =MAX(0,Consumption_PL!Q22) -> 14 | J14: =MAX(0,Consumption_PL!U22) -> 20 | K14: =SUM(G14:J14) -> 52 | M14: =IF(Advance!$I$53=0,0,K14/Advance!$I$53) -> 0.037795697 | N14: =IF(NOT(ISNUMBER($E14)),$E14,K14*$E14) -> 100124.44 | O14: =IF(NOT(ISNUMBER($E14)),$E14,N14/Advance!$I$53) -> 72.77448
B15: 7314-3652 | C15: Coupling sleeve T38 / T38 | D15: each | E15: =Inputs!$E$47 -> 69.96 | G15: =MAX(0,Consumption_PL!I23) -> 5 | H15: =MAX(0,Consumption_PL!M23) -> 1 | I15: =MAX(0,Consumption_PL!Q23) -> 3 | J15: =MAX(0,Consumption_PL!U23) -> 0 | K15: =SUM(G15:J15) -> 9 | M15: =IF(Advance!$I$53=0,0,K15/Advance!$I$53) -> 0.0065415629 | N15: =IF(NOT(ISNUMBER($E15)),$E15,K15*$E15) -> 629.64 | O15: =IF(NOT(ISNUMBER($E15)),$E15,N15/Advance!$I$53) -> 0.45764774
C16: Couplings and adaptors, subtotal | K16: =SUM(K13:K15) -> 112 | M16: =SUM(M13:M15) -> 0.081406116 | N16: =IF(COUNT(N13:N15)=0,"x",SUM(N13:N15)) -> 327880.03 | O16: =IF(COUNT(O13:O15)=0,"x",SUM(O13:O15)) -> 238.31643
B18: Bits
B19: 7580-5243A-S70 | C19: A340 43 mm button bit | D19: each | E19: =Inputs!$E$48 -> 66.52 | G19: =MAX(0,Consumption_PL!I9) -> 115 | H19: =MAX(0,Consumption_PL!M9) -> 0 | I19: =MAX(0,Consumption_PL!Q9) -> 10 | J19: =MAX(0,Consumption_PL!U9) -> 0 | K19: =SUM(G19:J19) -> 125 | M19: =IF(Advance!$I$53=0,0,K19/Advance!$I$53) -> 0.09085504 | N19: =IF(NOT(ISNUMBER($E19)),$E19,K19*$E19) -> 8315 | O19: =IF(NOT(ISNUMBER($E19)),$E19,N19/Advance!$I$53) -> 6.0436773
B20: 7580-5345A-R48 | C20: A340 45 mm button bit | D20: each | E20: =Inputs!$E$49 -> 78.93 | G20: =MAX(0,Consumption_PL!I10) -> 72 | H20: =MAX(0,Consumption_PL!M10) -> 0 | I20: =MAX(0,Consumption_PL!Q10) -> 10 | J20: =MAX(0,Consumption_PL!U10) -> 25 | K20: =SUM(G20:J20) -> 107 | M20: =IF(Advance!$I$53=0,0,K20/Advance!$I$53) -> 0.077771915 | N20: =IF(NOT(ISNUMBER($E20)),$E20,K20*$E20) -> 8445.51 | O20: =IF(NOT(ISNUMBER($E20)),$E20,N20/Advance!$I$53) -> 6.1385372
B21: 7580-5148A-S81 | C21: A340 48 mm TC button bit | D21: each | E21: =Inputs!$E$50 -> 108.19 | G21: =MAX(0,Consumption_PL!I24) -> 0 | H21: =MAX(0,Consumption_PL!M24) -> 0 | I21: =MAX(0,Consumption_PL!Q24) -> 0 | J21: =MAX(0,Consumption_PL!U24) -> 35 | K21: =SUM(G21:J21) -> 35 | M21: =IF(Advance!$I$53=0,0,K21/Advance!$I$53) -> 0.025439411 | N21: =IF(NOT(ISNUMBER($E21)),$E21,K21*$E21) -> 3786.65 | O21: =IF(NOT(ISNUMBER($E21)),$E21,N21/Advance!$I$53) -> 2.7522899
B22: 7580-4651A-S70 | C22: A340 51 mm retrac bit | D22: each | E22: =Inputs!$E$51 -> 94.13 | G22: =MAX(0,Consumption_PL!I25) -> 10 | H22: =MAX(0,Consumption_PL!M25) -> 15 | I22: =MAX(0,Consumption_PL!Q25) -> 10 | J22: =MAX(0,Consumption_PL!U25) -> 15 | K22: =SUM(G22:J22) -> 50 | M22: =IF(Advance!$I$53=0,0,K22/Advance!$I$53) -> 0.036342016 | N22: =IF(NOT(ISNUMBER($E22)),$E22,K22*$E22) -> 4706.5 | O22: =IF(NOT(ISNUMBER($E22)),$E22,N22/Advance!$I$53) -> 3.420874
B23: 7580-5602P-S70 | C23: Reaming bit A340 102 mm | D23: each | E23: =Inputs!$E$52 -> 343.33 | G23: =MAX(0,Consumption_PL!I26) -> 14 | H23: =MAX(0,Consumption_PL!M26) -> 2 | I23: =MAX(0,Consumption_PL!Q26) -> 14 | J23: =MAX(0,Consumption_PL!U26) -> 12 | K23: =SUM(G23:J23) -> 42 | M23: =IF(Advance!$I$53=0,0,K23/Advance!$I$53) -> 0.030527294 | N23: =IF(NOT(ISNUMBER($E23)),$E23,K23*$E23) -> 14419.86 | O23: =IF(NOT(ISNUMBER($E23)),$E23,N23/Advance!$I$53) -> 10.480936
B24: 7514-1664-S70 | C24: T38 64 mm button bit | D24: each | E24: =Inputs!$E$53 -> 136.44 | G24: =MAX(0,Consumption_PL!I27) -> 22 | H24: =MAX(0,Consumption_PL!M27) -> 20 | I24: =MAX(0,Consumption_PL!Q27) -> 1 | J24: =MAX(0,Consumption_PL!U27) -> 12 | K24: =SUM(G24:J24) -> 55 | M24: =IF(Advance!$I$53=0,0,K24/Advance!$I$53) -> 0.039976218 | N24: =IF(NOT(ISNUMBER($E24)),$E24,K24*$E24) -> 7504.2 | O24: =IF(NOT(ISNUMBER($E24)),$E24,N24/Advance!$I$53) -> 5.4543552
B25: 7580-6045-F49 | C25: Speedy bit A340 45 mm XT49 | D25: each | E25: =Inputs!$E$54 -> 79.73 | G25: =MAX(0,Consumption_PL!I28) -> 62 | H25: =MAX(0,Consumption_PL!M28) -> 42 | I25: =MAX(0,Consumption_PL!Q28) -> 20 | J25: =MAX(0,Consumption_PL!U28) -> 70 | K25: =SUM(G25:J25) -> 194 | M25: =IF(Advance!$I$53=0,0,K25/Advance!$I$53) -> 0.14100702 | N25: =IF(NOT(ISNUMBER($E25)),$E25,K25*$E25) -> 15467.62 | O25: =IF(NOT(ISNUMBER($E25)),$E25,N25/Advance!$I$53) -> 11.24249
C26: Bits, subtotal | K26: =SUM(K19:K25) -> 608 | M26: =SUM(M19:M25) -> 0.44191892 | N26: =IF(COUNT(N19:N25)=0,"x",SUM(N19:N25)) -> 62645.34 | O26: =IF(COUNT(O19:O25)=0,"x",SUM(O19:O25)) -> 45.533159
B28: Rods
B29: 7324-8037-20 | C29: Drifter rod T38 H35 A340 L=370, drilling steel | D29: each | E29: =Inputs!$E$55 -> 498.85 | G29: =MAX(0,Consumption_PL!I29) -> 1 | H29: =MAX(0,Consumption_PL!M29) -> 0 | I29: =MAX(0,Consumption_PL!Q29) -> 7 | J29: =MAX(0,Consumption_PL!U29) -> 19 | K29: =SUM(G29:J29) -> 27 | M29: =IF(Advance!$I$53=0,0,K29/Advance!$I$53) -> 0.019624689 | N29: =IF(NOT(ISNUMBER($E29)),$E29,K29*$E29) -> 13468.95 | O29: =IF(NOT(ISNUMBER($E29)),$E29,N29/Advance!$I$53) -> 9.789776
B30: 7324-7949-20 | C30: Drifter rod T38 R39 A340 L=491, speed rod | D30: each | E30: =Inputs!$E$56 -> 639 | G30: =MAX(0,Consumption_PL!I30) -> 15 | H30: =MAX(0,Consumption_PL!M30) -> 18 | I30: =MAX(0,Consumption_PL!Q30) -> 16 | J30: =MAX(0,Consumption_PL!U30) -> 24 | K30: =SUM(G30:J30) -> 73 | M30: =IF(Advance!$I$53=0,0,K30/Advance!$I$53) -> 0.053059344 | N30: =IF(NOT(ISNUMBER($E30)),$E30,K30*$E30) -> 46647 | O30: =IF(NOT(ISNUMBER($E30)),$E30,N30/Advance!$I$53) -> 33.904921
B31: 7324-4731-85 | C31: MF rod T38 R39 L=3050 mm | D31: each | E31: =Inputs!$E$57 -> 439.59 | G31: =MAX(0,Consumption_PL!I31) -> 2 | H31: =MAX(0,Consumption_PL!M31) -> 1 | I31: =MAX(0,Consumption_PL!Q31) -> 3 | J31: =MAX(0,Consumption_PL!U31) -> 4 | K31: =SUM(G31:J31) -> 10 | M31: =IF(Advance!$I$53=0,0,K31/Advance!$I$53) -> 0.0072684032 | N31: =IF(NOT(ISNUMBER($E31)),$E31,K31*$E31) -> 4395.9 | O31: =IF(NOT(ISNUMBER($E31)),$E31,N31/Advance!$I$53) -> 3.1951174
B32: 7324-4331C-30 | C32: T38 extension round rod L=3050 mm | D32: each | E32: =Inputs!$E$58 -> 317.43 | G32: =MAX(0,Consumption_PL!I32) -> 15 | H32: =MAX(0,Consumption_PL!M32) -> 12 | I32: =MAX(0,Consumption_PL!Q32) -> 0 | J32: =MAX(0,Consumption_PL!U32) -> 4 | K32: =SUM(G32:J32) -> 31 | M32: =IF(Advance!$I$53=0,0,K32/Advance!$I$53) -> 0.02253205 | N32: =IF(NOT(ISNUMBER($E32)),$E32,K32*$E32) -> 9840.33 | O32: =IF(NOT(ISNUMBER($E32)),$E32,N32/Advance!$I$53) -> 7.1523486
B33: 7324-4309C-30 | C33: Extension rod T38 R39 L=915 mm | D33: each | E33: =Inputs!$E$59 -> 184.75 | G33: =MAX(0,Consumption_PL!I33) -> 0 | H33: =MAX(0,Consumption_PL!M33) -> 4 | I33: =MAX(0,Consumption_PL!Q33) -> 1 | J33: =MAX(0,Consumption_PL!U33) -> 1 | K33: =SUM(G33:J33) -> 6 | M33: =IF(Advance!$I$53=0,0,K33/Advance!$I$53) -> 0.0043610419 | N33: =IF(NOT(ISNUMBER($E33)),$E33,K33*$E33) -> 1108.5 | O33: =IF(NOT(ISNUMBER($E33)),$E33,N33/Advance!$I$53) -> 0.8057025
B34: 7324-4709C-20 | C34: MF rod T38 R39 L=915 mm | D34: each | E34: =Inputs!$E$60 -> 276.63 | G34: =MAX(0,Consumption_PL!I34) -> 0 | H34: =MAX(0,Consumption_PL!M34) -> 1 | I34: =MAX(0,Consumption_PL!Q34) -> 1 | J34: =MAX(0,Consumption_PL!U34) -> 1 | K34: =SUM(G34:J34) -> 3 | M34: =IF(Advance!$I$53=0,0,K34/Advance!$I$53) -> 0.002180521 | N34: =IF(NOT(ISNUMBER($E34)),$E34,K34*$E34) -> 829.89 | O34: =IF(NOT(ISNUMBER($E34)),$E34,N34/Advance!$I$53) -> 0.60319752
C35: Rods, subtotal | K35: =SUM(K29:K34) -> 150 | M35: =SUM(M29:M34) -> 0.10902605 | N35: =IF(COUNT(N29:N34)=0,"x",SUM(N29:N34)) -> 76290.57 | O35: =IF(COUNT(O29:O34)=0,"x",SUM(O29:O34)) -> 55.451063
B37: Centralisers and dollies
B38: M2000354 | C38: Bolting centraliser dia 70 mm front | D38: each | E38: =Inputs!$E$61 -> 45.12 | G38: =MAX(0,Consumption_PL!I35) -> 0 | H38: =MAX(0,Consumption_PL!M35) -> 9 | I38: =MAX(0,Consumption_PL!Q35) -> 12 | J38: =MAX(0,Consumption_PL!U35) -> 4 | K38: =SUM(G38:J38) -> 25 | M38: =IF(Advance!$I$53=0,0,K38/Advance!$I$53) -> 0.018171008 | N38: =IF(NOT(ISNUMBER($E38)),$E38,K38*$E38) -> 1128 | O38: =IF(NOT(ISNUMBER($E38)),$E38,N38/Advance!$I$53) -> 0.81987588
B39: M2000353 | C39: Bolting centraliser dia 70 mm back | D39: each | E39: =Inputs!$E$62 -> 68 | G39: =MAX(0,Consumption_PL!I36) -> 0 | H39: =MAX(0,Consumption_PL!M36) -> 0 | I39: =MAX(0,Consumption_PL!Q36) -> 2 | J39: =MAX(0,Consumption_PL!U36) -> 1 | K39: =SUM(G39:J39) -> 3 | M39: =IF(Advance!$I$53=0,0,K39/Advance!$I$53) -> 0.002180521 | N39: =IF(NOT(ISNUMBER($E39)),$E39,K39*$E39) -> 204 | O39: =IF(NOT(ISNUMBER($E39)),$E39,N39/Advance!$I$53) -> 0.14827543
B40: M33191232 | C40: Boring centraliser dia 48 mm | D40: each | E40: =Inputs!$E$63 -> 61.09 | G40: =MAX(0,Consumption_PL!I37) -> 0 | H40: =MAX(0,Consumption_PL!M37) -> 0 | I40: =MAX(0,Consumption_PL!Q37) -> 4 | J40: =MAX(0,Consumption_PL!U37) -> 2 | K40: =SUM(G40:J40) -> 6 | M40: =IF(Advance!$I$53=0,0,K40/Advance!$I$53) -> 0.0043610419 | N40: =IF(NOT(ISNUMBER($E40)),$E40,K40*$E40) -> 366.54 | O40: =IF(NOT(ISNUMBER($E40)),$E40,N40/Advance!$I$53) -> 0.26641605
B41: 33191231 | C41: Boring centraliser dia 41 mm | D41: each | E41: =Inputs!$E$64 -> 1884.83 | G41: =MAX(0,Consumption_PL!I38) -> 0 | H41: =MAX(0,Consumption_PL!M38) -> 0 | I41: =MAX(0,Consumption_PL!Q38) -> 9 | J41: =MAX(0,Consumption_PL!U38) -> 1 | K41: =SUM(G41:J41) -> 10 | M41: =IF(Advance!$I$53=0,0,K41/Advance!$I$53) -> 0.0072684032 | N41: =IF(NOT(ISNUMBER($E41)),$E41,K41*$E41) -> 18848.3 | O41: =IF(NOT(ISNUMBER($E41)),$E41,N41/Advance!$I$53) -> 13.699704
B42: 33191232 | C42: Boring centraliser dia 48 mm | D42: each | E42: =Inputs!$E$65 -> 1733.67 | G42: =MAX(0,Consumption_PL!I39) -> 0 | H42: =MAX(0,Consumption_PL!M39) -> 0 | I42: =MAX(0,Consumption_PL!Q39) -> 2 | J42: =MAX(0,Consumption_PL!U39) -> 1 | K42: =SUM(G42:J42) -> 3 | M42: =IF(Advance!$I$53=0,0,K42/Advance!$I$53) -> 0.002180521 | N42: =IF(NOT(ISNUMBER($E42)),$E42,K42*$E42) -> 5201.01 | O42: =IF(NOT(ISNUMBER($E42)),$E42,N42/Advance!$I$53) -> 3.7803038
B43: 33191234 | C43: Bolting centraliser dia 66 mm guide | D43: each | E43: =Inputs!$E$66 -> 1376.29 | G43: =MAX(0,Consumption_PL!I40) -> 0 | H43: =MAX(0,Consumption_PL!M40) -> 0 | I43: =MAX(0,Consumption_PL!Q40) -> 2 | J43: =MAX(0,Consumption_PL!U40) -> 0 | K43: =SUM(G43:J43) -> 2 | M43: =IF(Advance!$I$53=0,0,K43/Advance!$I$53) -> 0.0014536806 | N43: =IF(NOT(ISNUMBER($E43)),$E43,K43*$E43) -> 2752.58 | O43: =IF(NOT(ISNUMBER($E43)),$E43,N43/Advance!$I$53) -> 2.0006861
B44: 7979-2630 | C44: T38 dolly 47 mm | D44: each | E44: =Inputs!$E$67 -> 96.3 | G44: =MAX(0,Consumption_PL!I41) -> 0 | H44: =MAX(0,Consumption_PL!M41) -> 3 | I44: =MAX(0,Consumption_PL!Q41) -> 1 | J44: =MAX(0,Consumption_PL!U41) -> 4 | K44: =SUM(G44:J44) -> 8 | M44: =IF(Advance!$I$53=0,0,K44/Advance!$I$53) -> 0.0058147226 | N44: =IF(NOT(ISNUMBER($E44)),$E44,K44*$E44) -> 770.4 | O44: =IF(NOT(ISNUMBER($E44)),$E44,N44/Advance!$I$53) -> 0.55995779
B45: 7979-2626 | C45: T38 dolly 39 mm | D45: each | E45: =Inputs!$E$68 -> 96.3 | G45: =MAX(0,Consumption_PL!I42) -> 0 | H45: =MAX(0,Consumption_PL!M42) -> 0 | I45: =MAX(0,Consumption_PL!Q42) -> 5 | J45: =MAX(0,Consumption_PL!U42) -> 0 | K45: =SUM(G45:J45) -> 5 | M45: =IF(Advance!$I$53=0,0,K45/Advance!$I$53) -> 0.0036342016 | N45: =IF(NOT(ISNUMBER($E45)),$E45,K45*$E45) -> 481.5 | O45: =IF(NOT(ISNUMBER($E45)),$E45,N45/Advance!$I$53) -> 0.34997362
C46: Centralisers and dollies, subtotal | K46: =SUM(K38:K45) -> 62 | M46: =SUM(M38:M45) -> 0.0450641 | N46: =IF(COUNT(N38:N45)=0,"x",SUM(N38:N45)) -> 29752.33 | O46: =IF(COUNT(O38:O45)=0,"x",SUM(O38:O45)) -> 21.625193
C48: SHEET TOTAL | N48: =IF(COUNT(N10,N16,N26,N35,N46)=0,"x",SUM(N10,N16,N26,N35,N46)) -> 985916.22 | O48: =IF(COUNT(O10,O16,O26,O35,O46)=0,"x",SUM(O10,O16,O26,O35,O46)) -> 716.60366
C50: Key
C51: x | D51: No unit price in the source data. Enter prices here and the model completes.
C52: Units per metre | D52: Measured consumption. A complete result that needs no price.

Sheet D_Cable_Bolting
B2: SHEET D CABLE BOLTING
B3: Cable bolt installation in crosscuts, wide spans, poor ground and stock brows.
B4: Quantities are measured consumption. Cost = quantity x unit cost. All costs in United States dollars.
B6: Item code | C6: Description | D6: Unit | E6: Unit cost (US$) | G6: May (units) | H6: June (units) | I6: July (units) | J6: August (units) | K6: Total (units) | M6: Units per metre | N6: Total cost (US$), period | O6: Cost per metre (US$/m), period
B7: Cable bolts and hardware
B8: CBD1B065DC05WA | C8: Cable bolt twin strand bulbed 15.2 mm | D8: each | E8: =Inputs!$E$16 -> 68.071961 | G8: =MAX(0,Consumption_PL!I43) -> 27 | H8: =MAX(0,Consumption_PL!M43) -> 0 | I8: =MAX(0,Consumption_PL!Q43) -> 60 | J8: =MAX(0,Consumption_PL!U43) -> 60 | K8: =SUM(G8:J8) -> 147 | M8: =IF(Advance!$I$53=0,0,K8/Advance!$I$53) -> 0.10684553 | N8: =IF(NOT(ISNUMBER($E8)),$E8,K8*$E8) -> 10006.578 | O8: =IF(NOT(ISNUMBER($E8)),$E8,N8/Advance!$I$53) -> 7.2731845
B9: BLW15003RWA | C9: Barrel and 3 piece wedge anchor | D9: each | E9: x | G9: =MAX(0,Consumption_PL!I44) -> 3 | H9: =MAX(0,Consumption_PL!M44) -> 406 | I9: =MAX(0,Consumption_PL!Q44) -> 0 | J9: =MAX(0,Consumption_PL!U44) -> 141 | K9: =SUM(G9:J9) -> 550 | M9: =IF(Advance!$I$53=0,0,K9/Advance!$I$53) -> 0.39976218 | N9: =IF(NOT(ISNUMBER($E9)),$E9,K9*$E9) -> x | O9: =IF(NOT(ISNUMBER($E9)),$E9,N9/Advance!$I$53) -> x
B10: FCB20203H222WA | C10: Plate flat 200 x 200 x 12 mm | D10: each | E10: - | G10: =MAX(0,Consumption_PL!I45) -> 306 | H10: =MAX(0,Consumption_PL!M45) -> 94 | I10: =MAX(0,Consumption_PL!Q45) -> 26 | J10: =MAX(0,Consumption_PL!U45) -> 157 | K10: =SUM(G10:J10) -> 583 | M10: =IF(Advance!$I$53=0,0,K10/Advance!$I$53) -> 0.42374791 | N10: =IF(NOT(ISNUMBER($E10)),$E10,K10*$E10) -> - | O10: =IF(NOT(ISNUMBER($E10)),$E10,N10/Advance!$I$53) -> -
C11: Cable bolts and hardware, subtotal | K11: =SUM(K8:K10) -> 1280 | M11: =SUM(M8:M10) -> 0.93035561 | N11: =IF(COUNT(N8:N10)=0,"x",SUM(N8:N10)) -> 10006.578 | O11: =IF(COUNT(O8:O10)=0,"x",SUM(O8:O10)) -> 7.2731845
C13: SHEET TOTAL | N13: =IF(COUNT(N11)=0,"x",SUM(N11)) -> 10006.578 | O13: =IF(COUNT(O11)=0,"x",SUM(O11)) -> 7.2731845
C15: Key
C16: x | D16: No unit price in the source data.
C17: - | D17: Plate cost is inside the bolt price.

Sheet DRM
B2: DRILLED METRES
B3: DRM = total metres of hole drilled. Drill steel wears with metres of hole drilled, not metres of heading advanced.
B4: Bolt hole metres come from bolts installed. Face metres come from the holes actually drilled, recorded in LiveMine.
B6: 1 BOLT HOLE DRILLED METRES, CALCULATED FROM BOLTS INSTALLED
B7: Bolt type | C7: Hole length (m) | E7: May (drilled m) | F7: June (drilled m) | G7: July (drilled m) | H7: August (drilled m) | I7: Total (drilled m) | K7: Bolts installed, period | M7: Calculation
B8: MD bolt 2.4 m galvanised | C8: 2.4 | E8: =MAX(0,B_Ground_Support!G11)*$C8 -> 6180 | F8: =MAX(0,B_Ground_Support!H11)*$C8 -> 8817.6 | G8: =MAX(0,B_Ground_Support!I11)*$C8 -> 9991.2 | H8: =MAX(0,B_Ground_Support!J11)*$C8 -> 7965.6 | I8: =SUM(E8:H8) -> 32954.4 | K8: =B_Ground_Support!K11 -> 13731 | M8: =TEXT(K8,"#,##0")&" bolts x "&TEXT(C8,"0.0")&" m = "&TEXT(I8,"#,##0")&" drilled m" -> 13,731 bolts x 2.4 m = 32,954 drilled m
B9: Friction bolt 47 x 2400 galvanised | C9: 2.4 | E9: =MAX(0,B_Ground_Support!G10)*$C9 -> 1783.2 | F9: =MAX(0,B_Ground_Support!H10)*$C9 -> 2277.6 | G9: =MAX(0,B_Ground_Support!I10)*$C9 -> 5181.6 | H9: =MAX(0,B_Ground_Support!J10)*$C9 -> 5486.4 | I9: =SUM(E9:H9) -> 14728.8 | K9: =B_Ground_Support!K10 -> 6137 | M9: =TEXT(K9,"#,##0")&" bolts x "&TEXT(C9,"0.0")&" m = "&TEXT(I9,"#,##0")&" drilled m" -> 6,137 bolts x 2.4 m = 14,729 drilled m
B10: Friction bolt 47 x 900 galvanised | C10: 0.9 | E10: =MAX(0,B_Ground_Support!G9)*$C10 -> 270 | F10: =MAX(0,B_Ground_Support!H9)*$C10 -> 476.1 | G10: =MAX(0,B_Ground_Support!I9)*$C10 -> 360.9 | H10: =MAX(0,B_Ground_Support!J9)*$C10 -> 288 | I10: =SUM(E10:H10) -> 1395 | K10: =B_Ground_Support!K9 -> 1550 | M10: =TEXT(K10,"#,##0")&" bolts x "&TEXT(C10,"0.0")&" m = "&TEXT(I10,"#,##0")&" drilled m" -> 1,550 bolts x 0.9 m = 1,395 drilled m
B11: Friction bolt 39 x 900 galvanised | C11: 0.9 | E11: =MAX(0,B_Ground_Support!G8)*$C11 -> 164.7 | F11: =MAX(0,B_Ground_Support!H8)*$C11 -> 159.3 | G11: =MAX(0,B_Ground_Support!I8)*$C11 -> 0 | H11: =MAX(0,B_Ground_Support!J8)*$C11 -> 72 | I11: =SUM(E11:H11) -> 396 | K11: =B_Ground_Support!K8 -> 440 | M11: =TEXT(K11,"#,##0")&" bolts x "&TEXT(C11,"0.0")&" m = "&TEXT(I11,"#,##0")&" drilled m" -> 440 bolts x 0.9 m = 396 drilled m
B12: Cable bolt twin strand bulbed 15.2 mm | C12: 6.5 | E12: =MAX(0,D_Cable_Bolting!G8)*$C12 -> 175.5 | F12: =MAX(0,D_Cable_Bolting!H8)*$C12 -> 0 | G12: =MAX(0,D_Cable_Bolting!I8)*$C12 -> 390 | H12: =MAX(0,D_Cable_Bolting!J8)*$C12 -> 390 | I12: =SUM(E12:H12) -> 955.5 | K12: =D_Cable_Bolting!K8 -> 147 | M12: =TEXT(K12,"#,##0")&" bolts x "&TEXT(C12,"0.0")&" m = "&TEXT(I12,"#,##0")&" drilled m" -> 147 bolts x 6.5 m = 956 drilled m
B13: Total bolt hole drilled metres | E13: =SUM(E8:E12) -> 8573.4 | F13: =SUM(F8:F12) -> 11730.6 | G13: =SUM(G8:G12) -> 15923.7 | H13: =SUM(H8:H12) -> 14202 | I13: =SUM(I8:I12) -> 50429.7
B15: 2 FACE DRILLED METRES, FROM THE LIVEMINE JUMBO PLOD
B16: Term | C16: Unit | E16: May | F16: June | G16: July | H16: August | I16: Period total | K16: Source
B17: Face holes drilled | C17: holes | E17: 4459 | F17: 4777 | G17: 7198 | H17: 5983 | I17: =SUM(E17:H17) -> 22417 | K17: LiveMine Jumbo PLOD, Face Hole Drilled
B18: Reaming holes drilled | C18: holes | E18: 380 | F18: 371 | G18: 575 | H18: 549 | I18: =SUM(E18:H18) -> 1875 | K18: LiveMine Jumbo PLOD, Ream Hole Drilled
B19: Drilled length per hole | C19: m | E19: 4.3 | F19: 4.3 | G19: 4.3 | H19: 4.3 | I19: =AVERAGE(E19:H19) -> 4.3 | K19: LiveMine Jumbo PLOD, Hole Length
B20: Face drilled metres | C20: drilled m | E20: =(E17+E18)*E19 -> 20807.7 | F20: =(F17+F18)*F19 -> 22136.4 | G20: =(G17+G18)*G19 -> 33423.9 | H20: =(H17+H18)*H19 -> 28087.6 | I20: =(I17+I18)*I19 -> 104455.6 | K20: ( face holes + reaming holes ) x drilled length per hole
B21: Metres advanced | C21: m | E21: =Advance!E53 -> 270.436 | F21: =Advance!F53 -> 316.617 | G21: =Advance!G53 -> 397.798 | H21: =Advance!H53 -> 390.967 | I21: =Advance!I53 -> 1375.818
B22: Face drilled metres per advance metre | C22: drilled m / m | E22: =IF(E21=0,0,E20/E21) -> 76.94131 | F22: =IF(F21=0,0,F20/F21) -> 69.915387 | G22: =IF(G21=0,0,G20/G21) -> 84.022293 | H22: =IF(H21=0,0,H20/H21) -> 71.841357 | I22: =IF(I21=0,0,I20/I21) -> 75.922542
B24: 3 TOTAL DRILLED METRES
B25: Term | C25: Unit | E25: May | F25: June | G25: July | H25: August | I25: Period total | K25: Note
B26: DRM, total drilled metres | C26: drilled m | E26: =E13+E20 -> 29381.1 | F26: =F13+F20 -> 33867 | G26: =G13+G20 -> 49347.6 | H26: =H13+H20 -> 42289.6 | I26: =I13+I20 -> 154885.3
B27: DRM per advance metre | C27: drilled m / m | E27: =IF(E21=0,0,E26/E21) -> 108.64345 | F27: =IF(F21=0,0,F26/F21) -> 106.9652 | G27: =IF(G21=0,0,G26/G21) -> 124.05191 | H27: =IF(H21=0,0,H26/H21) -> 108.16667 | I27: =IF(I21=0,0,I26/I21) -> 112.57688
B30: 4 BIT LIFE, THE TWO BITS UNDER INVESTIGATION
B31: See Notes sheet, note 8.
B33: Bit | E33: Bits consumed, period | F33: Drilled metres per bit, from records | G33: Resharpens per bit, from the trial | H33: Drilled metres per bit, from the trial | J33: Note
B34: A340 43 mm button bit | E34: =C_Face_Drilling!K19 -> 125 | F34: =IF(E34<=0,"no bits used",$H$20/E34) -> 224.7008 | M34: Enter the trial result in the two shaded cells
B35: A340 48 mm TC button bit | E35: =C_Face_Drilling!K21 -> 35 | F35: =IF(E35<=0,"no bits used",$H$20/E35) -> 802.50286 | M35: Enter the trial result in the two shaded cells
B37: Difference, 48 mm against 43 mm | F37: =IF(OR(F34="no bits used",F35="no bits used"),"",F35-F34) -> 577.80206 | H37: =IF(COUNT(H34,H35)<2,"",H35-H34)
B39: See Notes sheet, note 9.

Sheet Plan_vs_Actual
B2: PLAN VERSUS ACTUAL GROUND SUPPORT, BY GROUND CLASS
B3: V = actual per metre - design per metre. V % = ( actual - design ) / design x 100
B4: Design quantities are read from the GSS drawings and are per cut. They are converted to a per metre basis using the cut length on the Inputs sheet.
B6: 1 METRES DRIVEN IN EACH GROUND CLASS
B7: Ground class | C7: Ground condition | E7: May (m) | F7: June (m) | G7: July (m) | H7: August (m) | I7: Period (m) | K7: Share of total
B8: GSS_01 | C8: Good ground, Q >= 10 | E8: =SUMIFS(Advance!$J$8:$J$48,Advance!$H$8:$H$48,$B8,Advance!$B$8:$B$48,"May 2026") -> 191.654 | F8: =SUMIFS(Advance!$J$8:$J$48,Advance!$H$8:$H$48,$B8,Advance!$B$8:$B$48,"June 2026") -> 140.782 | G8: =SUMIFS(Advance!$J$8:$J$48,Advance!$H$8:$H$48,$B8,Advance!$B$8:$B$48,"July 2026") -> 138.592 | H8: =SUMIFS(Advance!$J$8:$J$48,Advance!$H$8:$H$48,$B8,Advance!$B$8:$B$48,"August 2026") -> 152.678 | I8: =SUM(E8:H8) -> 623.706 | K8: =IF($I$11=0,0,I8/$I$11) -> 0.45333467
B9: GSS_02 | C9: Fair to poor ground, 10 > Q >= 4 | E9: =SUMIFS(Advance!$J$8:$J$48,Advance!$H$8:$H$48,$B9,Advance!$B$8:$B$48,"May 2026") -> 78.782 | F9: =SUMIFS(Advance!$J$8:$J$48,Advance!$H$8:$H$48,$B9,Advance!$B$8:$B$48,"June 2026") -> 175.835 | G9: =SUMIFS(Advance!$J$8:$J$48,Advance!$H$8:$H$48,$B9,Advance!$B$8:$B$48,"July 2026") -> 41.815 | H9: =SUMIFS(Advance!$J$8:$J$48,Advance!$H$8:$H$48,$B9,Advance!$B$8:$B$48,"August 2026") -> 238.289 | I9: =SUM(E9:H9) -> 534.721 | K9: =IF($I$11=0,0,I9/$I$11) -> 0.38865678
B10: GSS_03 | C10: Poor ground, Q < 4 | E10: =SUMIFS(Advance!$J$8:$J$48,Advance!$H$8:$H$48,$B10,Advance!$B$8:$B$48,"May 2026") -> 0 | F10: =SUMIFS(Advance!$J$8:$J$48,Advance!$H$8:$H$48,$B10,Advance!$B$8:$B$48,"June 2026") -> 0 | G10: =SUMIFS(Advance!$J$8:$J$48,Advance!$H$8:$H$48,$B10,Advance!$B$8:$B$48,"July 2026") -> 217.391 | H10: =SUMIFS(Advance!$J$8:$J$48,Advance!$H$8:$H$48,$B10,Advance!$B$8:$B$48,"August 2026") -> 0 | I10: =SUM(E10:H10) -> 217.391 | K10: =IF($I$11=0,0,I10/$I$11) -> 0.15800854
B11: Total | E11: =SUM(E8:E10) -> 270.436 | F11: =SUM(F8:F10) -> 316.617 | G11: =SUM(G8:G10) -> 397.798 | H11: =SUM(H8:H10) -> 390.967 | I11: =SUM(I8:I10) -> 1375.818
B13: 2 DESIGN QUANTITY PER METRE, WEIGHTED BY GROUND CLASS
B14: Consumable | C14: Design per cut | E14: May (per m) | F14: June (per m) | G14: July (per m) | H14: August (per m) | I14: Period (per m) | K14: Note
B15: MD bolt 2.4 m x 47 mm | C15: see Inputs section 6 | E15: =IF(NOT(ISNUMBER(Inputs!$E$79)),"y",IF(IF(ISNUMBER(Inputs!$D$73),0,E8)+IF(ISNUMBER(Inputs!$D$74),0,E9)+IF(ISNUMBER(Inputs!$D$75),0,E10)>0,"y",IF(E11=0,0,(IF(ISNUMBER(Inputs!$D$73),E8*Inputs!$D$73,0)+IF(ISNUMBER(Inputs!$D$74),E9*Inputs!$D$74,0)+IF(ISNUMBER(Inputs!$D$75),E10*Inputs!$D$75,0))/E11/Inputs!$E$79))) -> 6.9390836 | F15: =IF(NOT(ISNUMBER(Inputs!$E$79)),"y",IF(IF(ISNUMBER(Inputs!$D$73),0,F8)+IF(ISNUMBER(Inputs!$D$74),0,F9)+IF(ISNUMBER(Inputs!$D$75),0,F10)>0,"y",IF(F11=0,0,(IF(ISNUMBER(Inputs!$D$73),F8*Inputs!$D$73,0)+IF(ISNUMBER(Inputs!$D$74),F9*Inputs!$D$74,0)+IF(ISNUMBER(Inputs!$D$75),F10*Inputs!$D$75,0))/F11/Inputs!$E$79))) -> 5.7509001 | G15: =IF(NOT(ISNUMBER(Inputs!$E$79)),"y",IF(IF(ISNUMBER(Inputs!$D$73),0,G8)+IF(ISNUMBER(Inputs!$D$74),0,G9)+IF(ISNUMBER(Inputs!$D$75),0,G10)>0,"y",IF(G11=0,0,(IF(ISNUMBER(Inputs!$D$73),G8*Inputs!$D$73,0)+IF(ISNUMBER(Inputs!$D$74),G9*Inputs!$D$74,0)+IF(ISNUMBER(Inputs!$D$75),G10*Inputs!$D$75,0))/G11/Inputs!$E$79))) -> 5.3177907 | H15: =IF(NOT(ISNUMBER(Inputs!$E$79)),"y",IF(IF(ISNUMBER(Inputs!$D$73),0,H8)+IF(ISNUMBER(Inputs!$D$74),0,H9)+IF(ISNUMBER(Inputs!$D$75),0,H10)>0,"y",IF(H11=0,0,(IF(ISNUMBER(Inputs!$D$73),H8*Inputs!$D$73,0)+IF(ISNUMBER(Inputs!$D$74),H9*Inputs!$D$74,0)+IF(ISNUMBER(Inputs!$D$75),H10*Inputs!$D$75,0))/H11/Inputs!$E$79))) -> 5.507312 | I15: =IF(NOT(ISNUMBER(Inputs!$E$79)),"y",IF(IF(ISNUMBER(Inputs!$D$73),0,I8)+IF(ISNUMBER(Inputs!$D$74),0,I9)+IF(ISNUMBER(Inputs!$D$75),0,I10)>0,"y",IF(I11=0,0,(IF(ISNUMBER(Inputs!$D$73),I8*Inputs!$D$73,0)+IF(ISNUMBER(Inputs!$D$74),I9*Inputs!$D$74,0)+IF(ISNUMBER(Inputs!$D$75),I10*Inputs!$D$75,0))/I11/Inputs!$E$79))) -> 5.790006 | K15: Weighted by the metres driven in each ground class
B16: Split set 2.4 m x 47 mm | C16: see Inputs section 6 | E16: =IF(NOT(ISNUMBER(Inputs!$E$79)),"y",IF(IF(ISNUMBER(Inputs!$E$73),0,E8)+IF(ISNUMBER(Inputs!$E$74),0,E9)+IF(ISNUMBER(Inputs!$E$75),0,E10)>0,"y",IF(E11=0,0,(IF(ISNUMBER(Inputs!$E$73),E8*Inputs!$E$73,0)+IF(ISNUMBER(Inputs!$E$74),E9*Inputs!$E$74,0)+IF(ISNUMBER(Inputs!$E$75),E10*Inputs!$E$75,0))/E11/Inputs!$E$79))) -> 1.3109164 | F16: =IF(NOT(ISNUMBER(Inputs!$E$79)),"y",IF(IF(ISNUMBER(Inputs!$E$73),0,F8)+IF(ISNUMBER(Inputs!$E$74),0,F9)+IF(ISNUMBER(Inputs!$E$75),0,F10)>0,"y",IF(F11=0,0,(IF(ISNUMBER(Inputs!$E$73),F8*Inputs!$E$73,0)+IF(ISNUMBER(Inputs!$E$74),F9*Inputs!$E$74,0)+IF(ISNUMBER(Inputs!$E$75),F10*Inputs!$E$75,0))/F11/Inputs!$E$79))) -> 2.4990999 | G16: =IF(NOT(ISNUMBER(Inputs!$E$79)),"y",IF(IF(ISNUMBER(Inputs!$E$73),0,G8)+IF(ISNUMBER(Inputs!$E$74),0,G9)+IF(ISNUMBER(Inputs!$E$75),0,G10)>0,"y",IF(G11=0,0,(IF(ISNUMBER(Inputs!$E$73),G8*Inputs!$E$73,0)+IF(ISNUMBER(Inputs!$E$74),G9*Inputs!$E$74,0)+IF(ISNUMBER(Inputs!$E$75),G10*Inputs!$E$75,0))/G11/Inputs!$E$79))) -> 2.9322093 | H16: =IF(NOT(ISNUMBER(Inputs!$E$79)),"y",IF(IF(ISNUMBER(Inputs!$E$73),0,H8)+IF(ISNUMBER(Inputs!$E$74),0,H9)+IF(ISNUMBER(Inputs!$E$75),0,H10)>0,"y",IF(H11=0,0,(IF(ISNUMBER(Inputs!$E$73),H8*Inputs!$E$73,0)+IF(ISNUMBER(Inputs!$E$74),H9*Inputs!$E$74,0)+IF(ISNUMBER(Inputs!$E$75),H10*Inputs!$E$75,0))/H11/Inputs!$E$79))) -> 2.742688 | I16: =IF(NOT(ISNUMBER(Inputs!$E$79)),"y",IF(IF(ISNUMBER(Inputs!$E$73),0,I8)+IF(ISNUMBER(Inputs!$E$74),0,I9)+IF(ISNUMBER(Inputs!$E$75),0,I10)>0,"y",IF(I11=0,0,(IF(ISNUMBER(Inputs!$E$73),I8*Inputs!$E$73,0)+IF(ISNUMBER(Inputs!$E$74),I9*Inputs!$E$74,0)+IF(ISNUMBER(Inputs!$E$75),I10*Inputs!$E$75,0))/I11/Inputs!$E$79))) -> 2.459994 | K16: Weighted by the metres driven in each ground class
B17: Stubby split set 0.9 m x 39 mm | C17: see Inputs section 6 | E17: =IF(NOT(ISNUMBER(Inputs!$E$79)),"y",IF(IF(ISNUMBER(Inputs!$F$73),0,E8)+IF(ISNUMBER(Inputs!$F$74),0,E9)+IF(ISNUMBER(Inputs!$F$75),0,E10)>0,"y",IF(E11=0,0,(IF(ISNUMBER(Inputs!$F$73),E8*Inputs!$F$73,0)+IF(ISNUMBER(Inputs!$F$74),E9*Inputs!$F$74,0)+IF(ISNUMBER(Inputs!$F$75),E10*Inputs!$F$75,0))/E11/Inputs!$E$79))) -> 2.75 | F17: =IF(NOT(ISNUMBER(Inputs!$E$79)),"y",IF(IF(ISNUMBER(Inputs!$F$73),0,F8)+IF(ISNUMBER(Inputs!$F$74),0,F9)+IF(ISNUMBER(Inputs!$F$75),0,F10)>0,"y",IF(F11=0,0,(IF(ISNUMBER(Inputs!$F$73),F8*Inputs!$F$73,0)+IF(ISNUMBER(Inputs!$F$74),F9*Inputs!$F$74,0)+IF(ISNUMBER(Inputs!$F$75),F10*Inputs!$F$75,0))/F11/Inputs!$E$79))) -> 2.75 | G17: =IF(NOT(ISNUMBER(Inputs!$E$79)),"y",IF(IF(ISNUMBER(Inputs!$F$73),0,G8)+IF(ISNUMBER(Inputs!$F$74),0,G9)+IF(ISNUMBER(Inputs!$F$75),0,G10)>0,"y",IF(G11=0,0,(IF(ISNUMBER(Inputs!$F$73),G8*Inputs!$F$73,0)+IF(ISNUMBER(Inputs!$F$74),G9*Inputs!$F$74,0)+IF(ISNUMBER(Inputs!$F$75),G10*Inputs!$F$75,0))/G11/Inputs!$E$79))) -> 2.75 | H17: =IF(NOT(ISNUMBER(Inputs!$E$79)),"y",IF(IF(ISNUMBER(Inputs!$F$73),0,H8)+IF(ISNUMBER(Inputs!$F$74),0,H9)+IF(ISNUMBER(Inputs!$F$75),0,H10)>0,"y",IF(H11=0,0,(IF(ISNUMBER(Inputs!$F$73),H8*Inputs!$F$73,0)+IF(ISNUMBER(Inputs!$F$74),H9*Inputs!$F$74,0)+IF(ISNUMBER(Inputs!$F$75),H10*Inputs!$F$75,0))/H11/Inputs!$E$79))) -> 2.75 | I17: =IF(NOT(ISNUMBER(Inputs!$E$79)),"y",IF(IF(ISNUMBER(Inputs!$F$73),0,I8)+IF(ISNUMBER(Inputs!$F$74),0,I9)+IF(ISNUMBER(Inputs!$F$75),0,I10)>0,"y",IF(I11=0,0,(IF(ISNUMBER(Inputs!$F$73),I8*Inputs!$F$73,0)+IF(ISNUMBER(Inputs!$F$74),I9*Inputs!$F$74,0)+IF(ISNUMBER(Inputs!$F$75),I10*Inputs!$F$75,0))/I11/Inputs!$E$79))) -> 2.75 | K17: Weighted by the metres driven in each ground class
B18: Mesh sheet 4.5 x 2.4 m | C18: see Inputs section 6 | E18: =IF(NOT(ISNUMBER(Inputs!$E$79)),"y",IF(IF(ISNUMBER(Inputs!$G$73),0,E8)+IF(ISNUMBER(Inputs!$G$74),0,E9)+IF(ISNUMBER(Inputs!$G$75),0,E10)>0,"y",IF(E11=0,0,(IF(ISNUMBER(Inputs!$G$73),E8*Inputs!$G$73,0)+IF(ISNUMBER(Inputs!$G$74),E9*Inputs!$G$74,0)+IF(ISNUMBER(Inputs!$G$75),E10*Inputs!$G$75,0))/E11/Inputs!$E$79))) -> 1.5 | F18: =IF(NOT(ISNUMBER(Inputs!$E$79)),"y",IF(IF(ISNUMBER(Inputs!$G$73),0,F8)+IF(ISNUMBER(Inputs!$G$74),0,F9)+IF(ISNUMBER(Inputs!$G$75),0,F10)>0,"y",IF(F11=0,0,(IF(ISNUMBER(Inputs!$G$73),F8*Inputs!$G$73,0)+IF(ISNUMBER(Inputs!$G$74),F9*Inputs!$G$74,0)+IF(ISNUMBER(Inputs!$G$75),F10*Inputs!$G$75,0))/F11/Inputs!$E$79))) -> 1.5 | G18: =IF(NOT(ISNUMBER(Inputs!$E$79)),"y",IF(IF(ISNUMBER(Inputs!$G$73),0,G8)+IF(ISNUMBER(Inputs!$G$74),0,G9)+IF(ISNUMBER(Inputs!$G$75),0,G10)>0,"y",IF(G11=0,0,(IF(ISNUMBER(Inputs!$G$73),G8*Inputs!$G$73,0)+IF(ISNUMBER(Inputs!$G$74),G9*Inputs!$G$74,0)+IF(ISNUMBER(Inputs!$G$75),G10*Inputs!$G$75,0))/G11/Inputs!$E$79))) -> 1.5 | H18: =IF(NOT(ISNUMBER(Inputs!$E$79)),"y",IF(IF(ISNUMBER(Inputs!$G$73),0,H8)+IF(ISNUMBER(Inputs!$G$74),0,H9)+IF(ISNUMBER(Inputs!$G$75),0,H10)>0,"y",IF(H11=0,0,(IF(ISNUMBER(Inputs!$G$73),H8*Inputs!$G$73,0)+IF(ISNUMBER(Inputs!$G$74),H9*Inputs!$G$74,0)+IF(ISNUMBER(Inputs!$G$75),H10*Inputs!$G$75,0))/H11/Inputs!$E$79))) -> 1.5 | I18: =IF(NOT(ISNUMBER(Inputs!$E$79)),"y",IF(IF(ISNUMBER(Inputs!$G$73),0,I8)+IF(ISNUMBER(Inputs!$G$74),0,I9)+IF(ISNUMBER(Inputs!$G$75),0,I10)>0,"y",IF(I11=0,0,(IF(ISNUMBER(Inputs!$G$73),I8*Inputs!$G$73,0)+IF(ISNUMBER(Inputs!$G$74),I9*Inputs!$G$74,0)+IF(ISNUMBER(Inputs!$G$75),I10*Inputs!$G$75,0))/I11/Inputs!$E$79))) -> 1.5 | K18: Weighted by the metres driven in each ground class
B21: 3 ACTUAL QUANTITY PER METRE
B22: Consumable | E22: May (per m) | F22: June (per m) | G22: July (per m) | H22: August (per m) | I22: Period (per m) | K22: Units consumed, period
B23: MD bolt 2.4 m x 47 mm | E23: =IF(Advance!E53=0,0,(MAX(0,B_Ground_Support!G11))/Advance!E53) -> 9.5216613 | F23: =IF(Advance!F53=0,0,(MAX(0,B_Ground_Support!H11))/Advance!F53) -> 11.603925 | G23: =IF(Advance!G53=0,0,(MAX(0,B_Ground_Support!I11))/Advance!G53) -> 10.46511 | H23: =IF(Advance!H53=0,0,(MAX(0,B_Ground_Support!J11))/Advance!H53) -> 8.4892075 | I23: =IF(Advance!I53=0,0,(MAX(0,B_Ground_Support!K11))/Advance!I53) -> 9.9802445 | K23: =MAX(0,B_Ground_Support!K11) -> 13731
B24: Split set 2.4 m x 47 mm | E24: =IF(Advance!E53=0,0,(MAX(0,B_Ground_Support!G10))/Advance!E53) -> 2.7474153 | F24: =IF(Advance!F53=0,0,(MAX(0,B_Ground_Support!H10))/Advance!F53) -> 2.9973122 | G24: =IF(Advance!G53=0,0,(MAX(0,B_Ground_Support!I10))/Advance!G53) -> 5.4273777 | H24: =IF(Advance!H53=0,0,(MAX(0,B_Ground_Support!J10))/Advance!H53) -> 5.8470408 | I24: =IF(Advance!I53=0,0,(MAX(0,B_Ground_Support!K10))/Advance!I53) -> 4.4606191 | K24: =MAX(0,B_Ground_Support!K10) -> 6137
B25: Stubby split set 0.9 m x 39 mm | E25: =IF(Advance!E53=0,0,(MAX(0,B_Ground_Support!G8))/Advance!E53) -> 0.67668506 | F25: =IF(Advance!F53=0,0,(MAX(0,B_Ground_Support!H8))/Advance!F53) -> 0.55903505 | G25: =IF(Advance!G53=0,0,(MAX(0,B_Ground_Support!I8))/Advance!G53) -> 0 | H25: =IF(Advance!H53=0,0,(MAX(0,B_Ground_Support!J8))/Advance!H53) -> 0.20462085 | I25: =IF(Advance!I53=0,0,(MAX(0,B_Ground_Support!K8))/Advance!I53) -> 0.31980974 | K25: =MAX(0,B_Ground_Support!K8) -> 440
B26: Mesh sheet 4.5 x 2.4 m | E26: =IF(Advance!E53=0,0,(MAX(0,B_Ground_Support!G21))/Advance!E53) -> 8.4715053 | F26: =IF(Advance!F53=0,0,(MAX(0,B_Ground_Support!H21))/Advance!F53) -> 1.2886232 | G26: =IF(Advance!G53=0,0,(MAX(0,B_Ground_Support!I21))/Advance!G53) -> 2.0638616 | H26: =IF(Advance!H53=0,0,(MAX(0,B_Ground_Support!J21))/Advance!H53) -> 1.9669179 | I26: =IF(Advance!I53=0,0,(MAX(0,B_Ground_Support!K21))/Advance!I53) -> 3.1174181 | K26: =MAX(0,B_Ground_Support!K21) -> 4289
B29: 4 VARIANCE AGAINST DESIGN
B30: Consumable | C30: Unit | E30: May | F30: June | G30: July | H30: August | I30: Period total | K30: Meaning
B31: MD bolt 2.4 m x 47 mm variance | C31: units / m | E31: =IF(NOT(ISNUMBER(E15)),"y",E23-E15) -> 2.5825778 | F31: =IF(NOT(ISNUMBER(F15)),"y",F23-F15) -> 5.8530251 | G31: =IF(NOT(ISNUMBER(G15)),"y",G23-G15) -> 5.1473197 | H31: =IF(NOT(ISNUMBER(H15)),"y",H23-H15) -> 2.9818955 | I31: =IF(NOT(ISNUMBER(I15)),"y",I23-I15) -> 4.1902385 | K31: Positive means more consumed than the design requires
B32: MD bolt 2.4 m x 47 mm variance, per cent | C32: % | E32: =IF(NOT(ISNUMBER(E15)),"y",IF(E15=0,"y",(E23-E15)/E15)) -> 0.37217851 | F32: =IF(NOT(ISNUMBER(F15)),"y",IF(F15=0,"y",(F23-F15)/F15)) -> 1.0177581 | G32: =IF(NOT(ISNUMBER(G15)),"y",IF(G15=0,"y",(G23-G15)/G15)) -> 0.96794328 | H32: =IF(NOT(ISNUMBER(H15)),"y",IF(H15=0,"y",(H23-H15)/H15)) -> 0.541443 | I32: =IF(NOT(ISNUMBER(I15)),"y",IF(I15=0,"y",(I23-I15)/I15)) -> 0.72370192
B34: Split set 2.4 m x 47 mm variance | C34: units / m | E34: =IF(NOT(ISNUMBER(E16)),"y",E24-E16) -> 1.4364988 | F34: =IF(NOT(ISNUMBER(F16)),"y",F24-F16) -> 0.49821235 | G34: =IF(NOT(ISNUMBER(G16)),"y",G24-G16) -> 2.4951684 | H34: =IF(NOT(ISNUMBER(H16)),"y",H24-H16) -> 3.1043528 | I34: =IF(NOT(ISNUMBER(I16)),"y",I24-I16) -> 2.0006251 | K34: Positive means more consumed than the design requires
B35: Split set 2.4 m x 47 mm variance, per cent | C35: % | E35: =IF(NOT(ISNUMBER(E16)),"y",IF(E16=0,"y",(E24-E16)/E16)) -> 1.0957974 | F35: =IF(NOT(ISNUMBER(F16)),"y",IF(F16=0,"y",(F24-F16)/F16)) -> 0.19935672 | G35: =IF(NOT(ISNUMBER(G16)),"y",IF(G16=0,"y",(G24-G16)/G16)) -> 0.85095167 | H35: =IF(NOT(ISNUMBER(H16)),"y",IF(H16=0,"y",(H24-H16)/H16)) -> 1.1318651 | I35: =IF(NOT(ISNUMBER(I16)),"y",IF(I16=0,"y",(I24-I16)/I16)) -> 0.81326422
B37: Stubby split set 0.9 m x 39 mm variance | C37: units / m | E37: =IF(NOT(ISNUMBER(E17)),"y",E25-E17) -> -2.0733149 | F37: =IF(NOT(ISNUMBER(F17)),"y",F25-F17) -> -2.190965 | G37: =IF(NOT(ISNUMBER(G17)),"y",G25-G17) -> -2.75 | H37: =IF(NOT(ISNUMBER(H17)),"y",H25-H17) -> -2.5453791 | I37: =IF(NOT(ISNUMBER(I17)),"y",I25-I17) -> -2.4301903 | K37: Positive means more consumed than the design requires
B38: Stubby split set 0.9 m x 39 mm variance, per cent | C38: % | E38: =IF(NOT(ISNUMBER(E17)),"y",IF(E17=0,"y",(E25-E17)/E17)) -> -0.75393271 | F38: =IF(NOT(ISNUMBER(F17)),"y",IF(F17=0,"y",(F25-F17)/F17)) -> -0.79671453 | G38: =IF(NOT(ISNUMBER(G17)),"y",IF(G17=0,"y",(G25-G17)/G17)) -> -1 | H38: =IF(NOT(ISNUMBER(H17)),"y",IF(H17=0,"y",(H25-H17)/H17)) -> -0.92559242 | I38: =IF(NOT(ISNUMBER(I17)),"y",IF(I17=0,"y",(I25-I17)/I17)) -> -0.88370555
B40: Mesh sheet 4.5 x 2.4 m variance | C40: units / m | E40: =IF(NOT(ISNUMBER(E18)),"y",E26-E18) -> 6.9715053 | F40: =IF(NOT(ISNUMBER(F18)),"y",F26-F18) -> -0.21137684 | G40: =IF(NOT(ISNUMBER(G18)),"y",G26-G18) -> 0.56386156 | H40: =IF(NOT(ISNUMBER(H18)),"y",H26-H18) -> 0.46691792 | I40: =IF(NOT(ISNUMBER(I18)),"y",I26-I18) -> 1.6174181 | K40: Positive means more consumed than the design requires
B41: Mesh sheet 4.5 x 2.4 m variance, per cent | C41: % | E41: =IF(NOT(ISNUMBER(E18)),"y",IF(E18=0,"y",(E26-E18)/E18)) -> 4.6476702 | F41: =IF(NOT(ISNUMBER(F18)),"y",IF(F18=0,"y",(F26-F18)/F18)) -> -0.14091789 | G41: =IF(NOT(ISNUMBER(G18)),"y",IF(G18=0,"y",(G26-G18)/G18)) -> 0.37590771 | H41: =IF(NOT(ISNUMBER(H18)),"y",IF(H18=0,"y",(H26-H18)/H18)) -> 0.31127862 | I41: =IF(NOT(ISNUMBER(I18)),"y",IF(I18=0,"y",(I26-I18)/I18)) -> 1.0782788
B43: 5 CLASSIFICATION OF ANY OVER CONSUMPTION
B44: Month | C44: Consumable | E44: Variance (units/m) | F44: Classification | G44: Evidence relied on | J44: Action
B45: May 2026 | C45: MD bolt 2.4 m x 47 mm | E45: =IF(OR(NOT(ISNUMBER(E23)),NOT(ISNUMBER(E15))),"y",E23-E15) -> 2.5825778
B46: May 2026 | C46: Split set 2.4 m x 47 mm | E46: =IF(OR(NOT(ISNUMBER(E24)),NOT(ISNUMBER(E16))),"y",E24-E16) -> 1.4364988
B47: May 2026 | C47: Stubby split set 0.9 m x 39 mm | E47: =IF(OR(NOT(ISNUMBER(E25)),NOT(ISNUMBER(E17))),"y",E25-E17) -> -2.0733149
B48: May 2026 | C48: Mesh sheet 4.5 x 2.4 m | E48: =IF(OR(NOT(ISNUMBER(E26)),NOT(ISNUMBER(E18))),"y",E26-E18) -> 6.9715053
B49: June 2026 | C49: MD bolt 2.4 m x 47 mm | E49: =IF(OR(NOT(ISNUMBER(F23)),NOT(ISNUMBER(F15))),"y",F23-F15) -> 5.8530251
B50: June 2026 | C50: Split set 2.4 m x 47 mm | E50: =IF(OR(NOT(ISNUMBER(F24)),NOT(ISNUMBER(F16))),"y",F24-F16) -> 0.49821235
B51: June 2026 | C51: Stubby split set 0.9 m x 39 mm | E51: =IF(OR(NOT(ISNUMBER(F25)),NOT(ISNUMBER(F17))),"y",F25-F17) -> -2.190965
B52: June 2026 | C52: Mesh sheet 4.5 x 2.4 m | E52: =IF(OR(NOT(ISNUMBER(F26)),NOT(ISNUMBER(F18))),"y",F26-F18) -> -0.21137684
B53: July 2026 | C53: MD bolt 2.4 m x 47 mm | E53: =IF(OR(NOT(ISNUMBER(G23)),NOT(ISNUMBER(G15))),"y",G23-G15) -> 5.1473197
B54: July 2026 | C54: Split set 2.4 m x 47 mm | E54: =IF(OR(NOT(ISNUMBER(G24)),NOT(ISNUMBER(G16))),"y",G24-G16) -> 2.4951684
B55: July 2026 | C55: Stubby split set 0.9 m x 39 mm | E55: =IF(OR(NOT(ISNUMBER(G25)),NOT(ISNUMBER(G17))),"y",G25-G17) -> -2.75
B56: July 2026 | C56: Mesh sheet 4.5 x 2.4 m | E56: =IF(OR(NOT(ISNUMBER(G26)),NOT(ISNUMBER(G18))),"y",G26-G18) -> 0.56386156
B57: August 2026 | C57: MD bolt 2.4 m x 47 mm | E57: =IF(OR(NOT(ISNUMBER(H23)),NOT(ISNUMBER(H15))),"y",H23-H15) -> 2.9818955
B58: August 2026 | C58: Split set 2.4 m x 47 mm | E58: =IF(OR(NOT(ISNUMBER(H24)),NOT(ISNUMBER(H16))),"y",H24-H16) -> 3.1043528
B59: August 2026 | C59: Stubby split set 0.9 m x 39 mm | E59: =IF(OR(NOT(ISNUMBER(H25)),NOT(ISNUMBER(H17))),"y",H25-H17) -> -2.5453791
B60: August 2026 | C60: Mesh sheet 4.5 x 2.4 m | E60: =IF(OR(NOT(ISNUMBER(H26)),NOT(ISNUMBER(H18))),"y",H26-H18) -> 0.46691792
B62: See Notes sheet, note 10.
B65: 6 DESIGN PER METRE AT A RANGE OF CUT LENGTHS, PERIOD BASIS
B66: Cut length (m) | E66: MD bolt design (per m) | F66: MD bolt actual (per m) | G66: Variance (per m) | H66: Variance (per cent) | K66: Mesh design (per m)
B67: 3 | E67: =IF($B67=0,0,(IF(ISNUMBER(Inputs!$D$73),$H$8*Inputs!$D$73,0)+IF(ISNUMBER(Inputs!$D$74),$H$9*Inputs!$D$74,0)+IF(ISNUMBER(Inputs!$D$75),$H$10*Inputs!$D$75,0))/(IF(ISNUMBER(Inputs!$D$73),$H$8,0)+IF(ISNUMBER(Inputs!$D$74),$H$9,0)+IF(ISNUMBER(Inputs!$D$75),$H$10,0))/$B67) -> 7.3430827 | F67: =$H$23 -> 8.4892075 | G67: =F67-E67 -> 1.1461249 | I67: =IF(E67=0,"",(F67-E67)/E67) -> 0.15608225 | K67: =IF($B67=0,0,(IF(ISNUMBER(Inputs!$F$73),$H$8*Inputs!$F$73,0)+IF(ISNUMBER(Inputs!$F$74),$H$9*Inputs!$F$74,0)+IF(ISNUMBER(Inputs!$F$75),$H$10*Inputs!$F$75,0))/(IF(ISNUMBER(Inputs!$D$73),$H$8,0)+IF(ISNUMBER(Inputs!$D$74),$H$9,0)+IF(ISNUMBER(Inputs!$D$75),$H$10,0))/$B67) -> 3.6666667
B68: 3.2 | E68: =IF($B68=0,0,(IF(ISNUMBER(Inputs!$D$73),$H$8*Inputs!$D$73,0)+IF(ISNUMBER(Inputs!$D$74),$H$9*Inputs!$D$74,0)+IF(ISNUMBER(Inputs!$D$75),$H$10*Inputs!$D$75,0))/(IF(ISNUMBER(Inputs!$D$73),$H$8,0)+IF(ISNUMBER(Inputs!$D$74),$H$9,0)+IF(ISNUMBER(Inputs!$D$75),$H$10,0))/$B68) -> 6.88414 | F68: =$H$23 -> 8.4892075 | G68: =F68-E68 -> 1.6050675 | I68: =IF(E68=0,"",(F68-E68)/E68) -> 0.2331544 | K68: =IF($B68=0,0,(IF(ISNUMBER(Inputs!$F$73),$H$8*Inputs!$F$73,0)+IF(ISNUMBER(Inputs!$F$74),$H$9*Inputs!$F$74,0)+IF(ISNUMBER(Inputs!$F$75),$H$10*Inputs!$F$75,0))/(IF(ISNUMBER(Inputs!$D$73),$H$8,0)+IF(ISNUMBER(Inputs!$D$74),$H$9,0)+IF(ISNUMBER(Inputs!$D$75),$H$10,0))/$B68) -> 3.4375
B69: 3.4 | E69: =IF($B69=0,0,(IF(ISNUMBER(Inputs!$D$73),$H$8*Inputs!$D$73,0)+IF(ISNUMBER(Inputs!$D$74),$H$9*Inputs!$D$74,0)+IF(ISNUMBER(Inputs!$D$75),$H$10*Inputs!$D$75,0))/(IF(ISNUMBER(Inputs!$D$73),$H$8,0)+IF(ISNUMBER(Inputs!$D$74),$H$9,0)+IF(ISNUMBER(Inputs!$D$75),$H$10,0))/$B69) -> 6.4791906 | F69: =$H$23 -> 8.4892075 | G69: =F69-E69 -> 2.0100169 | I69: =IF(E69=0,"",(F69-E69)/E69) -> 0.31022655 | K69: =IF($B69=0,0,(IF(ISNUMBER(Inputs!$F$73),$H$8*Inputs!$F$73,0)+IF(ISNUMBER(Inputs!$F$74),$H$9*Inputs!$F$74,0)+IF(ISNUMBER(Inputs!$F$75),$H$10*Inputs!$F$75,0))/(IF(ISNUMBER(Inputs!$D$73),$H$8,0)+IF(ISNUMBER(Inputs!$D$74),$H$9,0)+IF(ISNUMBER(Inputs!$D$75),$H$10,0))/$B69) -> 3.2352941
B70: 3.6 | E70: =IF($B70=0,0,(IF(ISNUMBER(Inputs!$D$73),$H$8*Inputs!$D$73,0)+IF(ISNUMBER(Inputs!$D$74),$H$9*Inputs!$D$74,0)+IF(ISNUMBER(Inputs!$D$75),$H$10*Inputs!$D$75,0))/(IF(ISNUMBER(Inputs!$D$73),$H$8,0)+IF(ISNUMBER(Inputs!$D$74),$H$9,0)+IF(ISNUMBER(Inputs!$D$75),$H$10,0))/$B70) -> 6.1192356 | F70: =$H$23 -> 8.4892075 | G70: =F70-E70 -> 2.369972 | I70: =IF(E70=0,"",(F70-E70)/E70) -> 0.3872987 | K70: =IF($B70=0,0,(IF(ISNUMBER(Inputs!$F$73),$H$8*Inputs!$F$73,0)+IF(ISNUMBER(Inputs!$F$74),$H$9*Inputs!$F$74,0)+IF(ISNUMBER(Inputs!$F$75),$H$10*Inputs!$F$75,0))/(IF(ISNUMBER(Inputs!$D$73),$H$8,0)+IF(ISNUMBER(Inputs!$D$74),$H$9,0)+IF(ISNUMBER(Inputs!$D$75),$H$10,0))/$B70) -> 3.0555556
B71: 3.8 | E71: =IF($B71=0,0,(IF(ISNUMBER(Inputs!$D$73),$H$8*Inputs!$D$73,0)+IF(ISNUMBER(Inputs!$D$74),$H$9*Inputs!$D$74,0)+IF(ISNUMBER(Inputs!$D$75),$H$10*Inputs!$D$75,0))/(IF(ISNUMBER(Inputs!$D$73),$H$8,0)+IF(ISNUMBER(Inputs!$D$74),$H$9,0)+IF(ISNUMBER(Inputs!$D$75),$H$10,0))/$B71) -> 5.7971705 | F71: =$H$23 -> 8.4892075 | G71: =F71-E71 -> 2.692037 | I71: =IF(E71=0,"",(F71-E71)/E71) -> 0.46437085 | K71: =IF($B71=0,0,(IF(ISNUMBER(Inputs!$F$73),$H$8*Inputs!$F$73,0)+IF(ISNUMBER(Inputs!$F$74),$H$9*Inputs!$F$74,0)+IF(ISNUMBER(Inputs!$F$75),$H$10*Inputs!$F$75,0))/(IF(ISNUMBER(Inputs!$D$73),$H$8,0)+IF(ISNUMBER(Inputs!$D$74),$H$9,0)+IF(ISNUMBER(Inputs!$D$75),$H$10,0))/$B71) -> 2.8947368
B72: 4 | E72: =IF($B72=0,0,(IF(ISNUMBER(Inputs!$D$73),$H$8*Inputs!$D$73,0)+IF(ISNUMBER(Inputs!$D$74),$H$9*Inputs!$D$74,0)+IF(ISNUMBER(Inputs!$D$75),$H$10*Inputs!$D$75,0))/(IF(ISNUMBER(Inputs!$D$73),$H$8,0)+IF(ISNUMBER(Inputs!$D$74),$H$9,0)+IF(ISNUMBER(Inputs!$D$75),$H$10,0))/$B72) -> 5.507312 | F72: =$H$23 -> 8.4892075 | G72: =F72-E72 -> 2.9818955 | I72: =IF(E72=0,"",(F72-E72)/E72) -> 0.541443 | K72: =IF($B72=0,0,(IF(ISNUMBER(Inputs!$F$73),$H$8*Inputs!$F$73,0)+IF(ISNUMBER(Inputs!$F$74),$H$9*Inputs!$F$74,0)+IF(ISNUMBER(Inputs!$F$75),$H$10*Inputs!$F$75,0))/(IF(ISNUMBER(Inputs!$D$73),$H$8,0)+IF(ISNUMBER(Inputs!$D$74),$H$9,0)+IF(ISNUMBER(Inputs!$D$75),$H$10,0))/$B72) -> 2.75
B74: See Notes sheet, note 11.
B76: See Notes sheet, note 12.

Sheet Unit_Cost
B2: DEVELOPMENT UNIT COST
B3: Equations 1 to 4, cost per drilled metre, and the advance rate scenarios.
B4: All costs in United States dollars. Metres are survey measured. Whole underground mine.
B6: 1 EQUATION 2 UC support = ( C bolts + C mesh + C plates + C resin + C cable ) ÷ m
B7: Term | C7: Unit | E7: May 2026 | F7: June 2026 | G7: July 2026 | H7: August 2026 | I7: Period total | K7: Note
B8: C bolts | C8: US$ | E8: =MAX(0,B_Ground_Support!G8)*B_Ground_Support!$E$8+MAX(0,B_Ground_Support!G9)*B_Ground_Support!$E$9+MAX(0,B_Ground_Support!G10)*B_Ground_Support!$E$10+MAX(0,B_Ground_Support!G11)*B_Ground_Support!$E$11 -> 186694.05 | F8: =MAX(0,B_Ground_Support!H8)*B_Ground_Support!$E$8+MAX(0,B_Ground_Support!H9)*B_Ground_Support!$E$9+MAX(0,B_Ground_Support!H10)*B_Ground_Support!$E$10+MAX(0,B_Ground_Support!H11)*B_Ground_Support!$E$11 -> 265285.3 | G8: =MAX(0,B_Ground_Support!I8)*B_Ground_Support!$E$8+MAX(0,B_Ground_Support!I9)*B_Ground_Support!$E$9+MAX(0,B_Ground_Support!I10)*B_Ground_Support!$E$10+MAX(0,B_Ground_Support!I11)*B_Ground_Support!$E$11 -> 313818.56 | H8: =MAX(0,B_Ground_Support!J8)*B_Ground_Support!$E$8+MAX(0,B_Ground_Support!J9)*B_Ground_Support!$E$9+MAX(0,B_Ground_Support!J10)*B_Ground_Support!$E$10+MAX(0,B_Ground_Support!J11)*B_Ground_Support!$E$11 -> 259786.59 | I8: =SUM(E8:H8) -> 1025584.5 | K8: Price includes the plate
B9: C mesh | C9: US$ | E9: =MAX(0,B_Ground_Support!G21)*B_Ground_Support!$E$21 -> 188974.08 | F9: =MAX(0,B_Ground_Support!H21)*B_Ground_Support!$E$21 -> 33654.048 | G9: =MAX(0,B_Ground_Support!I21)*B_Ground_Support!$E$21 -> 67720.522 | H9: =MAX(0,B_Ground_Support!J21)*B_Ground_Support!$E$21 -> 63431.281 | I9: =SUM(E9:H9) -> 353779.93 | K9: 10.8 m2 per sheet
B10: C plates | C10: US$ | E10: 0 | F10: 0 | G10: 0 | H10: 0 | I10: =SUM(E10:H10) -> 0 | K10: Zero, sits inside the bolt price
B11: C resin and grout | C11: US$ | E11: 0 | F11: 0 | G11: 0 | H11: 0 | I11: =SUM(E11:H11) -> 0 | K11: Zero, no unit price available
B12: C cable bolts | C12: US$ | E12: =MAX(0,D_Cable_Bolting!G8)*D_Cable_Bolting!$E$8 -> 1837.9429 | F12: =MAX(0,D_Cable_Bolting!H8)*D_Cable_Bolting!$E$8 -> 0 | G12: =MAX(0,D_Cable_Bolting!I8)*D_Cable_Bolting!$E$8 -> 4084.3176 | H12: =MAX(0,D_Cable_Bolting!J8)*D_Cable_Bolting!$E$8 -> 4084.3176 | I12: =SUM(E12:H12) -> 10006.578 | K12: Reported separately
B13: Total ground support consumable cost | C13: US$ | E13: =SUM(E8:E12) -> 377506.07 | F13: =SUM(F8:F12) -> 298939.35 | G13: =SUM(G8:G12) -> 385623.4 | H13: =SUM(H8:H12) -> 327302.19 | I13: =SUM(I8:I12) -> 1389371
B14: m, metres advanced | C14: m | E14: =Advance!E53 -> 270.436 | F14: =Advance!F53 -> 316.617 | G14: =Advance!G53 -> 397.798 | H14: =Advance!H53 -> 390.967 | I14: =Advance!I53 -> 1375.818
B15: UC support | C15: US$ / m | E15: =IF(E14=0,0,E13/E14) -> 1395.9165 | F15: =IF(F14=0,0,F13/F14) -> 944.16708 | G15: =IF(G14=0,0,G13/G14) -> 969.39503 | H15: =IF(H14=0,0,H13/H14) -> 837.16066 | I15: =IF(I14=0,0,I13/I14) -> 1009.8509
B17: 2 EQUATION 1 UC drill = ( C bits + C rods + C shanks + C couplings + C centralisers ) ÷ m
B18: Term | C18: Unit | E18: May 2026 | F18: June 2026 | G18: July 2026 | H18: August 2026 | I18: Period total | K18: Note
B19: C bits | C19: US$ | E19: =MAX(0,C_Face_Drilling!G19)*IF(ISNUMBER(C_Face_Drilling!$E$19),C_Face_Drilling!$E$19,0)+MAX(0,C_Face_Drilling!G20)*IF(ISNUMBER(C_Face_Drilling!$E$20),C_Face_Drilling!$E$20,0)+MAX(0,C_Face_Drilling!G21)*IF(ISNUMBER(C_Face_Drilling!$E$21),C_Face_Drilling!$E$21,0)+MAX(0,C_Face_Drilling!G22)*IF(ISNUMBER(C_Face_Drilling!$E$22),C_Face_Drilling!$E$22,0)+MAX(0,C_Face_Drilling!G23)*IF(ISNUMBER(C_Face_Drilling!$E$23),C_Face_Drilling!$E$23,0)+MAX(0,C_Face_Drilling!G24)*IF(ISNUMBER(C_Face_Drilling!$E$24),C_Face_Drilling!$E$24,0)+MAX(0,C_Face_Drilling!G25)*IF(ISNUMBER(C_Face_Drilling!$E$25),C_Face_Drilling!$E$25,0) -> 27025.62 | F19: =MAX(0,C_Face_Drilling!H19)*IF(ISNUMBER(C_Face_Drilling!$E$19),C_Face_Drilling!$E$19,0)+MAX(0,C_Face_Drilling!H20)*IF(ISNUMBER(C_Face_Drilling!$E$20),C_Face_Drilling!$E$20,0)+MAX(0,C_Face_Drilling!H21)*IF(ISNUMBER(C_Face_Drilling!$E$21),C_Face_Drilling!$E$21,0)+MAX(0,C_Face_Drilling!H22)*IF(ISNUMBER(C_Face_Drilling!$E$22),C_Face_Drilling!$E$22,0)+MAX(0,C_Face_Drilling!H23)*IF(ISNUMBER(C_Face_Drilling!$E$23),C_Face_Drilling!$E$23,0)+MAX(0,C_Face_Drilling!H24)*IF(ISNUMBER(C_Face_Drilling!$E$24),C_Face_Drilling!$E$24,0)+MAX(0,C_Face_Drilling!H25)*IF(ISNUMBER(C_Face_Drilling!$E$25),C_Face_Drilling!$E$25,0) -> 8176.07 | G19: =MAX(0,C_Face_Drilling!I19)*IF(ISNUMBER(C_Face_Drilling!$E$19),C_Face_Drilling!$E$19,0)+MAX(0,C_Face_Drilling!I20)*IF(ISNUMBER(C_Face_Drilling!$E$20),C_Face_Drilling!$E$20,0)+MAX(0,C_Face_Drilling!I21)*IF(ISNUMBER(C_Face_Drilling!$E$21),C_Face_Drilling!$E$21,0)+MAX(0,C_Face_Drilling!I22)*IF(ISNUMBER(C_Face_Drilling!$E$22),C_Face_Drilling!$E$22,0)+MAX(0,C_Face_Drilling!I23)*IF(ISNUMBER(C_Face_Drilling!$E$23),C_Face_Drilling!$E$23,0)+MAX(0,C_Face_Drilling!I24)*IF(ISNUMBER(C_Face_Drilling!$E$24),C_Face_Drilling!$E$24,0)+MAX(0,C_Face_Drilling!I25)*IF(ISNUMBER(C_Face_Drilling!$E$25),C_Face_Drilling!$E$25,0) -> 8933.46 | H19: =MAX(0,C_Face_Drilling!J19)*IF(ISNUMBER(C_Face_Drilling!$E$19),C_Face_Drilling!$E$19,0)+MAX(0,C_Face_Drilling!J20)*IF(ISNUMBER(C_Face_Drilling!$E$20),C_Face_Drilling!$E$20,0)+MAX(0,C_Face_Drilling!J21)*IF(ISNUMBER(C_Face_Drilling!$E$21),C_Face_Drilling!$E$21,0)+MAX(0,C_Face_Drilling!J22)*IF(ISNUMBER(C_Face_Drilling!$E$22),C_Face_Drilling!$E$22,0)+MAX(0,C_Face_Drilling!J23)*IF(ISNUMBER(C_Face_Drilling!$E$23),C_Face_Drilling!$E$23,0)+MAX(0,C_Face_Drilling!J24)*IF(ISNUMBER(C_Face_Drilling!$E$24),C_Face_Drilling!$E$24,0)+MAX(0,C_Face_Drilling!J25)*IF(ISNUMBER(C_Face_Drilling!$E$25),C_Face_Drilling!$E$25,0) -> 18510.19 | I19: =SUM(E19:H19) -> 62645.34 | K19: Quantity x unit price, from C_Face_Drilling
B20: C rods | C20: US$ | E20: =MAX(0,C_Face_Drilling!G29)*IF(ISNUMBER(C_Face_Drilling!$E$29),C_Face_Drilling!$E$29,0)+MAX(0,C_Face_Drilling!G30)*IF(ISNUMBER(C_Face_Drilling!$E$30),C_Face_Drilling!$E$30,0)+MAX(0,C_Face_Drilling!G31)*IF(ISNUMBER(C_Face_Drilling!$E$31),C_Face_Drilling!$E$31,0)+MAX(0,C_Face_Drilling!G32)*IF(ISNUMBER(C_Face_Drilling!$E$32),C_Face_Drilling!$E$32,0)+MAX(0,C_Face_Drilling!G33)*IF(ISNUMBER(C_Face_Drilling!$E$33),C_Face_Drilling!$E$33,0)+MAX(0,C_Face_Drilling!G34)*IF(ISNUMBER(C_Face_Drilling!$E$34),C_Face_Drilling!$E$34,0) -> 15724.48 | F20: =MAX(0,C_Face_Drilling!H29)*IF(ISNUMBER(C_Face_Drilling!$E$29),C_Face_Drilling!$E$29,0)+MAX(0,C_Face_Drilling!H30)*IF(ISNUMBER(C_Face_Drilling!$E$30),C_Face_Drilling!$E$30,0)+MAX(0,C_Face_Drilling!H31)*IF(ISNUMBER(C_Face_Drilling!$E$31),C_Face_Drilling!$E$31,0)+MAX(0,C_Face_Drilling!H32)*IF(ISNUMBER(C_Face_Drilling!$E$32),C_Face_Drilling!$E$32,0)+MAX(0,C_Face_Drilling!H33)*IF(ISNUMBER(C_Face_Drilling!$E$33),C_Face_Drilling!$E$33,0)+MAX(0,C_Face_Drilling!H34)*IF(ISNUMBER(C_Face_Drilling!$E$34),C_Face_Drilling!$E$34,0) -> 16766.38 | G20: =MAX(0,C_Face_Drilling!I29)*IF(ISNUMBER(C_Face_Drilling!$E$29),C_Face_Drilling!$E$29,0)+MAX(0,C_Face_Drilling!I30)*IF(ISNUMBER(C_Face_Drilling!$E$30),C_Face_Drilling!$E$30,0)+MAX(0,C_Face_Drilling!I31)*IF(ISNUMBER(C_Face_Drilling!$E$31),C_Face_Drilling!$E$31,0)+MAX(0,C_Face_Drilling!I32)*IF(ISNUMBER(C_Face_Drilling!$E$32),C_Face_Drilling!$E$32,0)+MAX(0,C_Face_Drilling!I33)*IF(ISNUMBER(C_Face_Drilling!$E$33),C_Face_Drilling!$E$33,0)+MAX(0,C_Face_Drilling!I34)*IF(ISNUMBER(C_Face_Drilling!$E$34),C_Face_Drilling!$E$34,0) -> 15496.1 | H20: =MAX(0,C_Face_Drilling!J29)*IF(ISNUMBER(C_Face_Drilling!$E$29),C_Face_Drilling!$E$29,0)+MAX(0,C_Face_Drilling!J30)*IF(ISNUMBER(C_Face_Drilling!$E$30),C_Face_Drilling!$E$30,0)+MAX(0,C_Face_Drilling!J31)*IF(ISNUMBER(C_Face_Drilling!$E$31),C_Face_Drilling!$E$31,0)+MAX(0,C_Face_Drilling!J32)*IF(ISNUMBER(C_Face_Drilling!$E$32),C_Face_Drilling!$E$32,0)+MAX(0,C_Face_Drilling!J33)*IF(ISNUMBER(C_Face_Drilling!$E$33),C_Face_Drilling!$E$33,0)+MAX(0,C_Face_Drilling!J34)*IF(ISNUMBER(C_Face_Drilling!$E$34),C_Face_Drilling!$E$34,0) -> 28303.61 | I20: =SUM(E20:H20) -> 76290.57 | K20: Quantity x unit price, from C_Face_Drilling
B21: C shanks | C21: US$ | E21: =MAX(0,C_Face_Drilling!G8)*IF(ISNUMBER(C_Face_Drilling!$E$8),C_Face_Drilling!$E$8,0)+MAX(0,C_Face_Drilling!G9)*IF(ISNUMBER(C_Face_Drilling!$E$9),C_Face_Drilling!$E$9,0) -> 44856.5 | F21: =MAX(0,C_Face_Drilling!H8)*IF(ISNUMBER(C_Face_Drilling!$E$8),C_Face_Drilling!$E$8,0)+MAX(0,C_Face_Drilling!H9)*IF(ISNUMBER(C_Face_Drilling!$E$9),C_Face_Drilling!$E$9,0) -> 107342.95 | G21: =MAX(0,C_Face_Drilling!I8)*IF(ISNUMBER(C_Face_Drilling!$E$8),C_Face_Drilling!$E$8,0)+MAX(0,C_Face_Drilling!I9)*IF(ISNUMBER(C_Face_Drilling!$E$9),C_Face_Drilling!$E$9,0) -> 203195.2 | H21: =MAX(0,C_Face_Drilling!J8)*IF(ISNUMBER(C_Face_Drilling!$E$8),C_Face_Drilling!$E$8,0)+MAX(0,C_Face_Drilling!J9)*IF(ISNUMBER(C_Face_Drilling!$E$9),C_Face_Drilling!$E$9,0) -> 133953.3 | I21: =SUM(E21:H21) -> 489347.95 | K21: Quantity x unit price, from C_Face_Drilling
B22: C couplings | C22: US$ | E22: =MAX(0,C_Face_Drilling!G13)*IF(ISNUMBER(C_Face_Drilling!$E$13),C_Face_Drilling!$E$13,0)+MAX(0,C_Face_Drilling!G14)*IF(ISNUMBER(C_Face_Drilling!$E$14),C_Face_Drilling!$E$14,0)+MAX(0,C_Face_Drilling!G15)*IF(ISNUMBER(C_Face_Drilling!$E$15),C_Face_Drilling!$E$15,0) -> 88331.72 | F22: =MAX(0,C_Face_Drilling!H13)*IF(ISNUMBER(C_Face_Drilling!$E$13),C_Face_Drilling!$E$13,0)+MAX(0,C_Face_Drilling!H14)*IF(ISNUMBER(C_Face_Drilling!$E$14),C_Face_Drilling!$E$14,0)+MAX(0,C_Face_Drilling!H15)*IF(ISNUMBER(C_Face_Drilling!$E$15),C_Face_Drilling!$E$15,0) -> 31362.05 | G22: =MAX(0,C_Face_Drilling!I13)*IF(ISNUMBER(C_Face_Drilling!$E$13),C_Face_Drilling!$E$13,0)+MAX(0,C_Face_Drilling!I14)*IF(ISNUMBER(C_Face_Drilling!$E$14),C_Face_Drilling!$E$14,0)+MAX(0,C_Face_Drilling!I15)*IF(ISNUMBER(C_Face_Drilling!$E$15),C_Face_Drilling!$E$15,0) -> 98421.66 | H22: =MAX(0,C_Face_Drilling!J13)*IF(ISNUMBER(C_Face_Drilling!$E$13),C_Face_Drilling!$E$13,0)+MAX(0,C_Face_Drilling!J14)*IF(ISNUMBER(C_Face_Drilling!$E$14),C_Face_Drilling!$E$14,0)+MAX(0,C_Face_Drilling!J15)*IF(ISNUMBER(C_Face_Drilling!$E$15),C_Face_Drilling!$E$15,0) -> 109764.6 | I22: =SUM(E22:H22) -> 327880.03 | K22: Quantity x unit price, from C_Face_Drilling
B23: C centralisers and dollies | C23: US$ | E23: =MAX(0,C_Face_Drilling!G38)*IF(ISNUMBER(C_Face_Drilling!$E$38),C_Face_Drilling!$E$38,0)+MAX(0,C_Face_Drilling!G39)*IF(ISNUMBER(C_Face_Drilling!$E$39),C_Face_Drilling!$E$39,0)+MAX(0,C_Face_Drilling!G40)*IF(ISNUMBER(C_Face_Drilling!$E$40),C_Face_Drilling!$E$40,0)+MAX(0,C_Face_Drilling!G41)*IF(ISNUMBER(C_Face_Drilling!$E$41),C_Face_Drilling!$E$41,0)+MAX(0,C_Face_Drilling!G42)*IF(ISNUMBER(C_Face_Drilling!$E$42),C_Face_Drilling!$E$42,0)+MAX(0,C_Face_Drilling!G43)*IF(ISNUMBER(C_Face_Drilling!$E$43),C_Face_Drilling!$E$43,0)+MAX(0,C_Face_Drilling!G44)*IF(ISNUMBER(C_Face_Drilling!$E$44),C_Face_Drilling!$E$44,0)+MAX(0,C_Face_Drilling!G45)*IF(ISNUMBER(C_Face_Drilling!$E$45),C_Face_Drilling!$E$45,0) -> 0 | F23: =MAX(0,C_Face_Drilling!H38)*IF(ISNUMBER(C_Face_Drilling!$E$38),C_Face_Drilling!$E$38,0)+MAX(0,C_Face_Drilling!H39)*IF(ISNUMBER(C_Face_Drilling!$E$39),C_Face_Drilling!$E$39,0)+MAX(0,C_Face_Drilling!H40)*IF(ISNUMBER(C_Face_Drilling!$E$40),C_Face_Drilling!$E$40,0)+MAX(0,C_Face_Drilling!H41)*IF(ISNUMBER(C_Face_Drilling!$E$41),C_Face_Drilling!$E$41,0)+MAX(0,C_Face_Drilling!H42)*IF(ISNUMBER(C_Face_Drilling!$E$42),C_Face_Drilling!$E$42,0)+MAX(0,C_Face_Drilling!H43)*IF(ISNUMBER(C_Face_Drilling!$E$43),C_Face_Drilling!$E$43,0)+MAX(0,C_Face_Drilling!H44)*IF(ISNUMBER(C_Face_Drilling!$E$44),C_Face_Drilling!$E$44,0)+MAX(0,C_Face_Drilling!H45)*IF(ISNUMBER(C_Face_Drilling!$E$45),C_Face_Drilling!$E$45,0) -> 694.98 | G23: =MAX(0,C_Face_Drilling!I38)*IF(ISNUMBER(C_Face_Drilling!$E$38),C_Face_Drilling!$E$38,0)+MAX(0,C_Face_Drilling!I39)*IF(ISNUMBER(C_Face_Drilling!$E$39),C_Face_Drilling!$E$39,0)+MAX(0,C_Face_Drilling!I40)*IF(ISNUMBER(C_Face_Drilling!$E$40),C_Face_Drilling!$E$40,0)+MAX(0,C_Face_Drilling!I41)*IF(ISNUMBER(C_Face_Drilling!$E$41),C_Face_Drilling!$E$41,0)+MAX(0,C_Face_Drilling!I42)*IF(ISNUMBER(C_Face_Drilling!$E$42),C_Face_Drilling!$E$42,0)+MAX(0,C_Face_Drilling!I43)*IF(ISNUMBER(C_Face_Drilling!$E$43),C_Face_Drilling!$E$43,0)+MAX(0,C_Face_Drilling!I44)*IF(ISNUMBER(C_Face_Drilling!$E$44),C_Face_Drilling!$E$44,0)+MAX(0,C_Face_Drilling!I45)*IF(ISNUMBER(C_Face_Drilling!$E$45),C_Face_Drilling!$E$45,0) -> 24682.99 | H23: =MAX(0,C_Face_Drilling!J38)*IF(ISNUMBER(C_Face_Drilling!$E$38),C_Face_Drilling!$E$38,0)+MAX(0,C_Face_Drilling!J39)*IF(ISNUMBER(C_Face_Drilling!$E$39),C_Face_Drilling!$E$39,0)+MAX(0,C_Face_Drilling!J40)*IF(ISNUMBER(C_Face_Drilling!$E$40),C_Face_Drilling!$E$40,0)+MAX(0,C_Face_Drilling!J41)*IF(ISNUMBER(C_Face_Drilling!$E$41),C_Face_Drilling!$E$41,0)+MAX(0,C_Face_Drilling!J42)*IF(ISNUMBER(C_Face_Drilling!$E$42),C_Face_Drilling!$E$42,0)+MAX(0,C_Face_Drilling!J43)*IF(ISNUMBER(C_Face_Drilling!$E$43),C_Face_Drilling!$E$43,0)+MAX(0,C_Face_Drilling!J44)*IF(ISNUMBER(C_Face_Drilling!$E$44),C_Face_Drilling!$E$44,0)+MAX(0,C_Face_Drilling!J45)*IF(ISNUMBER(C_Face_Drilling!$E$45),C_Face_Drilling!$E$45,0) -> 4374.36 | I23: =SUM(E23:H23) -> 29752.33 | K23: Quantity x unit price, from C_Face_Drilling
B24: Total drilling consumable cost | C24: US$ | E24: =SUM(E19:E23) -> 175938.32 | F24: =SUM(F19:F23) -> 164342.43 | G24: =SUM(G19:G23) -> 350729.41 | H24: =SUM(H19:H23) -> 294906.06 | I24: =SUM(I19:I23) -> 985916.22
B25: m, metres advanced | C25: m | E25: =Advance!E53 -> 270.436 | F25: =Advance!F53 -> 316.617 | G25: =Advance!G53 -> 397.798 | H25: =Advance!H53 -> 390.967 | I25: =Advance!I53 -> 1375.818
B26: UC drill, per metre advanced | C26: US$ / m | E26: =IF(E25=0,0,E24/E25) -> 650.57285 | F26: =IF(F25=0,0,F24/F25) -> 519.0575 | G26: =IF(G25=0,0,G24/G25) -> 881.67716 | H26: =IF(H25=0,0,H24/H25) -> 754.29911 | I26: =IF(I25=0,0,I24/I25) -> 716.60366
B27: DRM, total drilled metres | C27: drilled m | E27: =DRM!E26 -> 29381.1 | F27: =DRM!F26 -> 33867 | G27: =DRM!G26 -> 49347.6 | H27: =DRM!H26 -> 42289.6 | I27: =DRM!I26 -> 154885.3
B28: UC drill per drilled metre | C28: US$ / drilled m | E28: =IF(E27=0,0,E24/E27) -> 5.9881461 | F28: =IF(F27=0,0,F24/F27) -> 4.852583 | G28: =IF(G27=0,0,G24/G27) -> 7.1073246 | H28: =IF(H27=0,0,H24/H27) -> 6.973489 | I28: =IF(I27=0,0,I24/I27) -> 6.3654602
B30: See Notes sheet, note 13.
B32: See Notes sheet, note 14.
B34: 3 EQUATION 3 UC total = UC drill + UC support
B35: Term | C35: Unit | E35: May 2026 | F35: June 2026 | G35: July 2026 | H35: August 2026 | I35: Period total | K35: Note
B36: UC support, from Equation 2 | C36: US$ / m | E36: =E15 -> 1395.9165 | F36: =F15 -> 944.16708 | G36: =G15 -> 969.39503 | H36: =H15 -> 837.16066 | I36: =I15 -> 1009.8509
B37: UC drill, from Equation 1 | C37: US$ / m | E37: =E26 -> 650.57285 | F37: =F26 -> 519.0575 | G37: =G26 -> 881.67716 | H37: =H26 -> 754.29911 | I37: =I26 -> 716.60366
B38: Consumable unit cost, UC drill + UC support | C38: US$ / m | E38: =IF(NOT(ISNUMBER(E37)),E36,E37+E36) -> 2046.4893 | F38: =IF(NOT(ISNUMBER(F37)),F36,F37+F36) -> 1463.2246 | G38: =IF(NOT(ISNUMBER(G37)),G36,G37+G36) -> 1851.0722 | H38: =IF(NOT(ISNUMBER(H37)),H36,H37+H36) -> 1591.4598 | I38: =IF(NOT(ISNUMBER(I37)),I36,I37+I36) -> 1726.4545
B39: UC total | C39: US$ / m | E39: =E38 -> 2046.4893 | F39: =F38 -> 1463.2246 | G39: =G38 -> 1851.0722 | H39: =H38 -> 1591.4598 | I39: =I38 -> 1726.4545
B41: 4 ADVANCE RATE AGAINST CONSUMABLE UNIT COST
B42: Scenario, on the August basis | C42: Metres advanced | E42: If consumption stays at the same total (US$/m) | G42: If consumption stays at the same rate per metre (US$/m) | K42: Change in the first case
B43: Advance as achieved in July | C43: =Advance!$H$53*1 -> 390.967 | E43: =IF(C43=0,0,($H$13+$H$24)/C43) -> 1591.4598 | G43: =$H$38 -> 1591.4598 | K43: =IF($E$43=0,0,E43/$E$43-1) -> 0
B44: Advance 15 per cent higher | C44: =Advance!$H$53*1.15 -> 449.61205 | E44: =IF(C44=0,0,($H$13+$H$24)/C44) -> 1383.8781 | G44: =$H$38 -> 1591.4598 | K44: =IF($E$43=0,0,E44/$E$43-1) -> -0.13043478
B45: Advance 30 per cent higher | C45: =Advance!$H$53*1.3 -> 508.2571 | E45: =IF(C45=0,0,($H$13+$H$24)/C45) -> 1224.1998 | G45: =$H$38 -> 1591.4598 | K45: =IF($E$43=0,0,E45/$E$43-1) -> -0.23076923
B47: See Notes sheet, note 15.
B49: 5 EQUATION 4 WHY THE CONSUMABLE UNIT COST MOVED
B50: Term | C50: Unit | E50: May to June | F50: June to July | G50: July to August | J50: Meaning
B51: U0, unit cost in the earlier month | C51: US$ / m | E51: =E38 -> 2046.4893 | F51: =F38 -> 1463.2246 | G51: =G38 -> 1851.0722
B52: U1, unit cost in the later month | C52: US$ / m | E52: =F38 -> 1463.2246 | F52: =G38 -> 1851.0722 | G52: =H38 -> 1591.4598
B53: C0, total consumable cost in the earlier month | C53: US$ | E53: =E13+E24 -> 553444.39 | F53: =F13+F24 -> 463281.78 | G53: =G13+G24 -> 736352.81
B54: C1, total consumable cost in the later month | C54: US$ | E54: =F13+F24 -> 463281.78 | F54: =G13+G24 -> 736352.81 | G54: =H13+H24 -> 622208.25
B55: A0, metres advanced in the earlier month | C55: m | E55: =E14 -> 270.436 | F55: =F14 -> 316.617 | G55: =G14 -> 397.798
B56: A1, metres advanced in the later month | C56: m | E56: =F14 -> 316.617 | F56: =G14 -> 397.798 | G56: =H14 -> 390.967
B57: Total change in unit cost | C57: US$ / m | E57: =E52-E51 -> -583.26475 | F57: =F52-F51 -> 387.8476 | G57: =G52-G51 -> -259.61242
B58: Change caused by consumption | C58: US$ / m | E58: =IF(E55=0,0,(E54-E53)/E55) -> -333.39722 | F58: =IF(F55=0,0,(F54-F53)/F55) -> 862.46486 | G58: =IF(G55=0,0,(G54-G53)/G55) -> -286.94102 | K58: More or less material used
B59: Change caused by advance rate | C59: US$ / m | E59: =IF(OR(E55=0,E56=0),0,E54*(1/E56-1/E55)) -> -249.86753 | F59: =IF(OR(F55=0,F56=0),0,F54*(1/F56-1/F55)) -> -474.61725 | G59: =IF(OR(G55=0,G56=0),0,G54*(1/G56-1/G55)) -> 27.328598 | K59: Spend spread over more or fewer metres
B60: Check, the two causes sum to the total | C60: US$ / m | E60: =E58+E59-E57 -> 0 | F60: =F58+F59-F57 -> 0 | G60: =G58+G59-G57 -> 0 | K60: Reads 0.000000, exact

Sheet Portal_Analysis
B2: ANALYSIS BY HEADING AND BY PORTAL
B3: May, June, July and August 2026. Every heading in all four months is confirmed to a portal.
B4: The Northern Portal is driven entirely in GSS_02 and GSS_03 ground. The Southern Portal is driven entirely in GSS_01 ground.
B6: 1 DEVELOPMENT ADVANCE BY HEADING
B7: Heading | C7: Portal | E7: May 2026 (m) | F7: June 2026 (m) | G7: July 2026 (m) | H7: August 2026 (m) | I7: Total (m) | K7: Share of portal | L7: Share of mine | N7: Ground support standard
B8: North Decline | C8: Northern | E8: =SUMIFS(Advance!$J$8:$J$48,Advance!$E$8:$E$48,$B8,Advance!$B$8:$B$48,"May 2026") -> 55.882 | F8: =SUMIFS(Advance!$J$8:$J$48,Advance!$E$8:$E$48,$B8,Advance!$B$8:$B$48,"June 2026") -> 81.29 | G8: =SUMIFS(Advance!$J$8:$J$48,Advance!$E$8:$E$48,$B8,Advance!$B$8:$B$48,"July 2026") -> 108.092 | H8: =SUMIFS(Advance!$J$8:$J$48,Advance!$E$8:$E$48,$B8,Advance!$B$8:$B$48,"August 2026") -> 95.452 | I8: =SUM(E8:H8) -> 340.716 | K8: =IFERROR(I8/SUMIFS($I$8:$I$32,$C$8:$C$32,$C8),0) -> 0.45045016 | L8: =IFERROR(I8/SUM($I$8:$I$32),0) -> 0.24764613 | N8: GSS_02, GSS_03
B9: North Shoot Decline (NS_1040_ACC_N) | C9: Northern | E9: =SUMIFS(Advance!$J$8:$J$48,Advance!$E$8:$E$48,$B9,Advance!$B$8:$B$48,"May 2026") -> 0 | F9: =SUMIFS(Advance!$J$8:$J$48,Advance!$E$8:$E$48,$B9,Advance!$B$8:$B$48,"June 2026") -> 71.538 | G9: =SUMIFS(Advance!$J$8:$J$48,Advance!$E$8:$E$48,$B9,Advance!$B$8:$B$48,"July 2026") -> 100.974 | H9: =SUMIFS(Advance!$J$8:$J$48,Advance!$E$8:$E$48,$B9,Advance!$B$8:$B$48,"August 2026") -> 31.787 | I9: =SUM(E9:H9) -> 204.299 | K9: =IFERROR(I9/SUMIFS($I$8:$I$32,$C$8:$C$32,$C9),0) -> 0.27009744 | L9: =IFERROR(I9/SUM($I$8:$I$32),0) -> 0.14849275 | N9: GSS_02, GSS_03
B10: NS_1020_ACC_W | C10: Northern | E10: =SUMIFS(Advance!$J$8:$J$48,Advance!$E$8:$E$48,$B10,Advance!$B$8:$B$48,"May 2026") -> 0 | F10: =SUMIFS(Advance!$J$8:$J$48,Advance!$E$8:$E$48,$B10,Advance!$B$8:$B$48,"June 2026") -> 0 | G10: =SUMIFS(Advance!$J$8:$J$48,Advance!$E$8:$E$48,$B10,Advance!$B$8:$B$48,"July 2026") -> 0 | H10: =SUMIFS(Advance!$J$8:$J$48,Advance!$E$8:$E$48,$B10,Advance!$B$8:$B$48,"August 2026") -> 57.558 | I10: =SUM(E10:H10) -> 57.558 | K10: =IFERROR(I10/SUMIFS($I$8:$I$32,$C$8:$C$32,$C10),0) -> 0.076095665 | L10: =IFERROR(I10/SUM($I$8:$I$32),0) -> 0.041835475 | N10: GSS_02
B11: NS_1020_RAD_N | C11: Northern | E11: =SUMIFS(Advance!$J$8:$J$48,Advance!$E$8:$E$48,$B11,Advance!$B$8:$B$48,"May 2026") -> 0 | F11: =SUMIFS(Advance!$J$8:$J$48,Advance!$E$8:$E$48,$B11,Advance!$B$8:$B$48,"June 2026") -> 0 | G11: =SUMIFS(Advance!$J$8:$J$48,Advance!$E$8:$E$48,$B11,Advance!$B$8:$B$48,"July 2026") -> 0 | H11: =SUMIFS(Advance!$J$8:$J$48,Advance!$E$8:$E$48,$B11,Advance!$B$8:$B$48,"August 2026") -> 32.709 | I11: =SUM(E11:H11) -> 32.709 | K11: =IFERROR(I11/SUMIFS($I$8:$I$32,$C$8:$C$32,$C11),0) -> 0.043243565 | L11: =IFERROR(I11/SUM($I$8:$I$32),0) -> 0.02377422 | N11: GSS_02
B12: N_1040_ACCESS (NS 1040 access) | C12: Northern | E12: =SUMIFS(Advance!$J$8:$J$48,Advance!$E$8:$E$48,$B12,Advance!$B$8:$B$48,"May 2026") -> 27.178 | F12: =SUMIFS(Advance!$J$8:$J$48,Advance!$E$8:$E$48,$B12,Advance!$B$8:$B$48,"June 2026") -> 0 | G12: =SUMIFS(Advance!$J$8:$J$48,Advance!$E$8:$E$48,$B12,Advance!$B$8:$B$48,"July 2026") -> 0 | H12: =SUMIFS(Advance!$J$8:$J$48,Advance!$E$8:$E$48,$B12,Advance!$B$8:$B$48,"August 2026") -> 0 | I12: =SUM(E12:H12) -> 27.178 | K12: =IFERROR(I12/SUMIFS($I$8:$I$32,$C$8:$C$32,$C12),0) -> 0.0359312 | L12: =IFERROR(I12/SUM($I$8:$I$32),0) -> 0.019754066 | N12: GSS_01, GSS_02
B13: NS_1040_DSP02_W | C13: Northern | E13: =SUMIFS(Advance!$J$8:$J$48,Advance!$E$8:$E$48,$B13,Advance!$B$8:$B$48,"May 2026") -> 0 | F13: =SUMIFS(Advance!$J$8:$J$48,Advance!$E$8:$E$48,$B13,Advance!$B$8:$B$48,"June 2026") -> 0 | G13: =SUMIFS(Advance!$J$8:$J$48,Advance!$E$8:$E$48,$B13,Advance!$B$8:$B$48,"July 2026") -> 25.788 | H13: =SUMIFS(Advance!$J$8:$J$48,Advance!$E$8:$E$48,$B13,Advance!$B$8:$B$48,"August 2026") -> 0 | I13: =SUM(E13:H13) -> 25.788 | K13: =IFERROR(I13/SUMIFS($I$8:$I$32,$C$8:$C$32,$C13),0) -> 0.034093523 | L13: =IFERROR(I13/SUM($I$8:$I$32),0) -> 0.018743758 | N13: GSS_02
B14: NS_1040_LSP01_W | C14: Northern | E14: =SUMIFS(Advance!$J$8:$J$48,Advance!$E$8:$E$48,$B14,Advance!$B$8:$B$48,"May 2026") -> 0 | F14: =SUMIFS(Advance!$J$8:$J$48,Advance!$E$8:$E$48,$B14,Advance!$B$8:$B$48,"June 2026") -> 0 | G14: =SUMIFS(Advance!$J$8:$J$48,Advance!$E$8:$E$48,$B14,Advance!$B$8:$B$48,"July 2026") -> 24.352 | H14: =SUMIFS(Advance!$J$8:$J$48,Advance!$E$8:$E$48,$B14,Advance!$B$8:$B$48,"August 2026") -> 0 | I14: =SUM(E14:H14) -> 24.352 | K14: =IFERROR(I14/SUMIFS($I$8:$I$32,$C$8:$C$32,$C14),0) -> 0.032195032 | L14: =IFERROR(I14/SUM($I$8:$I$32),0) -> 0.017700016 | N14: GSS_03
B15: NS_1040_SP_E | C15: Northern | E15: =SUMIFS(Advance!$J$8:$J$48,Advance!$E$8:$E$48,$B15,Advance!$B$8:$B$48,"May 2026") -> 0 | F15: =SUMIFS(Advance!$J$8:$J$48,Advance!$E$8:$E$48,$B15,Advance!$B$8:$B$48,"June 2026") -> 23.007 | G15: =SUMIFS(Advance!$J$8:$J$48,Advance!$E$8:$E$48,$B15,Advance!$B$8:$B$48,"July 2026") -> 0 | H15: =SUMIFS(Advance!$J$8:$J$48,Advance!$E$8:$E$48,$B15,Advance!$B$8:$B$48,"August 2026") -> 0 | I15: =SUM(E15:H15) -> 23.007 | K15: =IFERROR(I15/SUMIFS($I$8:$I$32,$C$8:$C$32,$C15),0) -> 0.030416848 | L15: =IFERROR(I15/SUM($I$8:$I$32),0) -> 0.016722415 | N15: GSS_02
B16: NS_1020_DSMP | C16: Northern | E16: =SUMIFS(Advance!$J$8:$J$48,Advance!$E$8:$E$48,$B16,Advance!$B$8:$B$48,"May 2026") -> 0 | F16: =SUMIFS(Advance!$J$8:$J$48,Advance!$E$8:$E$48,$B16,Advance!$B$8:$B$48,"June 2026") -> 0 | G16: =SUMIFS(Advance!$J$8:$J$48,Advance!$E$8:$E$48,$B16,Advance!$B$8:$B$48,"July 2026") -> 0 | H16: =SUMIFS(Advance!$J$8:$J$48,Advance!$E$8:$E$48,$B16,Advance!$B$8:$B$48,"August 2026") -> 10.505 | I16: =SUM(E16:H16) -> 10.505 | K16: =IFERROR(I16/SUMIFS($I$8:$I$32,$C$8:$C$32,$C16),0) -> 0.013888338 | L16: =IFERROR(I16/SUM($I$8:$I$32),0) -> 0.0076354576 | N16: GSS_02
B17: NS_1020_LSP01 | C17: Northern | E17: =SUMIFS(Advance!$J$8:$J$48,Advance!$E$8:$E$48,$B17,Advance!$B$8:$B$48,"May 2026") -> 0 | F17: =SUMIFS(Advance!$J$8:$J$48,Advance!$E$8:$E$48,$B17,Advance!$B$8:$B$48,"June 2026") -> 0 | G17: =SUMIFS(Advance!$J$8:$J$48,Advance!$E$8:$E$48,$B17,Advance!$B$8:$B$48,"July 2026") -> 0 | H17: =SUMIFS(Advance!$J$8:$J$48,Advance!$E$8:$E$48,$B17,Advance!$B$8:$B$48,"August 2026") -> 10.278 | I17: =SUM(E17:H17) -> 10.278 | K17: =IFERROR(I17/SUMIFS($I$8:$I$32,$C$8:$C$32,$C17),0) -> 0.013588228 | L17: =IFERROR(I17/SUM($I$8:$I$32),0) -> 0.0074704648 | N17: GSS_02
B18: South Decline | C18: Southern | E18: =SUMIFS(Advance!$J$8:$J$48,Advance!$E$8:$E$48,$B18,Advance!$B$8:$B$48,"May 2026") -> 75.154 | F18: =SUMIFS(Advance!$J$8:$J$48,Advance!$E$8:$E$48,$B18,Advance!$B$8:$B$48,"June 2026") -> 70.356 | G18: =SUMIFS(Advance!$J$8:$J$48,Advance!$E$8:$E$48,$B18,Advance!$B$8:$B$48,"July 2026") -> 95.817 | H18: =SUMIFS(Advance!$J$8:$J$48,Advance!$E$8:$E$48,$B18,Advance!$B$8:$B$48,"August 2026") -> 66.894 | I18: =SUM(E18:H18) -> 308.221 | K18: =IFERROR(I18/SUMIFS($I$8:$I$32,$C$8:$C$32,$C18),0) -> 0.49758971 | L18: =IFERROR(I18/SUM($I$8:$I$32),0) -> 0.22402745 | N18: GSS_01
B19: MS900_DDR_N | C19: Southern | E19: =SUMIFS(Advance!$J$8:$J$48,Advance!$E$8:$E$48,$B19,Advance!$B$8:$B$48,"May 2026") -> 65.685 | F19: =SUMIFS(Advance!$J$8:$J$48,Advance!$E$8:$E$48,$B19,Advance!$B$8:$B$48,"June 2026") -> 0 | G19: =SUMIFS(Advance!$J$8:$J$48,Advance!$E$8:$E$48,$B19,Advance!$B$8:$B$48,"July 2026") -> 0 | H19: =SUMIFS(Advance!$J$8:$J$48,Advance!$E$8:$E$48,$B19,Advance!$B$8:$B$48,"August 2026") -> 0 | I19: =SUM(E19:H19) -> 65.685 | K19: =IFERROR(I19/SUMIFS($I$8:$I$32,$C$8:$C$32,$C19),0) -> 0.10604138 | L19: =IFERROR(I19/SUM($I$8:$I$32),0) -> 0.047742507 | N19: GSS_01
... B32: MS_0900_SP_E | C32: Southern | E32: =SUMIFS(Advance!$J$8:$J$48,Advance!$E$8:$E$48,$B32,Advance!$B$8:$B$48,"May 2026") -> 0 | F32: =SUMIFS(Advance!$J$8:$J$48,Advance!$E$8:$E$48,$B32,Advance!$B$8:$B$48,"June 2026") -> 0 | G32: =SUMIFS(Advance!$J$8:$J$48,Advance!$E$8:$E$48,$B32,Advance!$B$8:$B$48,"July 2026") -> 2.2 | H32: =SUMIFS(Advance!$J$8:$J$48,Advance!$E$8:$E$48,$B32,Advance!$B$8:$B$48,"August 2026") -> 0 | I32: =SUM(E32:H32) -> 2.2 | K32: =IFERROR(I32/SUMIFS($I$8:$I$32,$C$8:$C$32,$C32),0) -> 0.0035516638 | L32: =IFERROR(I32/SUM($I$8:$I$32),0) -> 0.0015990487 | N32: GSS_01
B33: Total, both portals | E33: =SUM(E8:E32) -> 270.436 | F33: =SUM(F8:F32) -> 316.617 | G33: =SUM(G8:G32) -> 397.798 | H33: =SUM(H8:H32) -> 390.967 | I33: =SUM(I8:I32) -> 1375.818
B35: 2 PORTAL AND WHOLE MINE RESULTS
B36: Measure | C36: Unit | E36: Northern Portal | F36: Southern Portal | G36: Whole mine | L36: Note
B37: Metres advanced, May 2026 | C37: m | E37: =SUMIFS($E$8:$E$32,$C$8:$C$32,"Northern") -> 83.06 | F37: =SUMIFS($E$8:$E$32,$C$8:$C$32,"Southern") -> 187.376 | G37: =E37+F37 -> 270.436
B38: Metres advanced, June 2026 | C38: m | E38: =SUMIFS($F$8:$F$32,$C$8:$C$32,"Northern") -> 175.835 | F38: =SUMIFS($F$8:$F$32,$C$8:$C$32,"Southern") -> 140.782 | G38: =E38+F38 -> 316.617
B39: Metres advanced, July 2026 | C39: m | E39: =SUMIFS($G$8:$G$32,$C$8:$C$32,"Northern") -> 259.206 | F39: =SUMIFS($G$8:$G$32,$C$8:$C$32,"Southern") -> 138.592 | G39: =E39+F39 -> 397.798
B40: Metres advanced, August 2026 | C40: m | E40: =SUMIFS($H$8:$H$32,$C$8:$C$32,"Northern") -> 238.289 | F40: =SUMIFS($H$8:$H$32,$C$8:$C$32,"Southern") -> 152.678 | G40: =E40+F40 -> 390.967
B41: Metres advanced, May to August | C41: m | E41: =E37+E38+E39+E40 -> 756.39 | F41: =F37+F38+F39+F40 -> 619.428 | G41: =G37+G38+G39+G40 -> 1375.818 | N41: Measured by survey
B43: Ground support consumable cost, May 2026 | C43: US$ | E43: =Unit_Cost!E13*Inputs!$C$25 -> 149771.43 | F43: =Unit_Cost!E13*Inputs!$D$25 -> 227734.64 | G43: =Unit_Cost!E13 -> 377506.07 | N43: Split, see Inputs
B44: Ground support consumable cost, June 2026 | C44: US$ | E44: =Unit_Cost!F13*Inputs!$C$26 -> 179716.59 | F44: =Unit_Cost!F13*Inputs!$D$26 -> 119222.76 | G44: =Unit_Cost!F13 -> 298939.35 | N44: Split, see Inputs
B45: Ground support consumable cost, July 2026 | C45: US$ | E45: =Unit_Cost!G13*Inputs!$C$27 -> 255241.02 | F45: =Unit_Cost!G13*Inputs!$D$27 -> 130382.38 | G45: =Unit_Cost!G13 -> 385623.4 | N45: Split, see Inputs
B46: Ground support consumable cost, August 2026 | C46: US$ | E46: =Unit_Cost!H13*Inputs!$C$28 -> 199486.18 | F46: =Unit_Cost!H13*Inputs!$D$28 -> 127816.01 | G46: =Unit_Cost!H13 -> 327302.19 | N46: Split, see Inputs
B47: Ground support consumable cost, May to August | C47: US$ | E47: =E43+E44+E45+E46 -> 784215.22 | F47: =F43+F44+F45+F46 -> 605155.8 | G47: =G43+G44+G45+G46 -> 1389371
B49: UC support, May 2026 | C49: US$ / m | E49: =IF(E37=0,0,E43/E37) -> 1803.1716 | F49: =IF(F37=0,0,F43/F37) -> 1215.3885 | G49: =IF(G37=0,0,G43/G37) -> 1395.9165
B50: UC support, June 2026 | C50: US$ / m | E50: =IF(E38=0,0,E44/E38) -> 1022.0752 | F50: =IF(F38=0,0,F44/F38) -> 846.8608 | G50: =IF(G38=0,0,G44/G38) -> 944.16708
B51: UC support, July 2026 | C51: US$ / m | E51: =IF(E39=0,0,E45/E39) -> 984.70336 | F51: =IF(F39=0,0,F45/F39) -> 940.76415 | G51: =IF(G39=0,0,G45/G39) -> 969.39503
B52: UC support, August 2026 | C52: US$ / m | E52: =IF(E40=0,0,E46/E40) -> 837.16066 | F52: =IF(F40=0,0,F46/F40) -> 837.16066 | G52: =IF(G40=0,0,G46/G40) -> 837.16066
B53: UC support, May to August | C53: US$ / m | E53: =IF(E41=0,0,E47/E41) -> 1036.7869 | F53: =IF(F41=0,0,F47/F41) -> 976.95906 | G53: =IF(G41=0,0,G47/G41) -> 1009.8509
B55: Drilling consumable cost, May 2026 | C55: US$ | E55: =Unit_Cost!E24*Inputs!$C$34 -> 71007.964 | F55: =Unit_Cost!E24*Inputs!$D$34 -> 104930.36 | G55: =Unit_Cost!E24 -> 175938.32 | N55: Split by measured drilled metres
B56: Drilling consumable cost, June 2026 | C56: US$ | E56: =Unit_Cost!F24*Inputs!$C$35 -> 92546.368 | F56: =Unit_Cost!F24*Inputs!$D$35 -> 71796.062 | G56: =Unit_Cost!F24 -> 164342.43 | N56: Split by measured drilled metres
B57: Drilling consumable cost, July 2026 | C57: US$ | E57: =Unit_Cost!G24*Inputs!$C$36 -> 227175.94 | F57: =Unit_Cost!G24*Inputs!$D$36 -> 123553.47 | G57: =Unit_Cost!G24 -> 350729.41 | N57: Split by measured drilled metres
B58: Drilling consumable cost, August 2026 | C58: US$ | E58: =Unit_Cost!H24*Inputs!$C$37 -> 189614.95 | F58: =Unit_Cost!H24*Inputs!$D$37 -> 105291.11 | G58: =Unit_Cost!H24 -> 294906.06 | N58: Split by measured drilled metres
B59: Drilling consumable cost, May to August | C59: US$ | E59: =E55+E56+E57+E58 -> 580345.22 | F59: =F55+F56+F57+F58 -> 405571 | G59: =G55+G56+G57+G58 -> 985916.22
B61: UC drill, May to August | C61: US$ / m | E61: =IF(E41=0,0,E59/E41) -> 767.2566 | F61: =IF(F41=0,0,F59/F41) -> 654.75083 | G61: =IF(G41=0,0,G59/G41) -> 716.60366
B62: UC total consumable, May to August | C62: US$ / m | E62: =IF(E41=0,0,(E47+E59)/E41) -> 1804.0435 | F62: =IF(F41=0,0,(F47+F59)/F41) -> 1631.7099 | G62: =IF(G41=0,0,(G47+G59)/G41) -> 1726.4545 | N62: Support plus drilling
B64: 3 RECONCILIATION CHECKS
B65: Check | C65: Unit | E65: Value | F65: Result
B66: Sum of headings less both portals combined | E66: =SUM($I$8:$I$32)-G41 -> 0 | F66: =IF(ABS(E66)<0.000001,"Reconciles","CHECK") -> Reconciles
B67: Northern plus Southern metres less combined | E67: =E41+F41-G41 -> 0 | F67: =IF(ABS(E67)<0.000001,"Reconciles","CHECK") -> Reconciles
B68: Northern plus Southern cost less combined | E68: =E47+F47-G47 -> 0 | F68: =IF(ABS(E68)<0.000001,"Reconciles","CHECK") -> Reconciles
B69: May to August mine cost less Equation 2 total | E69: =G47-(Unit_Cost!E13+Unit_Cost!F13+Unit_Cost!G13+Unit_Cost!H13) -> 0 | F69: =IF(ABS(E69)<0.000001,"Reconciles","CHECK") -> Reconciles

Sheet Pareto
B2: PARETO ANALYSIS OF CONSUMABLE COST
B3: P i = C i ÷ Σ C i × 100 Cum i = Σ ( C 1 … C i ) ÷ Σ C i × 100
B4: All priced consumables, ground support and drilling, over the whole four month period May to August 2026, not a single month.
B6: Rank and consumable | C6: Activity | E6: Total cost (US$) | F6: Cost per metre (US$/m) | H6: Share of total | I6: Cumulative share | K6: In the top 80 per cent | L6: Note
B7: 1. MD bolt 2.4 m galvanised | C7: Ground support | E7: =B_Ground_Support!N11 -> 904575.32 | F7: =B_Ground_Support!O11 -> 657.48182 | H7: =IF($E$39=0,0,E7/$E$39) -> 0.38082776 | I7: =IF($E$39=0,0,SUM($E$7:E7)/$E$39) -> 0.38082776 | K7: ="Yes" -> Yes
B8: 2. Shank T45 RD520/525 D45 L525 | C8: Face drilling | E8: =C_Face_Drilling!N9 -> 473326.75 | F8: =C_Face_Drilling!O9 -> 344.03297 | H8: =IF($E$39=0,0,E8/$E$39) -> 0.19927137 | I8: =IF($E$39=0,0,SUM($E$7:E8)/$E$39) -> 0.58009913 | K8: =IF(I8<=0.8,"Yes",IF(I7<0.8,"Yes","No")) -> Yes
B9: 3. Mesh 2.40 x 4.50 m galvanised | C9: Ground support | E9: =B_Ground_Support!N21 -> 353779.93 | F9: =B_Ground_Support!O21 -> 257.14152 | H9: =IF($E$39=0,0,E9/$E$39) -> 0.14894196 | I9: =IF($E$39=0,0,SUM($E$7:E9)/$E$39) -> 0.72904109 | K9: =IF(I9<=0.8,"Yes",IF(I8<0.8,"Yes","No")) -> Yes
B10: 4. Bit adaptor T45F / T38M | C10: Face drilling | E10: =C_Face_Drilling!N13 -> 227125.95 | F10: =C_Face_Drilling!O13 -> 165.0843 | H10: =IF($E$39=0,0,E10/$E$39) -> 0.095620415 | I10: =IF($E$39=0,0,SUM($E$7:E10)/$E$39) -> 0.8246615 | K10: =IF(I10<=0.8,"Yes",IF(I9<0.8,"Yes","No")) -> Yes
B11: 5. Coupling sleeve T45 / T38 | C11: Face drilling | E11: =C_Face_Drilling!N14 -> 100124.44 | F11: =C_Face_Drilling!O14 -> 72.77448 | H11: =IF($E$39=0,0,E11/$E$39) -> 0.042152561 | I11: =IF($E$39=0,0,SUM($E$7:E11)/$E$39) -> 0.86681407 | K11: =IF(I11<=0.8,"Yes",IF(I10<0.8,"Yes","No")) -> No
B12: 6. Friction bolt 47 x 2400 galvanised | C12: Ground support | E12: =B_Ground_Support!N10 -> 97769.314 | F12: =B_Ground_Support!O10 -> 71.06268 | H12: =IF($E$39=0,0,E12/$E$39) -> 0.041161049 | I12: =IF($E$39=0,0,SUM($E$7:E12)/$E$39) -> 0.90797511 | K12: =IF(I12<=0.8,"Yes",IF(I11<0.8,"Yes","No")) -> No
B13: 7. Drifter rod T38 R39 A340 L=491, speed rod | C13: Face drilling | E13: =C_Face_Drilling!N30 -> 46647 | F13: =C_Face_Drilling!O30 -> 33.904921 | H13: =IF($E$39=0,0,E13/$E$39) -> 0.019638467 | I13: =IF($E$39=0,0,SUM($E$7:E13)/$E$39) -> 0.92761358 | K13: =IF(I13<=0.8,"Yes",IF(I12<0.8,"Yes","No")) -> No
B14: 8. Friction bolt 47 x 900 galvanised | C14: Ground support | E14: =B_Ground_Support!N9 -> 19990.699 | F14: =B_Ground_Support!O9 -> 14.530046 | H14: =IF($E$39=0,0,E14/$E$39) -> 0.0084161184 | I14: =IF($E$39=0,0,SUM($E$7:E14)/$E$39) -> 0.9360297 | K14: =IF(I14<=0.8,"Yes",IF(I13<0.8,"Yes","No")) -> No
B15: 9. Boring centraliser dia 41 mm | C15: Face drilling | E15: =C_Face_Drilling!N41 -> 18848.3 | F15: =C_Face_Drilling!O41 -> 13.699704 | H15: =IF($E$39=0,0,E15/$E$39) -> 0.0079351666 | I15: =IF($E$39=0,0,SUM($E$7:E15)/$E$39) -> 0.94396487 | K15: =IF(I15<=0.8,"Yes",IF(I14<0.8,"Yes","No")) -> No
B16: 10. Shank T38 RD520/525 D45 L525 | C16: Face drilling | E16: =C_Face_Drilling!N8 -> 16021.2 | F16: =C_Face_Drilling!O8 -> 11.644854 | H16: =IF($E$39=0,0,E16/$E$39) -> 0.0067449527 | I16: =IF($E$39=0,0,SUM($E$7:E16)/$E$39) -> 0.95070982 | K16: =IF(I16<=0.8,"Yes",IF(I15<0.8,"Yes","No")) -> No
B17: 11. Speedy bit A340 45 mm XT49 | C17: Face drilling | E17: =C_Face_Drilling!N25 -> 15467.62 | F17: =C_Face_Drilling!O25 -> 11.24249 | H17: =IF($E$39=0,0,E17/$E$39) -> 0.0065118946 | I17: =IF($E$39=0,0,SUM($E$7:E17)/$E$39) -> 0.95722171 | K17: =IF(I17<=0.8,"Yes",IF(I16<0.8,"Yes","No")) -> No
B18: 12. Reaming bit A340 102 mm | C18: Face drilling | E18: =C_Face_Drilling!N23 -> 14419.86 | F18: =C_Face_Drilling!O23 -> 10.480936 | H18: =IF($E$39=0,0,E18/$E$39) -> 0.0060707858 | I18: =IF($E$39=0,0,SUM($E$7:E18)/$E$39) -> 0.9632925 | K18: =IF(I18<=0.8,"Yes",IF(I17<0.8,"Yes","No")) -> No
B19: 13. Drifter rod T38 H35 A340 L=370, drilling steel | C19: Face drilling | E19: =C_Face_Drilling!N29 -> 13468.95 | F19: =C_Face_Drilling!O29 -> 9.789776 | H19: =IF($E$39=0,0,E19/$E$39) -> 0.0056704511 | I19: =IF($E$39=0,0,SUM($E$7:E19)/$E$39) -> 0.96896295 | K19: =IF(I19<=0.8,"Yes",IF(I18<0.8,"Yes","No")) -> No
B20: 14. Cable bolt twin strand bulbed 15.2 mm | C20: Cable bolting | E20: =D_Cable_Bolting!N8 -> 10006.578 | F20: =D_Cable_Bolting!O8 -> 7.2731845 | H20: =IF($E$39=0,0,E20/$E$39) -> 0.0042127866 | I20: =IF($E$39=0,0,SUM($E$7:E20)/$E$39) -> 0.97317574 | K20: =IF(I20<=0.8,"Yes",IF(I19<0.8,"Yes","No")) -> No
B21: 15. T38 extension round rod L=3050 mm | C21: Face drilling | E21: =C_Face_Drilling!N32 -> 9840.33 | F21: =C_Face_Drilling!O32 -> 7.1523486 | H21: =IF($E$39=0,0,E21/$E$39) -> 0.0041427958 | I21: =IF($E$39=0,0,SUM($E$7:E21)/$E$39) -> 0.97731853 | K21: =IF(I21<=0.8,"Yes",IF(I20<0.8,"Yes","No")) -> No
B22: 16. A340 45 mm button bit | C22: Face drilling | E22: =C_Face_Drilling!N20 -> 8445.51 | F22: =C_Face_Drilling!O20 -> 6.1385372 | H22: =IF($E$39=0,0,E22/$E$39) -> 0.0035555742 | I22: =IF($E$39=0,0,SUM($E$7:E22)/$E$39) -> 0.98087411 | K22: =IF(I22<=0.8,"Yes",IF(I21<0.8,"Yes","No")) -> No
B23: 17. A340 43 mm button bit | C23: Face drilling | E23: =C_Face_Drilling!N19 -> 8315 | F23: =C_Face_Drilling!O19 -> 6.0436773 | H23: =IF($E$39=0,0,E23/$E$39) -> 0.0035006293 | I23: =IF($E$39=0,0,SUM($E$7:E23)/$E$39) -> 0.98437474 | K23: =IF(I23<=0.8,"Yes",IF(I22<0.8,"Yes","No")) -> No
B24: 18. T38 64 mm button bit | C24: Face drilling | E24: =C_Face_Drilling!N24 -> 7504.2 | F24: =C_Face_Drilling!O24 -> 5.4543552 | H24: =IF($E$39=0,0,E24/$E$39) -> 0.0031592811 | I24: =IF($E$39=0,0,SUM($E$7:E24)/$E$39) -> 0.98753402 | K24: =IF(I24<=0.8,"Yes",IF(I23<0.8,"Yes","No")) -> No
B25: 19. Boring centraliser dia 48 mm | C25: Face drilling | E25: =C_Face_Drilling!N42 -> 5201.01 | F25: =C_Face_Drilling!O42 -> 3.7803038 | H25: =IF($E$39=0,0,E25/$E$39) -> 0.0021896341 | I25: =IF($E$39=0,0,SUM($E$7:E25)/$E$39) -> 0.98972365 | K25: =IF(I25<=0.8,"Yes",IF(I24<0.8,"Yes","No")) -> No
B26: 20. A340 51 mm retrac bit | C26: Face drilling | E26: =C_Face_Drilling!N22 -> 4706.5 | F26: =C_Face_Drilling!O22 -> 3.420874 | H26: =IF($E$39=0,0,E26/$E$39) -> 0.0019814446 | I26: =IF($E$39=0,0,SUM($E$7:E26)/$E$39) -> 0.9917051 | K26: =IF(I26<=0.8,"Yes",IF(I25<0.8,"Yes","No")) -> No
B27: 21. MF rod T38 R39 L=3050 mm | C27: Face drilling | E27: =C_Face_Drilling!N31 -> 4395.9 | F27: =C_Face_Drilling!O31 -> 3.1951174 | H27: =IF($E$39=0,0,E27/$E$39) -> 0.0018506814 | I27: =IF($E$39=0,0,SUM($E$7:E27)/$E$39) -> 0.99355578 | K27: =IF(I27<=0.8,"Yes",IF(I26<0.8,"Yes","No")) -> No
B28: 22. A340 48 mm TC button bit | C28: Face drilling | E28: =C_Face_Drilling!N21 -> 3786.65 | F28: =C_Face_Drilling!O21 -> 2.7522899 | H28: =IF($E$39=0,0,E28/$E$39) -> 0.0015941861 | I28: =IF($E$39=0,0,SUM($E$7:E28)/$E$39) -> 0.99514996 | K28: =IF(I28<=0.8,"Yes",IF(I27<0.8,"Yes","No")) -> No
B29: 23. Friction bolt 39 x 900 galvanised | C29: Ground support | E29: =B_Ground_Support!N8 -> 3249.1776 | F29: =B_Ground_Support!O8 -> 2.3616333 | H29: =IF($E$39=0,0,E29/$E$39) -> 0.0013679094 | I29: =IF($E$39=0,0,SUM($E$7:E29)/$E$39) -> 0.99651787 | K29: =IF(I29<=0.8,"Yes",IF(I28<0.8,"Yes","No")) -> No
B30: 24. Bolting centraliser dia 66 mm guide | C30: Face drilling | E30: =C_Face_Drilling!N43 -> 2752.58 | F30: =C_Face_Drilling!O43 -> 2.0006861 | H30: =IF($E$39=0,0,E30/$E$39) -> 0.0011588409 | I30: =IF($E$39=0,0,SUM($E$7:E30)/$E$39) -> 0.99767671 | K30: =IF(I30<=0.8,"Yes",IF(I29<0.8,"Yes","No")) -> No
B31: 25. Bolting centraliser dia 70 mm front | C31: Face drilling | E31: =C_Face_Drilling!N38 -> 1128 | F31: =C_Face_Drilling!O38 -> 0.81987588 | H31: =IF($E$39=0,0,E31/$E$39) -> 0.00047488994 | I31: =IF($E$39=0,0,SUM($E$7:E31)/$E$39) -> 0.9981516 | K31: =IF(I31<=0.8,"Yes",IF(I30<0.8,"Yes","No")) -> No
B32: 26. Extension rod T38 R39 L=915 mm | C32: Face drilling | E32: =C_Face_Drilling!N33 -> 1108.5 | F32: =C_Face_Drilling!O33 -> 0.8057025 | H32: =IF($E$39=0,0,E32/$E$39) -> 0.0004666804 | I32: =IF($E$39=0,0,SUM($E$7:E32)/$E$39) -> 0.99861828 | K32: =IF(I32<=0.8,"Yes",IF(I31<0.8,"Yes","No")) -> No
B33: 27. MF rod T38 R39 L=915 mm | C33: Face drilling | E33: =C_Face_Drilling!N34 -> 829.89 | F33: =C_Face_Drilling!O34 -> 0.60319752 | H33: =IF($E$39=0,0,E33/$E$39) -> 0.00034938511 | I33: =IF($E$39=0,0,SUM($E$7:E33)/$E$39) -> 0.99896767 | K33: =IF(I33<=0.8,"Yes",IF(I32<0.8,"Yes","No")) -> No
B34: 28. T38 dolly 47 mm | C34: Face drilling | E34: =C_Face_Drilling!N44 -> 770.4 | F34: =C_Face_Drilling!O44 -> 0.55995779 | H34: =IF($E$39=0,0,E34/$E$39) -> 0.00032433972 | I34: =IF($E$39=0,0,SUM($E$7:E34)/$E$39) -> 0.99929201 | K34: =IF(I34<=0.8,"Yes",IF(I33<0.8,"Yes","No")) -> No
B35: 29. Coupling sleeve T38 / T38 | C35: Face drilling | E35: =C_Face_Drilling!N15 -> 629.64 | F35: =C_Face_Drilling!O15 -> 0.45764774 | H35: =IF($E$39=0,0,E35/$E$39) -> 0.00026507952 | I35: =IF($E$39=0,0,SUM($E$7:E35)/$E$39) -> 0.99955709 | K35: =IF(I35<=0.8,"Yes",IF(I34<0.8,"Yes","No")) -> No
B36: 30. T38 dolly 39 mm | C36: Face drilling | E36: =C_Face_Drilling!N45 -> 481.5 | F36: =C_Face_Drilling!O45 -> 0.34997362 | H36: =IF($E$39=0,0,E36/$E$39) -> 0.00020271233 | I36: =IF($E$39=0,0,SUM($E$7:E36)/$E$39) -> 0.9997598 | K36: =IF(I36<=0.8,"Yes",IF(I35<0.8,"Yes","No")) -> No
B37: 31. Boring centraliser dia 48 mm | C37: Face drilling | E37: =C_Face_Drilling!N40 -> 366.54 | F37: =C_Face_Drilling!O40 -> 0.26641605 | H37: =IF($E$39=0,0,E37/$E$39) -> 0.00015431397 | I37: =IF($E$39=0,0,SUM($E$7:E37)/$E$39) -> 0.99991412 | K37: =IF(I37<=0.8,"Yes",IF(I36<0.8,"Yes","No")) -> No
B38: 32. Bolting centraliser dia 70 mm back | C38: Face drilling | E38: =C_Face_Drilling!N39 -> 204 | F38: =C_Face_Drilling!O39 -> 0.14827543 | H38: =IF($E$39=0,0,E38/$E$39) -> 8.588435e-05 | I38: =IF($E$39=0,0,SUM($E$7:E38)/$E$39) -> 1 | K38: =IF(I38<=0.8,"Yes",IF(I37<0.8,"Yes","No")) -> No
B39: Total | E39: =SUM(E7:E38) -> 2375287.2 | F39: =SUM(F7:F38) -> 1726.4545 | I39: =IF($E$39=0,0,SUM($E$7:$E$38)/$E$39) -> 1
B41: Yes marks every item needed to reach 80 per cent of cumulative cost.
B43: See Notes sheet, note 16.

Sheet Triangulation
B2: RECONCILIATION OF CONSUMPTION ACROSS THE THREE MINE RECORDS
B3: Source: EOM stock counts, LiveMine installation records and Stock Usage issue registers, May to August 2026.
B4: No record has been adjusted to match another. Where they disagree, the disagreement is the finding.
B6: 1 WHAT EACH RECORD ACTUALLY MEASURES
B7: Record | C7: Measures | E7: What it captures | I7: Typically
B8: Stock count | C8: Left the store | E8: Everything drawn out of store between two counts, whether installed, broken, lost or still on the stockpile | I8: Highest
B9: LiveMine | C9: Went into the rock | E9: Material the operator recorded as installed, by shift and heading | I9: Middle
B10: Issue register | C10: Signed for | E10: Only transactions written on a docket. Bulk drops and untracked draws are missed | I10: Lowest
B12: See Notes sheet, note 17.
B14: 2 THE THREE RECORDS COMPARED
B15: Consumable | C15: Month | E15: Stock count | F15: LiveMine | G15: Issue register | I15: Costed in this model | K15: Spread, highest over lowest | L15: Bought but not installed | N15: Comment
B16: MD bolt 2.4 m | C16: May | E16: =MAX(0,Consumption_PL!I15) -> 2575 | F16: 2956 | G16: =Consumption_Issues!F14 -> 1852 | I16: =E16 -> 2575 | K16: =IF(NOT(ISNUMBER(F16)),"n/a",IF(MIN(E16,F16,G16)<=0,"n/a",MAX(E16,F16,G16)/MIN(E16,F16,G16))) -> 1.5961123 | L16: =IF(NOT(ISNUMBER(F16)),"",E16-F16) -> -381 | N16: =IF(OR(E16<=0,NOT(ISNUMBER(F16))),"",IF(ABS(E16-F16)/E16>0.25,"Investigate","Consistent")) -> Consistent
B17: MD bolt 2.4 m | C17: June | E17: =MAX(0,Consumption_PL!M15) -> 3674 | F17: 3191 | G17: =Consumption_Issues!G14 -> 885 | I17: =E17 -> 3674 | K17: =IF(NOT(ISNUMBER(F17)),"n/a",IF(MIN(E17,F17,G17)<=0,"n/a",MAX(E17,F17,G17)/MIN(E17,F17,G17))) -> 4.1514124 | L17: =IF(NOT(ISNUMBER(F17)),"",E17-F17) -> 483 | N17: =IF(OR(E17<=0,NOT(ISNUMBER(F17))),"",IF(ABS(E17-F17)/E17>0.25,"Investigate","Consistent")) -> Consistent
B18: MD bolt 2.4 m | C18: July | E18: =MAX(0,Consumption_PL!Q15) -> 4163 | F18: 3961 | G18: =Consumption_Issues!H14 -> 1602 | I18: =E18 -> 4163 | K18: =IF(NOT(ISNUMBER(F18)),"n/a",IF(MIN(E18,F18,G18)<=0,"n/a",MAX(E18,F18,G18)/MIN(E18,F18,G18))) -> 2.5986267 | L18: =IF(NOT(ISNUMBER(F18)),"",E18-F18) -> 202 | N18: =IF(OR(E18<=0,NOT(ISNUMBER(F18))),"",IF(ABS(E18-F18)/E18>0.25,"Investigate","Consistent")) -> Consistent
B19: MD bolt 2.4 m | C19: August | E19: =MAX(0,Consumption_PL!U15) -> 3319 | F19: not supplied | G19: =Consumption_Issues!I14 -> 4339 | I19: =E19 -> 3319 | K19: =IF(NOT(ISNUMBER(F19)),"n/a",IF(MIN(E19,F19,G19)<=0,"n/a",MAX(E19,F19,G19)/MIN(E19,F19,G19))) -> n/a | L19: =IF(NOT(ISNUMBER(F19)),"",E19-F19) | N19: =IF(OR(E19<=0,NOT(ISNUMBER(F19))),"",IF(ABS(E19-F19)/E19>0.25,"Investigate","Consistent"))
B20: Friction bolt 47 x 2400 | C20: May | E20: =MAX(0,Consumption_PL!I14) -> 743 | F20: 1025 | G20: =Consumption_Issues!F13 -> 156 | I20: =E20 -> 743 | K20: =IF(NOT(ISNUMBER(F20)),"n/a",IF(MIN(E20,F20,G20)<=0,"n/a",MAX(E20,F20,G20)/MIN(E20,F20,G20))) -> 6.5705128 | L20: =IF(NOT(ISNUMBER(F20)),"",E20-F20) -> -282 | N20: =IF(OR(E20<=0,NOT(ISNUMBER(F20))),"",IF(ABS(E20-F20)/E20>0.25,"Investigate","Consistent")) -> Investigate
B21: Friction bolt 47 x 2400 | C21: June | E21: =MAX(0,Consumption_PL!M14) -> 949 | F21: 671 | G21: =Consumption_Issues!G13 -> 1350 | I21: =E21 -> 949 | K21: =IF(NOT(ISNUMBER(F21)),"n/a",IF(MIN(E21,F21,G21)<=0,"n/a",MAX(E21,F21,G21)/MIN(E21,F21,G21))) -> 2.0119225 | L21: =IF(NOT(ISNUMBER(F21)),"",E21-F21) -> 278 | N21: =IF(OR(E21<=0,NOT(ISNUMBER(F21))),"",IF(ABS(E21-F21)/E21>0.25,"Investigate","Consistent")) -> Investigate
B22: Friction bolt 47 x 2400 | C22: July | E22: =MAX(0,Consumption_PL!Q14) -> 2159 | F22: 2114 | G22: =Consumption_Issues!H13 -> 728 | I22: =E22 -> 2159 | K22: =IF(NOT(ISNUMBER(F22)),"n/a",IF(MIN(E22,F22,G22)<=0,"n/a",MAX(E22,F22,G22)/MIN(E22,F22,G22))) -> 2.9656593 | L22: =IF(NOT(ISNUMBER(F22)),"",E22-F22) -> 45 | N22: =IF(OR(E22<=0,NOT(ISNUMBER(F22))),"",IF(ABS(E22-F22)/E22>0.25,"Investigate","Consistent")) -> Consistent
B23: Friction bolt 47 x 2400 | C23: August | E23: =MAX(0,Consumption_PL!U14) -> 2286 | F23: not supplied | G23: =Consumption_Issues!I13 -> 2234 | I23: =E23 -> 2286 | K23: =IF(NOT(ISNUMBER(F23)),"n/a",IF(MIN(E23,F23,G23)<=0,"n/a",MAX(E23,F23,G23)/MIN(E23,F23,G23))) -> n/a | L23: =IF(NOT(ISNUMBER(F23)),"",E23-F23) | N23: =IF(OR(E23<=0,NOT(ISNUMBER(F23))),"",IF(ABS(E23-F23)/E23>0.25,"Investigate","Consistent"))
B24: Friction bolt 47 x 900 | C24: May | E24: =MAX(0,Consumption_PL!I13) -> 300 | F24: 78 | G24: =Consumption_Issues!F12 -> 26 | I24: =E24 -> 300 | K24: =IF(NOT(ISNUMBER(F24)),"n/a",IF(MIN(E24,F24,G24)<=0,"n/a",MAX(E24,F24,G24)/MIN(E24,F24,G24))) -> 11.538462 | L24: =IF(NOT(ISNUMBER(F24)),"",E24-F24) -> 222 | N24: =IF(OR(E24<=0,NOT(ISNUMBER(F24))),"",IF(ABS(E24-F24)/E24>0.25,"Investigate","Consistent")) -> Investigate
B25: Friction bolt 47 x 900 | C25: June | E25: =MAX(0,Consumption_PL!M13) -> 529 | F25: 345 | G25: =Consumption_Issues!G12 -> 150 | I25: =E25 -> 529 | K25: =IF(NOT(ISNUMBER(F25)),"n/a",IF(MIN(E25,F25,G25)<=0,"n/a",MAX(E25,F25,G25)/MIN(E25,F25,G25))) -> 3.5266667 | L25: =IF(NOT(ISNUMBER(F25)),"",E25-F25) -> 184 | N25: =IF(OR(E25<=0,NOT(ISNUMBER(F25))),"",IF(ABS(E25-F25)/E25>0.25,"Investigate","Consistent")) -> Investigate
B26: Friction bolt 47 x 900 | C26: July | E26: =MAX(0,Consumption_PL!Q13) -> 401 | F26: 293 | G26: =Consumption_Issues!H12 -> 270 | I26: =E26 -> 401 | K26: =IF(NOT(ISNUMBER(F26)),"n/a",IF(MIN(E26,F26,G26)<=0,"n/a",MAX(E26,F26,G26)/MIN(E26,F26,G26))) -> 1.4851852 | L26: =IF(NOT(ISNUMBER(F26)),"",E26-F26) -> 108 | N26: =IF(OR(E26<=0,NOT(ISNUMBER(F26))),"",IF(ABS(E26-F26)/E26>0.25,"Investigate","Consistent")) -> Investigate
B27: Friction bolt 47 x 900 | C27: August | E27: =MAX(0,Consumption_PL!U13) -> 320 | F27: not supplied | G27: =Consumption_Issues!I12 -> 446 | I27: =E27 -> 320 | K27: =IF(NOT(ISNUMBER(F27)),"n/a",IF(MIN(E27,F27,G27)<=0,"n/a",MAX(E27,F27,G27)/MIN(E27,F27,G27))) -> n/a | L27: =IF(NOT(ISNUMBER(F27)),"",E27-F27) | N27: =IF(OR(E27<=0,NOT(ISNUMBER(F27))),"",IF(ABS(E27-F27)/E27>0.25,"Investigate","Consistent"))
B28: Friction bolt 39 x 900 | C28: May | E28: =MAX(0,Consumption_PL!I12) -> 183 | F28: 6 | G28: =Consumption_Issues!F11 -> 0 | I28: =E28 -> 183 | K28: =IF(NOT(ISNUMBER(F28)),"n/a",IF(MIN(E28,F28,G28)<=0,"n/a",MAX(E28,F28,G28)/MIN(E28,F28,G28))) -> n/a | L28: =IF(NOT(ISNUMBER(F28)),"",E28-F28) -> 177 | N28: =IF(OR(E28<=0,NOT(ISNUMBER(F28))),"",IF(ABS(E28-F28)/E28>0.25,"Investigate","Consistent")) -> Investigate
B29: Friction bolt 39 x 900 | C29: June | E29: =MAX(0,Consumption_PL!M12) -> 177 | F29: 37 | G29: =Consumption_Issues!G11 -> 0 | I29: =E29 -> 177 | K29: =IF(NOT(ISNUMBER(F29)),"n/a",IF(MIN(E29,F29,G29)<=0,"n/a",MAX(E29,F29,G29)/MIN(E29,F29,G29))) -> n/a | L29: =IF(NOT(ISNUMBER(F29)),"",E29-F29) -> 140 | N29: =IF(OR(E29<=0,NOT(ISNUMBER(F29))),"",IF(ABS(E29-F29)/E29>0.25,"Investigate","Consistent")) -> Investigate
B30: Friction bolt 39 x 900 | C30: July | E30: =MAX(0,Consumption_PL!Q12) -> 0 | F30: 5 | G30: =Consumption_Issues!H11 -> 150 | I30: =E30 -> 0 | K30: =IF(NOT(ISNUMBER(F30)),"n/a",IF(MIN(E30,F30,G30)<=0,"n/a",MAX(E30,F30,G30)/MIN(E30,F30,G30))) -> n/a | L30: =IF(NOT(ISNUMBER(F30)),"",E30-F30) -> -5 | N30: =IF(OR(E30<=0,NOT(ISNUMBER(F30))),"",IF(ABS(E30-F30)/E30>0.25,"Investigate","Consistent"))
B31: Friction bolt 39 x 900 | C31: August | E31: =MAX(0,Consumption_PL!U12) -> 80 | F31: not supplied | G31: =Consumption_Issues!I11 -> 150 | I31: =E31 -> 80 | K31: =IF(NOT(ISNUMBER(F31)),"n/a",IF(MIN(E31,F31,G31)<=0,"n/a",MAX(E31,F31,G31)/MIN(E31,F31,G31))) -> n/a | L31: =IF(NOT(ISNUMBER(F31)),"",E31-F31) | N31: =IF(OR(E31<=0,NOT(ISNUMBER(F31))),"",IF(ABS(E31-F31)/E31>0.25,"Investigate","Consistent"))
B32: Mesh 2.40 x 4.50 m | C32: May | E32: =MAX(0,Consumption_PL!I19) -> 2291 | F32: 396 | G32: =Consumption_Issues!F18 -> 200 | I32: =E32 -> 2291 | K32: =IF(NOT(ISNUMBER(F32)),"n/a",IF(MIN(E32,F32,G32)<=0,"n/a",MAX(E32,F32,G32)/MIN(E32,F32,G32))) -> 11.455 | L32: =IF(NOT(ISNUMBER(F32)),"",E32-F32) -> 1895 | N32: =IF(OR(E32<=0,NOT(ISNUMBER(F32))),"",IF(ABS(E32-F32)/E32>0.25,"Investigate","Consistent")) -> Investigate
B33: Mesh 2.40 x 4.50 m | C33: June | E33: =MAX(0,Consumption_PL!M19) -> 408 | F33: 483 | G33: =Consumption_Issues!G18 -> 230 | I33: =E33 -> 408 | K33: =IF(NOT(ISNUMBER(F33)),"n/a",IF(MIN(E33,F33,G33)<=0,"n/a",MAX(E33,F33,G33)/MIN(E33,F33,G33))) -> 2.1 | L33: =IF(NOT(ISNUMBER(F33)),"",E33-F33) -> -75 | N33: =IF(OR(E33<=0,NOT(ISNUMBER(F33))),"",IF(ABS(E33-F33)/E33>0.25,"Investigate","Consistent")) -> Consistent
B34: Mesh 2.40 x 4.50 m | C34: July | E34: =MAX(0,Consumption_PL!Q19) -> 821 | F34: 676 | G34: =Consumption_Issues!H18 -> 369 | I34: =E34 -> 821 | K34: =IF(NOT(ISNUMBER(F34)),"n/a",IF(MIN(E34,F34,G34)<=0,"n/a",MAX(E34,F34,G34)/MIN(E34,F34,G34))) -> 2.2249322 | L34: =IF(NOT(ISNUMBER(F34)),"",E34-F34) -> 145 | N34: =IF(OR(E34<=0,NOT(ISNUMBER(F34))),"",IF(ABS(E34-F34)/E34>0.25,"Investigate","Consistent")) -> Consistent
B35: Mesh 2.40 x 4.50 m | C35: August | E35: =MAX(0,Consumption_PL!U19) -> 769 | F35: not supplied | G35: =Consumption_Issues!I18 -> 799 | I35: =E35 -> 769 | K35: =IF(NOT(ISNUMBER(F35)),"n/a",IF(MIN(E35,F35,G35)<=0,"n/a",MAX(E35,F35,G35)/MIN(E35,F35,G35))) -> n/a | L35: =IF(NOT(ISNUMBER(F35)),"",E35-F35) | N35: =IF(OR(E35<=0,NOT(ISNUMBER(F35))),"",IF(ABS(E35-F35)/E35>0.25,"Investigate","Consistent"))
B36: Cable bolt | C36: May | E36: =MAX(0,Consumption_PL!I43) -> 27 | F36: 0 | G36: =Consumption_Issues!F42 -> 0 | I36: =E36 -> 27 | K36: =IF(NOT(ISNUMBER(F36)),"n/a",IF(MIN(E36,F36,G36)<=0,"n/a",MAX(E36,F36,G36)/MIN(E36,F36,G36))) -> n/a | L36: =IF(NOT(ISNUMBER(F36)),"",E36-F36) -> 27 | N36: =IF(OR(E36<=0,NOT(ISNUMBER(F36))),"",IF(ABS(E36-F36)/E36>0.25,"Investigate","Consistent")) -> Investigate
B37: Cable bolt | C37: June | E37: =MAX(0,Consumption_PL!M43) -> 0 | F37: 66 | G37: =Consumption_Issues!G42 -> 51 | I37: =E37 -> 0 | K37: =IF(NOT(ISNUMBER(F37)),"n/a",IF(MIN(E37,F37,G37)<=0,"n/a",MAX(E37,F37,G37)/MIN(E37,F37,G37))) -> n/a | L37: =IF(NOT(ISNUMBER(F37)),"",E37-F37) -> -66 | N37: =IF(OR(E37<=0,NOT(ISNUMBER(F37))),"",IF(ABS(E37-F37)/E37>0.25,"Investigate","Consistent"))
B38: Cable bolt | C38: July | E38: =MAX(0,Consumption_PL!Q43) -> 60 | F38: 40 | G38: =Consumption_Issues!H42 -> 18 | I38: =E38 -> 60 | K38: =IF(NOT(ISNUMBER(F38)),"n/a",IF(MIN(E38,F38,G38)<=0,"n/a",MAX(E38,F38,G38)/MIN(E38,F38,G38))) -> 3.3333333 | L38: =IF(NOT(ISNUMBER(F38)),"",E38-F38) -> 20 | N38: =IF(OR(E38<=0,NOT(ISNUMBER(F38))),"",IF(ABS(E38-F38)/E38>0.25,"Investigate","Consistent")) -> Investigate
B39: Cable bolt | C39: August | E39: =MAX(0,Consumption_PL!U43) -> 60 | F39: not supplied | G39: =Consumption_Issues!I42 -> 69 | I39: =E39 -> 60 | K39: =IF(NOT(ISNUMBER(F39)),"n/a",IF(MIN(E39,F39,G39)<=0,"n/a",MAX(E39,F39,G39)/MIN(E39,F39,G39))) -> n/a | L39: =IF(NOT(ISNUMBER(F39)),"",E39-F39) | N39: =IF(OR(E39<=0,NOT(ISNUMBER(F39))),"",IF(ABS(E39-F39)/E39>0.25,"Investigate","Consistent"))
B40: Total, all items, May to August | E40: =SUM(E16:E39) -> 26294 | F40: =SUMIF(F16:F39,"<>") -> 16343 | G40: =SUM(G16:G39) -> 16074 | I40: =SUM(I16:I39) -> 26294 | L40: =SUM(L16:L39) -> 3117
B42: 3 WHAT THE GAP MEANS, FOR THE MONTHS WHERE LIVEMINE WAS SUPPLIED
B43: Measure | E43: Units | I43: Share of stock count | N43: Meaning
B44: Left the store, by stock count | E44: =E16+E17+E18+E20+E21+E22+E24+E25+E26+E28+E29+E30+E32+E33+E34+E36+E37+E38 -> 19460 | I44: =IF($E$44=0,0,E44/$E$44) -> 1 | N44: The mine paid for all of this
B45: Went into the rock, by LiveMine | E45: =F16+F17+F18+F20+F21+F22+F24+F25+F26+F28+F29+F30+F32+F33+F34+F36+F37+F38 -> 16343 | I45: =IF($E$44=0,0,E45/$E$44) -> 0.83982528 | N45: This is what the ground actually received
B46: Difference, bought but not installed | E46: =(E16+E17+E18+E20+E21+E22+E24+E25+E26+E28+E29+E30+E32+E33+E34+E36+E37+E38)-(F16+F17+F18+F20+F21+F22+F24+F25+F26+F28+F29+F30+F32+F33+F34+F36+F37+F38) -> 3117 | I46: =IF($E$44=0,0,E46/$E$44) -> 0.16017472 | N46: Breakage, loss, and stock still lying at the portal
B48: See Notes sheet, note 18.
B50: 4 THE SAME GAP IN MONEY
B51: Measure | E51: Cost (US$), May to July | I51: US$ per metre advanced | N51: Meaning
B52: Ground support cost as costed, on the stock count | E52: =Unit_Cost!E13+Unit_Cost!F13+Unit_Cost!G13 -> 1062068.8 | I52: =IF((Advance!E53+Advance!F53+Advance!G53)=0,0,E52/(Advance!E53+Advance!F53+Advance!G53)) -> 1078.4056 | N52: The months where an installation record exists
B53: Ground support cost of the material actually installed | E53: =IF($E$44=0,0,(Unit_Cost!E13+Unit_Cost!F13+Unit_Cost!G13)*$E$45/$E$44) -> 891952.25 | I53: =IF((Advance!E53+Advance!F53+Advance!G53)=0,0,E53/(Advance!E53+Advance!F53+Advance!G53)) -> 905.67228 | N53: Scaled by the installed share above. It is an estimate, not a separate costing
B54: Cost of material bought but not installed | E54: =E52-E53 -> 170116.57 | I54: =IF((Advance!E53+Advance!F53+Advance!G53)=0,0,E54/(Advance!E53+Advance!F53+Advance!G53)) -> 172.73331 | N54: The size of the prize if the loss is closed
B56: See Notes sheet, note 19.
B58: 5 CHART DATA
B59: Record | C59: Units, period
B60: Stock count | C60: =E40 -> 26294
B61: LiveMine | C61: =F40 -> 16343
B62: Issue register | C62: =G40 -> 16074

Sheet May_Question
B2: WHY MAY SHOWS LOW METRES AND A HIGH CONSUMPTION RATE
B3: Question raised by the mine manager. Every figure below is calculated on this sheet from the same sources as the rest of the workbook.
B6: 1 THE TWO FIGURES THE QUESTION IS ABOUT
B7: Measure | C7: Unit | E7: May | F7: June | G7: July | H7: August | I7: Period | K7: Rank of May
B8: Metres advanced | C8: m | E8: =Advance!E53 -> 270.436 | F8: =Advance!F53 -> 316.617 | G8: =Advance!G53 -> 397.798 | H8: =Advance!H53 -> 390.967 | I8: =Advance!I53 -> 1375.818 | M8: Lowest of the four months
B9: Total consumable cost | C9: US$ | E9: =Unit_Cost!E13+Unit_Cost!E24 -> 553444.39 | F9: =Unit_Cost!F13+Unit_Cost!F24 -> 463281.78 | G9: =Unit_Cost!G13+Unit_Cost!G24 -> 736352.81 | H9: =Unit_Cost!H13+Unit_Cost!H24 -> 622208.25 | I9: =Unit_Cost!I13+Unit_Cost!I24 -> 2375287.2
B10: Consumable cost per metre, as counted | C10: US$ / m | E10: =IF(Advance!E53=0,0,(Unit_Cost!E13+Unit_Cost!E24)/Advance!E53) -> 2046.4893 | F10: =IF(Advance!F53=0,0,(Unit_Cost!F13+Unit_Cost!F24)/Advance!F53) -> 1463.2246 | G10: =IF(Advance!G53=0,0,(Unit_Cost!G13+Unit_Cost!G24)/Advance!G53) -> 1851.0722 | H10: =IF(Advance!H53=0,0,(Unit_Cost!H13+Unit_Cost!H24)/Advance!H53) -> 1591.4598 | I10: =IF(Advance!I53=0,0,(Unit_Cost!I13+Unit_Cost!I24)/Advance!I53) -> 1726.4545 | M10: Highest of the four months
B12: See Notes sheet, note 20.
B14: 2 IS THE MAY CONSUMPTION REAL? THE MESH TEST
B15: Record | C15: Unit | E15: May | F15: June | G15: July | H15: August | K15: What it measures
B16: Mesh sheets, stock count | C16: sheets | E16: =MAX(0,B_Ground_Support!G21) -> 2291 | F16: =MAX(0,B_Ground_Support!H21) -> 408 | G16: =MAX(0,B_Ground_Support!I21) -> 821 | H16: =MAX(0,B_Ground_Support!J21) -> 769 | M16: Everything that left the store
B17: Mesh sheets, LiveMine installed | C17: sheets | E17: 396 | F17: 483 | G17: 676 | H17: not supplied | M17: What the operator recorded as installed
B19: Sheets per metre advanced | C19: Unit | E19: May | F19: June | G19: July | H19: August | K19: Comparison
B20: From the stock count | C20: sheets / m | E20: =IF(OR(NOT(ISNUMBER(E16)),Advance!E53=0),"",E16/Advance!E53) -> 8.4715053 | F20: =IF(OR(NOT(ISNUMBER(F16)),Advance!F53=0),"",F16/Advance!F53) -> 1.2886232 | G20: =IF(OR(NOT(ISNUMBER(G16)),Advance!G53=0),"",G16/Advance!G53) -> 2.0638616 | H20: =IF(OR(NOT(ISNUMBER(H16)),Advance!H53=0),"",H16/Advance!H53) -> 1.9669179 | M20: May is four to six times every other month
B21: From LiveMine | C21: sheets / m | E21: =IF(OR(NOT(ISNUMBER(E17)),Advance!E53=0),"",E17/Advance!E53) -> 1.4643021 | F21: =IF(OR(NOT(ISNUMBER(F17)),Advance!F53=0),"",F17/Advance!F53) -> 1.5255024 | G21: =IF(OR(NOT(ISNUMBER(G17)),Advance!G53=0),"",G17/Advance!G53) -> 1.6993549 | H21: =IF(OR(NOT(ISNUMBER(H17)),Advance!H53=0),"",H17/Advance!H53) | M21: May sits with June, July and the design
B22: Design standard, both GSS drawings | C22: sheets / m | E22: =Plan_vs_Actual!E18 -> 1.5 | F22: =Plan_vs_Actual!F18 -> 1.5 | G22: =Plan_vs_Actual!G18 -> 1.5 | H22: =Plan_vs_Actual!H18 -> 1.5 | M22: 6 sheets per 4.0 m cut
B24: See Notes sheet, note 21.
B26: 3 THE SIZE OF THE COUNTING ERROR
B27: Measure | C27: Unit | E27: Value | K27: Basis
B28: Mesh sheets counted as used in May | C28: sheets | E28: =E16 -> 2291 | M28: End of month stock reconciliation
B29: Mesh sheets recorded as installed in May | C29: sheets | E29: =E17 -> 396 | M29: LiveMine installation record
B30: Sheets counted but not installed | C30: sheets | E30: =E16-E17 -> 1895 | M30: The difference between the two rows above
B31: Unit cost of one mesh sheet | C31: US$ | E31: =B_Ground_Support!$E$21 -> 82.485411 | M31: Mine price list, converted at the rate on Inputs
B32: Value of the overstatement | C32: US$ | E32: =E30*E31 -> 156309.85 | M32: Sheets counted but not installed, multiplied by the unit cost
B35: 4 MAY WITH THE COUNTING ERROR REMOVED
B36: Measure | C36: Unit | E36: May 2026 | K36: Comment
B37: Consumable cost per metre, as counted | C37: US$ / m | E37: =E10 -> 2046.4893 | M37: The figure the question is about
B38: Less the mesh overstatement, per metre | C38: US$ / m | E38: =IF(Advance!E53=0,0,E32/Advance!E53) -> 577.99203 | M38: The counting error expressed per metre advanced
B39: Consumable cost per metre, corrected | C39: US$ / m | E39: =E37-E38 -> 1468.4973 | M39: May on the same basis as the other three months
B40: Mean of June, July and August | C40: US$ / m | E40: =AVERAGE(F10:H10) -> 1635.2522 | M40: The three months with no known counting error
B41: Corrected May against that mean | C41: US$ / m | E41: =E39-E40 -> -166.75488 | M41: Negative means May was cheaper per metre than the other months
B43: See Notes sheet, note 22.
B45: 5 ANSWER IN ONE LINE
B46: May did not have a high consumption rate. One mesh stock count was overstated, and that single error accounts for the whole difference.
B48: See Notes sheet, note 23.

Sheet Charts
B2: FIGURES
B3: Each figure is followed by the table of values it was drawn from.
B6: Figure 1. Ground support consumable cost per metre, by month
B29: Values used in Figure 1
B30: Month | C30: US$ per metre
B31: May | C31: =Unit_Cost!E15 -> 1395.9165
B32: June | C32: =Unit_Cost!F15 -> 944.16708
B33: July | C33: =Unit_Cost!G15 -> 969.39503
B34: August | C34: =Unit_Cost!H15 -> 837.16066
B38: Figure 2. Development advance, by month
B61: Values used in Figure 2
B62: Month | C62: Metres advanced
B63: May | C63: =Advance!E53 -> 270.436
B64: June | C64: =Advance!F53 -> 316.617
B65: July | C65: =Advance!G53 -> 397.798
B66: August | C66: =Advance!H53 -> 390.967
B70: Figure 3. Total consumable cost, ten largest items, May to August 2026
B93: Values used in Figure 3
B94: Consumable | C94: Total cost (US$)
B95: MD bolt 2.4 m | C95: =Pareto!E7 -> 904575.32
B96: Shank T45 | C96: =Pareto!E8 -> 473326.75
B97: Mesh 2.4 x 4.5 m | C97: =Pareto!E9 -> 353779.93
B98: Bit adaptor T45/T38 | C98: =Pareto!E10 -> 227125.95
B99: Coupling T45/T38 | C99: =Pareto!E11 -> 100124.44
B100: Friction bolt 47x2400 | C100: =Pareto!E12 -> 97769.314
B101: Speed rod T38 | C101: =Pareto!E13 -> 46647
B102: Friction bolt 47x900 | C102: =Pareto!E14 -> 19990.699
B103: Boring centraliser 41 | C103: =Pareto!E15 -> 18848.3
B104: Shank T38 | C104: =Pareto!E16 -> 16021.2
B108: Figure 4. Share of total consumable cost, ten largest items
B131: Values used in Figure 4
B132: Consumable | C132: Share of total cost
B133: MD bolt 2.4 m | C133: =Pareto!H7 -> 0.38082776
B134: Shank T45 | C134: =Pareto!H8 -> 0.19927137
B135: Mesh 2.4 x 4.5 m | C135: =Pareto!H9 -> 0.14894196
B136: Bit adaptor T45/T38 | C136: =Pareto!H10 -> 0.095620415
B137: Coupling T45/T38 | C137: =Pareto!H11 -> 0.042152561
B138: Friction bolt 47x2400 | C138: =Pareto!H12 -> 0.041161049
B139: Speed rod T38 | C139: =Pareto!H13 -> 0.019638467
B140: Friction bolt 47x900 | C140: =Pareto!H14 -> 0.0084161184
B141: Boring centraliser 41 | C141: =Pareto!H15 -> 0.0079351666
B142: Shank T38 | C142: =Pareto!H16 -> 0.0067449527
B146: Figure 5. Bolts installed per metre advanced
B169: Values used in Figure 5
B170: Month | C170: Bolts per metre
B171: May | C171: =IF(Advance!E53=0,0,(MAX(0,B_Ground_Support!G8)+MAX(0,B_Ground_Support!G9)+MAX(0,B_Ground_Support!G10)+MAX(0,B_Ground_Support!G11))/Advance!E53) -> 14.055081
B172: June | C172: =IF(Advance!F53=0,0,(MAX(0,B_Ground_Support!H8)+MAX(0,B_Ground_Support!H9)+MAX(0,B_Ground_Support!H10)+MAX(0,B_Ground_Support!H11))/Advance!F53) -> 16.831061
B173: July | C173: =IF(Advance!G53=0,0,(MAX(0,B_Ground_Support!I8)+MAX(0,B_Ground_Support!I9)+MAX(0,B_Ground_Support!I10)+MAX(0,B_Ground_Support!I11))/Advance!G53) -> 16.900537
B174: August | C174: =IF(Advance!H53=0,0,(MAX(0,B_Ground_Support!J8)+MAX(0,B_Ground_Support!J9)+MAX(0,B_Ground_Support!J10)+MAX(0,B_Ground_Support!J11))/Advance!H53) -> 15.359353
B178: Figure 6. Mesh sheets installed per metre advanced
B201: Values used in Figure 6
B202: Month | C202: Mesh sheets per metre
B203: May | C203: =IF(Advance!E53=0,0,MAX(0,B_Ground_Support!G21)/Advance!E53) -> 8.4715053
B204: June | C204: =IF(Advance!F53=0,0,MAX(0,B_Ground_Support!H21)/Advance!F53) -> 1.2886232
B205: July | C205: =IF(Advance!G53=0,0,MAX(0,B_Ground_Support!I21)/Advance!G53) -> 2.0638616
B206: August | C206: =IF(Advance!H53=0,0,MAX(0,B_Ground_Support!J21)/Advance!H53) -> 1.9669179
B210: Figure 7. Consumption recorded by each measure, May to July 2026
B233: Values used in Figure 7
B234: Measure | C234: Units
B235: Stock count | C235: =Consumption_Compare!F176 -> 34961
B236: Issue register | C236: =Consumption_Compare!G176 -> 17102
B240: Figure 8. Metres driven in each ground class, May to August 2026
B263: Values used in Figure 8
B264: Ground class | C264: Metres
B265: GSS_01 good | C265: =Plan_vs_Actual!H8 -> 152.678
B266: GSS_02 fair | C266: =Plan_vs_Actual!H9 -> 238.289
B267: GSS_03 poor | C267: =Plan_vs_Actual!H10 -> 0
B271: Figure 9. Cost per metre by portal, May to August 2026
B294: Values used in Figure 9
B295: Portal | C295: US$ per metre
B296: Northern Portal | C296: =Portal_Analysis!E53 -> 1036.7869
B297: Southern Portal | C297: =Portal_Analysis!F53 -> 976.95906
B301: Figure 10. Development advance by heading, the eight largest
B332: Values used in Figure 10
B333: Heading | C333: Metres advanced
B334: North Decline | C334: =Portal_Analysis!H8 -> 95.452
B335: South Decline | C335: =Portal_Analysis!H18 -> 66.894
B336: North Shoot Decline (NS_1040_ACC_N) | C336: =Portal_Analysis!H9 -> 31.787
B337: MS900_DDR_N | C337: =Portal_Analysis!H19 -> 0
B338: NS_1020_ACC_W | C338: =Portal_Analysis!H10 -> 57.558
B339: MS_0900_RAD_E | C339: =Portal_Analysis!H20 -> 0
B340: MS_900_RAD_E | C340: =Portal_Analysis!H21 -> 32.861
B341: NS_1020_RAD_N | C341: =Portal_Analysis!H11 -> 32.709

Sheet Daily_Log
B2: DAILY LOG
B3: Source: LiveMine daily records, 1 May to 24 August 2026. One row per day.
B4: Rows to 24 August are loaded from LiveMine. Continue below in the same format, one row per day.
B6: Date | C6: Shift | D6: Portal | E6: Heading | F6: Ground class | H6: Advance (m) | I6: MD bolts installed | J6: Split sets installed | K6: Mesh sheets installed | M6: Holes drilled | N6: Rods changed | P6: Items returned serviceable | Q6: Source or remark
B7: 2026-05-01 | H7: 8 | I7: 70 | J7: 11 | K7: 13 | M7: 146 | Q7: LiveMine
B8: 2026-05-02 | H8: 8 | I8: 74 | J8: 27 | K8: 6 | M8: 100 | Q8: LiveMine
B9: 2026-05-03 | H9: 8 | I9: 90 | J9: 25 | K9: 15 | M9: 155 | Q9: LiveMine
B10: 2026-05-04 | H10: 8 | I10: 49 | J10: 11 | K10: 4 | M10: 123 | Q10: LiveMine
B11: 2026-05-05 | H11: 4 | I11: 63 | J11: 14 | K11: 9 | M11: 78 | Q11: LiveMine
B12: 2026-05-06 | H12: 8 | I12: 85 | J12: 66 | K12: 18 | M12: 149 | Q12: LiveMine
B13: 2026-05-07 | H13: 4 | I13: 97 | J13: 37 | K13: 16 | M13: 89 | Q13: LiveMine
B14: 2026-05-08 | H14: 8 | I14: 45 | J14: 13 | K14: 6 | M14: 118 | Q14: LiveMine
B15: 2026-05-09 | H15: 20 | I15: 113 | J15: 53 | K15: 16 | M15: 195 | Q15: LiveMine
B16: 2026-05-10 | H16: 8 | I16: 63 | J16: 54 | K16: 6 | M16: 95 | Q16: LiveMine
B17: 2026-05-11 | H17: 8 | I17: 59 | J17: 54 | K17: 9 | M17: 145 | Q17: LiveMine
B18: 2026-05-12 | H18: 4 | I18: 82 | J18: 15 | K18: 12 | M18: 78 | Q18: LiveMine
... B128: 2026-08-30 | H128: 4 | I128: 0 | J128: 0 | K128: 0 | M128: 84 | Q128: LiveMine

Sheet Daily_Tracker
B2: DAILY TRACKER
B3: Reads the Daily Log. Compares what is happening now against the May to July baseline.
B4: The tracker measures material installed, not material issued. See the Dashboard for why those differ.
B6: 1 BASELINE, MEASURED MAY TO JULY 2026
B7: Measure | C7: Unit | E7: Mean | F7: Standard deviation | G7: Lower limit | H7: Upper limit | J7: Basis
B8: Bolts installed per metre | C8: bolts/m | E8: 15.928893 | F8: 1.6231404 | G8: =E8-2*F8 -> 12.682612 | H8: =E8+2*F8 -> 19.175174 | K8: May to July figures, all bolt types
B9: Mesh sheets per metre | C9: sheets/m | E9: 1.6762424 | F9: 0.3876192 | G9: =E9-2*F9 -> 0.90100397 | H9: =E9+2*F9 -> 2.4514808 | K9: June and July only, May count is unreliable
B10: Advance rate | C10: m/day | E10: 10.732376 | F10: 2.3121894 | G10: =E10-2*F10 -> 6.1079969 | H10: =E10+2*F10 -> 15.356754 | K10: Survey metres divided by days in period
B12: See Notes sheet, note 24.
B14: 2 RUNNING TOTALS FROM THE DAILY LOG
B15: Measure | C15: Unit | E15: Value | K15: Against baseline
B16: Shifts logged | C16: shifts | E16: =COUNT(Daily_Log!$H$8:$H$188) -> 121
B17: Metres advanced | C17: m | E17: =SUM(Daily_Log!$H$8:$H$188) -> 1350.2
B18: MD bolts installed | C18: units | E18: =SUM(Daily_Log!$I$8:$I$188) -> 12490
B19: Split sets installed | C19: units | E19: =SUM(Daily_Log!$J$8:$J$188) -> 6040
B20: Mesh sheets installed | C20: units | E20: =SUM(Daily_Log!$K$8:$K$188) -> 1986
B21: Items returned serviceable | C21: units | E21: =SUM(Daily_Log!$P$8:$P$188) -> 0
B22: Bolts per metre, actual | C22: per m | E22: =IF(E17=0,0,(E18+E19)/E17) -> 13.723893 | J22: =IF(E22=0,"no data yet",IF(E22>H8,"Above the upper limit",IF(E22<G8,"Below the lower limit","Within the normal range"))) -> Within the normal range
B23: Mesh sheets per metre, actual | C23: per m | E23: =IF(E17=0,0,(E20)/E17) -> 1.4708932 | J23: =IF(E23=0,"no data yet",IF(E23>H9,"Above the upper limit",IF(E23<G9,"Below the lower limit","Within the normal range"))) -> Within the normal range
B26: 3 BY DAY
B27: Date | C27: Shifts | E27: Metres advanced | F27: MD bolts | G27: Split sets | H27: Mesh sheets | K27: Bolts per metre
C28: =IF($B28="","",COUNTIFS(Daily_Log!$B$8:$B$188,$B28)) | E28: =IF($B28="","",SUMIFS(Daily_Log!$H$8:$H$188,Daily_Log!$B$8:$B$188,$B28)) | F28: =IF($B28="","",SUMIFS(Daily_Log!$I$8:$I$188,Daily_Log!$B$8:$B$188,$B28)) | G28: =IF($B28="","",SUMIFS(Daily_Log!$J$8:$J$188,Daily_Log!$B$8:$B$188,$B28)) | H28: =IF($B28="","",SUMIFS(Daily_Log!$K$8:$K$188,Daily_Log!$B$8:$B$188,$B28)) | J28: =IF(OR($B28="",E28=0),"",(F28+G28)/E28)
C29: =IF($B29="","",COUNTIFS(Daily_Log!$B$8:$B$188,$B29)) | E29: =IF($B29="","",SUMIFS(Daily_Log!$H$8:$H$188,Daily_Log!$B$8:$B$188,$B29)) | F29: =IF($B29="","",SUMIFS(Daily_Log!$I$8:$I$188,Daily_Log!$B$8:$B$188,$B29)) | G29: =IF($B29="","",SUMIFS(Daily_Log!$J$8:$J$188,Daily_Log!$B$8:$B$188,$B29)) | H29: =IF($B29="","",SUMIFS(Daily_Log!$K$8:$K$188,Daily_Log!$B$8:$B$188,$B29)) | J29: =IF(OR($B29="",E29=0),"",(F29+G29)/E29)
C30: =IF($B30="","",COUNTIFS(Daily_Log!$B$8:$B$188,$B30)) | E30: =IF($B30="","",SUMIFS(Daily_Log!$H$8:$H$188,Daily_Log!$B$8:$B$188,$B30)) | F30: =IF($B30="","",SUMIFS(Daily_Log!$I$8:$I$188,Daily_Log!$B$8:$B$188,$B30)) | G30: =IF($B30="","",SUMIFS(Daily_Log!$J$8:$J$188,Daily_Log!$B$8:$B$188,$B30)) | H30: =IF($B30="","",SUMIFS(Daily_Log!$K$8:$K$188,Daily_Log!$B$8:$B$188,$B30)) | J30: =IF(OR($B30="",E30=0),"",(F30+G30)/E30)
C31: =IF($B31="","",COUNTIFS(Daily_Log!$B$8:$B$188,$B31)) | E31: =IF($B31="","",SUMIFS(Daily_Log!$H$8:$H$188,Daily_Log!$B$8:$B$188,$B31)) | F31: =IF($B31="","",SUMIFS(Daily_Log!$I$8:$I$188,Daily_Log!$B$8:$B$188,$B31)) | G31: =IF($B31="","",SUMIFS(Daily_Log!$J$8:$J$188,Daily_Log!$B$8:$B$188,$B31)) | H31: =IF($B31="","",SUMIFS(Daily_Log!$K$8:$K$188,Daily_Log!$B$8:$B$188,$B31)) | J31: =IF(OR($B31="",E31=0),"",(F31+G31)/E31)
C32: =IF($B32="","",COUNTIFS(Daily_Log!$B$8:$B$188,$B32)) | E32: =IF($B32="","",SUMIFS(Daily_Log!$H$8:$H$188,Daily_Log!$B$8:$B$188,$B32)) | F32: =IF($B32="","",SUMIFS(Daily_Log!$I$8:$I$188,Daily_Log!$B$8:$B$188,$B32)) | G32: =IF($B32="","",SUMIFS(Daily_Log!$J$8:$J$188,Daily_Log!$B$8:$B$188,$B32)) | H32: =IF($B32="","",SUMIFS(Daily_Log!$K$8:$K$188,Daily_Log!$B$8:$B$188,$B32)) | J32: =IF(OR($B32="",E32=0),"",(F32+G32)/E32)
C33: =IF($B33="","",COUNTIFS(Daily_Log!$B$8:$B$188,$B33)) | E33: =IF($B33="","",SUMIFS(Daily_Log!$H$8:$H$188,Daily_Log!$B$8:$B$188,$B33)) | F33: =IF($B33="","",SUMIFS(Daily_Log!$I$8:$I$188,Daily_Log!$B$8:$B$188,$B33)) | G33: =IF($B33="","",SUMIFS(Daily_Log!$J$8:$J$188,Daily_Log!$B$8:$B$188,$B33)) | H33: =IF($B33="","",SUMIFS(Daily_Log!$K$8:$K$188,Daily_Log!$B$8:$B$188,$B33)) | J33: =IF(OR($B33="",E33=0),"",(F33+G33)/E33)
C34: =IF($B34="","",COUNTIFS(Daily_Log!$B$8:$B$188,$B34)) | E34: =IF($B34="","",SUMIFS(Daily_Log!$H$8:$H$188,Daily_Log!$B$8:$B$188,$B34)) | F34: =IF($B34="","",SUMIFS(Daily_Log!$I$8:$I$188,Daily_Log!$B$8:$B$188,$B34)) | G34: =IF($B34="","",SUMIFS(Daily_Log!$J$8:$J$188,Daily_Log!$B$8:$B$188,$B34)) | H34: =IF($B34="","",SUMIFS(Daily_Log!$K$8:$K$188,Daily_Log!$B$8:$B$188,$B34)) | J34: =IF(OR($B34="",E34=0),"",(F34+G34)/E34)
C35: =IF($B35="","",COUNTIFS(Daily_Log!$B$8:$B$188,$B35)) | E35: =IF($B35="","",SUMIFS(Daily_Log!$H$8:$H$188,Daily_Log!$B$8:$B$188,$B35)) | F35: =IF($B35="","",SUMIFS(Daily_Log!$I$8:$I$188,Daily_Log!$B$8:$B$188,$B35)) | G35: =IF($B35="","",SUMIFS(Daily_Log!$J$8:$J$188,Daily_Log!$B$8:$B$188,$B35)) | H35: =IF($B35="","",SUMIFS(Daily_Log!$K$8:$K$188,Daily_Log!$B$8:$B$188,$B35)) | J35: =IF(OR($B35="",E35=0),"",(F35+G35)/E35)
C36: =IF($B36="","",COUNTIFS(Daily_Log!$B$8:$B$188,$B36)) | E36: =IF($B36="","",SUMIFS(Daily_Log!$H$8:$H$188,Daily_Log!$B$8:$B$188,$B36)) | F36: =IF($B36="","",SUMIFS(Daily_Log!$I$8:$I$188,Daily_Log!$B$8:$B$188,$B36)) | G36: =IF($B36="","",SUMIFS(Daily_Log!$J$8:$J$188,Daily_Log!$B$8:$B$188,$B36)) | H36: =IF($B36="","",SUMIFS(Daily_Log!$K$8:$K$188,Daily_Log!$B$8:$B$188,$B36)) | J36: =IF(OR($B36="",E36=0),"",(F36+G36)/E36)
C37: =IF($B37="","",COUNTIFS(Daily_Log!$B$8:$B$188,$B37)) | E37: =IF($B37="","",SUMIFS(Daily_Log!$H$8:$H$188,Daily_Log!$B$8:$B$188,$B37)) | F37: =IF($B37="","",SUMIFS(Daily_Log!$I$8:$I$188,Daily_Log!$B$8:$B$188,$B37)) | G37: =IF($B37="","",SUMIFS(Daily_Log!$J$8:$J$188,Daily_Log!$B$8:$B$188,$B37)) | H37: =IF($B37="","",SUMIFS(Daily_Log!$K$8:$K$188,Daily_Log!$B$8:$B$188,$B37)) | J37: =IF(OR($B37="",E37=0),"",(F37+G37)/E37)
C38: =IF($B38="","",COUNTIFS(Daily_Log!$B$8:$B$188,$B38)) | E38: =IF($B38="","",SUMIFS(Daily_Log!$H$8:$H$188,Daily_Log!$B$8:$B$188,$B38)) | F38: =IF($B38="","",SUMIFS(Daily_Log!$I$8:$I$188,Daily_Log!$B$8:$B$188,$B38)) | G38: =IF($B38="","",SUMIFS(Daily_Log!$J$8:$J$188,Daily_Log!$B$8:$B$188,$B38)) | H38: =IF($B38="","",SUMIFS(Daily_Log!$K$8:$K$188,Daily_Log!$B$8:$B$188,$B38)) | J38: =IF(OR($B38="",E38=0),"",(F38+G38)/E38)
C39: =IF($B39="","",COUNTIFS(Daily_Log!$B$8:$B$188,$B39)) | E39: =IF($B39="","",SUMIFS(Daily_Log!$H$8:$H$188,Daily_Log!$B$8:$B$188,$B39)) | F39: =IF($B39="","",SUMIFS(Daily_Log!$I$8:$I$188,Daily_Log!$B$8:$B$188,$B39)) | G39: =IF($B39="","",SUMIFS(Daily_Log!$J$8:$J$188,Daily_Log!$B$8:$B$188,$B39)) | H39: =IF($B39="","",SUMIFS(Daily_Log!$K$8:$K$188,Daily_Log!$B$8:$B$188,$B39)) | J39: =IF(OR($B39="",E39=0),"",(F39+G39)/E39)
... C67: =IF($B67="","",COUNTIFS(Daily_Log!$B$8:$B$188,$B67)) | E67: =IF($B67="","",SUMIFS(Daily_Log!$H$8:$H$188,Daily_Log!$B$8:$B$188,$B67)) | F67: =IF($B67="","",SUMIFS(Daily_Log!$I$8:$I$188,Daily_Log!$B$8:$B$188,$B67)) | G67: =IF($B67="","",SUMIFS(Daily_Log!$J$8:$J$188,Daily_Log!$B$8:$B$188,$B67)) | H67: =IF($B67="","",SUMIFS(Daily_Log!$K$8:$K$188,Daily_Log!$B$8:$B$188,$B67)) | J67: =IF(OR($B67="",E67=0),"",(F67+G67)/E67)
B69: Type a date in the first column and the row fills itself from the Daily Log.

Sheet Anomalies
B2: DATA QUERIES AND ITEMS FOR CONFIRMATION
B3: Queries raised against the source records during the analysis, with the effect of each on the result.
B6: No. | C6: Item | E6: Observation | G6: Effect on the result | H6: Status | J6: Action required
B7: 1 | C7: May mesh count | E7: The May stock count says 2,291 sheets. LiveMine says 396, the issue register 200, and the design 1.5 per metre. June, July and August all sit between 1.3 and 2.1 per metre; May would need 8.5. | G7: 1,895 sheets, US$156,310 of May cost | H7: Resolved, the count is wrong | J7: Recount, or accept the LiveMine figure of 396 which three records support. Worked through on the May_Question sheet.
B8: 2 | C8: Support standard read off the drawings | E8: The GSS01 and GSS02 drawings give 33 and 15 MD bolts per cut, 0 and 18 split sets of 2.4 m, 11 stubby split sets, and 6 mesh sheets. Earlier design figures used in this model were not taken from the drawings. | G8: Changes every design variance in the model | H8: Resolved | J8: Design quantities now read directly off the two approved drawings, split by bolt type.
B9: 3 | C9: Stubby split sets below the drawing quantity | E9: Both drawings call for 11 stubby 0.9 m split sets per cut. Consumption runs at 0.0 to 0.7 per metre against a drawing quantity of 2.75. The 0.9 m x 47 mm friction bolt, which has no line on either drawing, runs at 1.13 per metre. | G9: 75 to 100 per cent below, every month | H9: Open, for ground control | J9: Ask ground control and the shift bosses why the stubby is not reaching the face, and whether the 47 mm 0.9 m bolt is being used in its place.
B10: 4 | C10: Long bolts above the drawing quantity | E10: MD bolts run 37 to 102 per cent above and 2.4 m split sets 20 to 113 per cent above. Note that the drawings state a MINIMUM quantity per cut, so installing above it is compliance rather than over consumption. | G10: Long bolt excess is 2.55 times the stubby shortfall, so substitution explains at most 39 per cent of it | H10: Open, for ground control | J10: Confirm whether the extra support was required by ground conditions. Quantity of ground support is a geotechnical decision, not a cost decision.
B11: 5 | C11: Cut length assumption | E11: Design per metre is the quantity per cut divided by the cut length. The 4.0 m cut is an entered value, not a measured one. | G11: The MD bolt variance falls from 72 to 29 per cent between a 4.0 m and a 3.0 m cut | H11: Open | J11: Measure the achieved cut length from the survey record. Until then quote the range on Plan_vs_Actual section 6, not the single figure.
B12: 6 | C12: Three drilling prices | E12: Shank T45 at 5,568.55 against 308.10 for the T38 equivalent. Coupling T45/T38 at 1,925.47 against 69.96. Boring centraliser 41 mm at 1,884.83 against 61.09 for the same part under a second supplier code. | G12: 80 per cent of the drilling bill; the drilling unit cost ranges from US$717 to US$140 per metre | H12: Blocking | J12: Operations manager confirms whether these are per each, per box, or a currency error.
B13: 7 | C13: August LiveMine inventory not supplied | E13: The August extract contains the Jumbo PLOD but no inventory sheet, so August has no measured installation record. | G13: August cannot be triangulated and its portal split falls back to metres | H13: Open | J13: Request the August inventory extract from LiveMine.
B14: 8 | C14: July closing against August opening | E14: Six items show a different closing count at the end of July from the opening count at the start of August, the largest being 484 MD bolts. | G14: About 1 per cent of the period's bolts | H14: Open, small | J14: Confirm whether a recount or an unbooked issue took place between the two counts.
B15: 9 | C15: Survey metres against PLOD metres | E15: The survey claim and the LiveMine PLOD disagree on metres advanced. August is the widest, at 391.0 surveyed against 366.1 recorded. | G15: Up to 6 per cent in a single month | H15: Open, small | J15: Survey remains the authority for metres in this model. Confirm the PLOD shortfall is unrecorded shifts.
B16: 10 | C16: Friction bolt 39 x 900, July | E16: Closing count 3,380 against opening 3,123 with no receipt booked. Stock grew without a delivery, so consumption computes to a negative 257. | G16: One item, one month, held at zero | H16: Open, small | J16: Store confirms the unrecorded receipt.
B17: 11 | C17: Portal and ground class confounded | E17: The Northern Portal is driven entirely in GSS_02 and GSS_03 ground and the Southern Portal entirely in GSS_01, in all four months. | G17: The two effects cannot be separated | H17: Limitation | J17: Note as a limitation of the study design. No further data from this period would resolve it.
B18: 12 | C18: Stocktake and survey dates | E18: Survey months run from the 29th to the 28th. Stock counts run to calendar month end. | G18: Two to three days of consumption in the wrong month; no effect on period totals | H18: Agreed fix | J18: Align the stocktake date with the survey cut off.
... B21: 15 | C21: Four locations still unassigned | E21: PMP_STN01 and Navachab carry no level. DSP_O6 and DSP_07 match a DSP heading in both portals. | G21: Held out of the portal split, included in the mine total | H21: Open, small | J21: One question to survey on which decline each belongs to.

Sheet Data_Quality
B2: DATA QUALITY AND LIMITATIONS
B3: Issues found in the source data and what is needed to resolve each one.
B6: Severity | C6: Affected data | E6: Issue and effect | F6: Action required
B7: Critical | C7: Drilling consumable prices | E7: The unit cost file covers ground support only. No price exists for any bit, rod, shank or coupling. Drilling cost per metre shows x. Consumption is measured in full. | F7: Obtain the Sandvik, DSI and Maspro price list. Enter it on C_Face_Drilling.
B8: Critical | C8: Fixed labour and machine cost | E8: No labour or machine cost, and no shift count, appears in any supplied file. Equation 3 and the advance scenarios show y. | F8: Obtain the fixed cost schedule and the shift count per month.
B9: Critical | C9: Consumption not recorded by heading | E9: The stocktake is one count for the whole store. The issue register records only North Portal or South Portal. Cost per heading cannot be calculated. | F9: Code stores issues to a heading. This is what the field recording sheets capture.
B10: High | C10: MS_1040_ACC, May 2026 | E10: Southern prefix but Northern level number. 27.178 m affected. May is therefore excluded from the portal analysis. | F10: Ask survey which side the 1040 access was driven from in May 2026.
B11: High | C11: May 2026 stock counts | E11: The two May half month counts do not chain. 26 items disagree and 11 receipts appear twice. May mesh shows 8.47 sheets per metre against 1.29 in June, which is not physically achievable. | F11: Confirm the 15 May count with stores. Treat May as provisional.
B12: High | C12: Friction bolt 39 x 900, July | E12: Closing count exceeds opening plus receipts, giving minus 257 units. Held at zero in every calculation. | F12: Locate the unrecorded receipt or recount.
B13: High | C13: Ground support standard changed | E13: GSS_03 is absent in May and June, then covers 217 of 398 metres in July. This drives cost per metre directly. | F13: Confirm with the geotechnician whether ground or classification changed.
B14: High | C14: Design support quantities | E14: The GSS design drawings are not among the supplied files, so over consumption cannot be proved. | F14: Obtain the GSS_01, GSS_02 and GSS_03 drawings.
B15: Medium | C15: Bolts per metre look high | E15: 16.9 bolts per metre in July against an expected 9 to 12 for this profile. | F15: Compare against the design standard once the drawings are obtained.
B16: Medium | C16: Heading naming across months | E16: May uses a different naming convention from June and July, so no continuous heading series can be built. | F16: Obtain the survey heading register.
B17: Medium | C17: Reporting periods differ | E17: Survey months run 29th to 28th. Stock counts run to calendar month end. | F17: Align the stocktake date with the survey cut off.
... B21: Low | C21: Barrel and wedge anchors | E21: Consumed in all three months but no unit price is available. | F21: Request the price from the supplier.

Sheet How_to_Read
B2: HOW TO READ THIS WORKBOOK
B3: What each sheet contains, and what the symbols and formats mean.
B6: SYMBOLS AND FORMATS
B7: Symbol | C7: Meaning
B8: x | C8: No unit price for this item exists in the source data. It is not zero and is never treated as zero.
B9: y | C9: An input that has not yet been collected. It is not zero and is never treated as zero.
B10: - | C10: The cost is already carried by another line. Repeating it here would double count.
B11: Negative number | C11: Shown with a minus sign. In the consumption sheets it means the closing stock count was higher than opening stock plus recorded receipts, which is a counting or receipting error, not negative usage.
B12: Blue figures | C12: Entered directly from a source document.
B13: Green figures | C13: Drawn from another sheet in this workbook.
B14: Black figures | C14: Calculated on this sheet.
B15: Shaded cells | C15: Awaiting data. Every one is listed on the Data_Quality sheet.
B17: WHAT EACH SHEET CONTAINS
B18: Sheet | C18: Contents
B19: Equations | C19: Every equation used, with each symbol defined and the sheet it is calculated on.
B20: Inputs | C20: Unit costs, the exchange rate, the ground support design quantities and the drilling geometry. Everything the model needs that is not consumption or metres.
B21: Advance | C21: Survey advance exactly as recorded, then the monthly totals and advance rates.
B22: Consumption_PL | C22: Consumption measured by physical stock count: opening plus received less closing.
B23: Consumption_Issues | C23: Consumption measured by the stores issue registers: the sum of quantities signed out.
B24: Consumption_Compare | C24: The two measures side by side, with the gap between them.
B25: A_Scaling to D_Cable_Bolting | C25: One sheet per development activity. Quantities consumed, units per metre, cost and cost per metre for every item.
B26: DRM | C26: Drilled metres. Bolt hole metres are calculated from bolts installed. Face metres need the drilling geometry inputs.
B27: Plan_vs_Actual | C27: Design quantities from the GSS drawings against actual consumption, by ground class.
B28: Unit_Cost | C28: Equations 1, 2 and 3, the advance rate scenarios, and the split of why unit cost moved.
B29: Portal_Analysis | C29: Results by heading and by portal, with the reconciliation checks.
... B32: Data_Quality | C32: Every problem found in the source data and what is needed to resolve it.
B34: CHECKING THE WORKBOOK BALANCES
B35: Check | C35: Where
B36: Heading metres equal portal metres, and Northern plus Southern equals the mine total | C36: Portal_Analysis, section 3. All four checks must read zero.
B37: The two causes of a change in unit cost sum to the total change | C37: Unit_Cost, last row of the final section. Must read zero.
B38: The cumulative share reaches exactly 100 per cent | C38: Pareto, final row.
B39: Ground class metres equal total metres | C39: Plan_vs_Actual, section 1 total.
